Workbook

Sheet info
A1: SCENARIO SIMULATION TOOL|MARITIME SHIPPING DECARBONISATION
E2: SHEET INDEX | O2: COLOUR CODING
A3: Title | B3: Pacific Shipping Tool | E3: Name | G3: Function | P3: Model Inputs, Output Dashboard
A4: Developers | B4: Edoardo Santagata | E4: 1 | F4: MAIN | G4: Central input/output dashboard containing all scenario parameters and aggregated annual results (2025–2050) for fuel consumption, emissions, costs, renewable energy capacity, and IMO GHG Fuel Standard compliance. | P4: Detailed Parametrisation, Assumptions
A5: Supervision | B5: Anna Bruce | E5: 2 | F5: current | G5: Baseline fleet fuel consumption summary by fuel type in energy (TJ) and mass (tonnes). | P5: Energy Consumption by Vessel Type
B6: Iain MacGill | E6: 3 | F6: consumptions per type | G6: Aggregated annual energy consumption by vessel type with assigned baseline fuel and operational measure eligibility flags. | P6: Raw Data
B7: Atul Raturi | E7: 4 | F7: dictionary | G7: Vessel-type-specific clean fuel suitability proportions and operational measure applicability assumptions.
A8: Affiliation | B8: University of New South Wales (UNSW) | E8: 5 | F8: efficiency | G8: Energy conversion ratios between fossil and clean fuels, and engine/system efficiency values used in renewable energy capacity calculations.
B9: Centre for Sustainable Development Reform (CSDR), UNSW | E9: 6 | F9: re | G9: Renewable energy generation capacity (MW by source) required to produce the clean fuels consumed under the modelled scenario.
B10: Collaboration on Energy and Environmental Markets (CEEM), UNSW | E10: 7 | F10: production | G10: Production pathway proportions for each clean fuel, used to derive weighted-average emission intensities and costs.
A11: Version | B11: 2 | E11: 8 | F11: emissions | G11: Well-to-wake CO₂-equivalent emission factors for fossil and clean fuels, disaggregated by production pathway.
A12: Release Date | B12: 46063 | E12: 9 | F12: cost | G12: Unit fuel costs ($/TJ) for fossil and clean fuels, disaggregated by production pathway.
E13: 10 | F13: raw | G13: Fleet input data with one row per vessel containing type classifications, physical characteristics, operational parameters, and energy consumption.
E14: 11-56 | F14: 1-23 + (RU) | G14: Per-vessel-type decarbonisation trajectory calculations applying logistic S-curve adoption functions for operational measures and clean fuel transitions. (RU) sheets incorporate IMO GHG Fuel Standard compliance with BT/DCT thresholds and Revenue Unit calculations.
A17: Correspondence
A18: Name | B18: Edoardo Santagata
A19: Affiliation | B19: Centre for Sustainable Development Reform (CSDR), UNSW
A20: email | B20: edoardo.santagata@unsw.edu.au
A22: Copyright Information
A23: Disclaimer | B23: THE SOFTWARE IS PROVIDED "AS IS", WITHOUT WARRANTY OF ANY KIND, EXPRESS OR IMPLIED, INCLUDING BUT NOT LIMITED TO THE WARRANTIES OF MERCHANTABILITY, FITNESS FOR A PARTICULAR PURPOSE AND NON-INFRINGEMENT. IN NO EVENT SHALL THE AUTHORS OR COPYRIGHT HOLDERS BE LIABLE FOR ANY CLAIM, DAMAGES OR OTHER LIABILITY, WHETHER IN AN ACTION OF CONTRACT, TORT OR OTHERWISE, ARISING FROM, OUT OF OR IN CONNECTION WITH THE SOFTWARE OR THE USE OR OTHER DEALINGS IN THE SOFTWARE. | E23: USER MANUAL
A24: Distribution License | B24: © Copyright 2026 University of New South Wales (UNSW) | E24: Overview This tool simulates decarbonisation scenarios for maritime shipping fleets over the period 2025–2050. It models the transition from fossil fuels to clean fuels and operational efficiency measures using logistic S-curve adoption functions, and calculates annual fuel consumption, well-to-wake emissions, costs, renewable energy capacity requirements, and IMO carbon levy (Revenue Unit) impacts for each scenario. The tool is designed to work with fleet data produced by Function 2 of this repository, but can also accept user-provided fleet data from any source, provided it follows the required format in the raw sheet. Getting Started Populate the raw sheet with your vessel fleet data. The sample data included contains one dummy vessel per considered vessel type for demonstration purposes. Replace this with your actual fleet data, ensuring the following columns are present: Flag, Vessel Name, Imo, Vessel Type - Generic, Draught, Built, Length, Capacity - Dwt, Average Speed, Vessel Type - Detailed, Capacity - Gt, Operational Days, Vessel Type - Simplified, Vessel Type - Contextual, Estimated DWT, Fuel Consumption, Fuel Type, Energy Consumption (TJ/year). If using output from shippinganalysis.py (Function 2), the format will already match. Review the consumptions per type sheet, which automatically aggregates energy consumption from raw by vessel type. Check that the Fuel Type assignment and operational measure eligibility flags (HULL, SLOW, SAIL) are appropriate for your fleet. These flags determine which measures are applied to each vessel type in the scenario simulation. Set scenario parameters in the MAIN sheet. The key user inputs are located in cells A1–D12: Annual Growth Rate (cell B1): Fleet-wide annual growth rate applied to energy consumption (default: 2.1%) Operational Measures (rows 4–6): For each measure (hull coating + propeller upgrades, slow steaming, sailing & hybrid), set the logistic adoption rate k, energy savings fraction, and inflection year t₀ Clean Fuels (row 8): Set the logistic adoption rate k and inflection year t₀ for clean fuel uptake Fuel Swaps (rows 11–12): Set adoption parameters for HFO→LFO and MDO→MGO fuel swaps (set k = 0 to disable)
B25: Permission is hereby granted, free of charge, to any person obtaining a copy of this software and associated documentation files (the "Software"), to deal in the Software without restriction, including without limitation the rights to use, copy, modify, merge, publish, distribute, sublicense, and/or sell copies of the Software, and to permit persons to whom the Software is furnished to do so, subject to the following conditions:
B26: The above copyright notice and this permission notice shall be included in all copies or substantial portions of the Software.
A27: Citation | B27: While this tool is published under the conditions of the open source MIT license by making sure that the code can be used, edited, and re-distributed by others, we require that the tool developers are acknowledged by using the following citation:
B28: Santagata, E. 2026. Planning Frameworks and Tools for Secure and Resilient Clean Energy Transitions in Pacific Island Countries and Territories. PhD Thesis, UNSW Sydney. DOI: https://doi.org/10.26190/unsworks/31988
E29: Review assumption sheets as needed. The dictionary, efficiency, production, emissions, cost, and re sheets contain detailed parametrisation that can be adjusted for different scenarios or regions. See sheet descriptions below. Read results from the MAIN sheet. The output dashboard (rows 14 onwards and columns G onwards) presents annual time series for: fuel consumption by type (TJ), fossil vs clean fuel totals, consumption by vessel type, well-to-wake emissions (tCO₂-e), operational costs, renewable energy capacity requirements (MW by source), and IMO GHG Fuel Standard compliance indicators (BT and DCT thresholds, Revenue Unit requirements). Scenario Design The tool supports both normative and exploratory scenario approaches: Normative scenarios: Work backwards from a target (e.g. IMO 2050 net-zero, IEA Net Zero) by calibrating k and t₀ parameters to meet the desired emissions trajectory Exploratory scenarios: Test "what if" assumptions by varying adoption rates, measure eligibility, or fuel suitability proportions Each numbered vessel type sheet (1–23) and its corresponding RU variant (1–23 RU) can be inspected to understand the per-type transition dynamics. The N sheets model the scenario without IMO carbon levy constraints; the N (RU) sheets model the same scenario under IMO GHG Fuel Standard compliance obligations. IMO GHG Fuel Standard (Revenue Units) The tool includes the IMO's proposed GHG Fuel Standard framework with two compliance thresholds: BT (Below Threshold): The lower bound carbon intensity target DCT (Deemed Compliance Threshold): The upper bound These thresholds tighten annually from 2028 to 2050 (columns BT and DCT in MAIN). Vessels that exceed the DCT must purchase Revenue Units (RUs). The N (RU) sheets calculate per-type compliance under this framework, and MAIN aggregates fleet-wide RU requirements, costs, and income.

Sheet MAIN
A1: Annual Growth Rate | B1: 0.021 | G1: Year | H1: HFO | I1: LFO | J1: MDO | K1: MGO | L1: LNG | M1: Hydrogen (Combustion) | N1: Hydrogen (Fuel Cells) | O1: Ammonia | P1: Methanol | Q1: bio-LNG | R1: bio-Ethanol | S1: HVO | T1: Synthetic Diesel | U1: Electricity (Battery) | V1: Fossil Fuels | W1: Clean Fuels | Y1: TJ elec | Z1: RE MW | AA1: Solar | AB1: Wind | AC1: Hydro | AD1: Geothermal | AE1: Biomass | AF1: ='consumptions per type'!A2 -> Passenger Vessel | AG1: ='consumptions per type'!A3 -> General Cargo | AH1: ='consumptions per type'!A4 -> Special Craft | AI1: ='consumptions per type'!A5 -> Supply Vessel | AJ1: ='consumptions per type'!A6 -> Passenger/Cargo Ship | AK1: ='consumptions per type'!A7 -> Container Ship | AL1: ='consumptions per type'!A8 -> Ro-Ro/Vehicles Carrier | AM1: ='consumptions per type'!A9 -> LNG Tanker | AN1: ='consumptions per type'!A10 -> Other Special Craft | AO1: ='consumptions per type'!A11 -> Oil/Chemical Tanker | AP1: ='consumptions per type'!A12 -> Reefer | AQ1: ='consumptions per type'!A13 -> Bulk Carrier | AR1: ='consumptions per type'!A14 -> LPG Tanker | AS1: ='consumptions per type'!A15 -> Ro-Ro/Passenger Vessel | AT1: ='consumptions per type'!A16 -> Crude Oil Tanker | AU1: ='consumptions per type'!A17 -> Oil Products Tanker | AV1: ='consumptions per type'!A18 -> Heavy Load Carrier | AW1: ='consumptions per type'!A19 -> Landing Craft | AX1: ='consumptions per type'!A20 -> High Speed Craft | AY1: ='consumptions per type'!A21 -> Other Cargo | AZ1: ='consumptions per type'!A22 -> Special Cargo | BA1: ='consumptions per type'!A23 -> Other Passenger | BB1: ='consumptions per type'!A24 -> Special Passenger Vessel | BC1: Effective HCP | BD1: Effective SS | BE1: Effective SH | BF1: Effective CF | BG1: Obliged under Rus | BH1: BT | BI1: DCT | BK1: HFO | BL1: LFO | BM1: MDO | BN1: MGO | BO1: LNG | BP1: Hydrogen (Combustion) | BQ1: Hydrogen (Fuel Cells) | BR1: Ammonia | BS1: Methanol | BT1: bio-LNG | BU1: bio-Ethanol | BV1: HVO | BW1: Synthetic Diesel | BX1: Electricity (Battery) | BY1: Fossil Fuels | BZ1: Clean Fuels | CB1: Emissions | CC1: HFO | CD1: LFO | CE1: MDO | CF1: MGO | CG1: LNG | CH1: Hydrogen (Combustion) | CI1: Hydrogen (Fuel Cells) | CJ1: Ammonia | CK1: Methanol | CL1: bio-LNG | CM1: bio-Ethanol | CN1: HVO | CO1: Synthetic Diesel | CP1: Electricity (Battery) | CQ1: Fossil Fuels | CR1: Clean Fuels | CS1: TOTAL EM | CT1: TOTAL EM f | CU1: BT factor diff | CV1: DCT factor diff | CW1: BT | CX1: DCT | CY1: RU req | CZ1: Cost | DA1: Zone | DB1: Ru gen | DC1: Income | DD1: Year | DE1: RU | DF1: Emissions | DH1: BCT | DI1: DCT | DJ1: belwo helper | DK1: between | DL1: above | DN1: RU Mt | DO1: Baseline en 93.3 | DQ1: HFO | DR1: LFO | DS1: MDO | DT1: MGO | DU1: LNG | DV1: HFO em | DW1: LFO em | DX1: MDO em | DY1: MGO em | DZ1: LNG em | EA1: EMISSIONS | EB1: RU Requirements | ED1: OP COSTS | EE1: HFO | EF1: LFO | EG1: MDO | EH1: MGO | EI1: LNG | EJ1: Hydrogen (Combustion) | EK1: Hydrogen (Fuel Cells) | EL1: Ammonia | EM1: Methanol | EN1: bio-LNG | EO1: bio-Ethanol | EP1: HVO | EQ1: Synthetic Diesel | ER1: Electricity (Battery)
G2: 2025 | H2: ='2'!AB8+'6'!AB8+'7'!AB8+'9'!AB8+'11'!AB8+'12'!AB8+'13'!AB8+'16'!AB8+'17'!AB8+'18'!AB8+'22'!AB8 -> 380.37773 | I2: ='1'!AB8+'2'!AC8+'5'!AB8+'6'!AC8+'7'!AC8+'9'!AC8+'11'!AC8+'12'!AC8+'13'!AC8+'15'!AB8+'16'!AC8+'17'!AC8+'18'!AC8+'19'!AB8+'22'!AC8 -> 213.57532 | K2: ='3'!AB8+'4'!AB8+'10'!AB8+'20'!AB8+'21'!AB8+'23'!AB8 -> 21.924534 | L2: ='8'!AB8+'14'!AB8 -> 202.51922 | M2: ='1'!AD8+'2'!AD8+'3'!AD8+'4'!AD8+'5'!AD8+'6'!AD8+'7'!AD8+'8'!AD8+'9'!AD8+'10'!AD8+'11'!AD8+'12'!AD8+'13'!AD8+'14'!AD8+'15'!AD8+'16'!AD8+'17'!AD8+'18'!AD8+'19'!AD8+'20'!AD8+'21'!AD8+'22'!AD8+'23'!AD8 -> 0 | N2: ='1'!AE8+'2'!AE8+'3'!AE8+'4'!AE8+'5'!AE8+'6'!AE8+'7'!AE8+'8'!AE8+'9'!AE8+'10'!AE8+'11'!AE8+'12'!AE8+'13'!AE8+'14'!AE8+'15'!AE8+'16'!AE8+'17'!AE8+'18'!AE8+'19'!AE8+'20'!AE8+'21'!AE8+'22'!AE8+'23'!AE8 -> 0 | O2: ='1'!AF8+'2'!AF8+'3'!AF8+'4'!AF8+'5'!AF8+'6'!AF8+'7'!AF8+'8'!AF8+'9'!AF8+'10'!AF8+'11'!AF8+'12'!AF8+'13'!AF8+'14'!AF8+'15'!AF8+'16'!AF8+'17'!AF8+'18'!AF8+'19'!AF8+'20'!AF8+'21'!AF8+'22'!AF8+'23'!AF8 -> 0 | P2: ='1'!AG8+'2'!AG8+'3'!AG8+'4'!AG8+'5'!AG8+'6'!AG8+'7'!AG8+'8'!AG8+'9'!AG8+'10'!AG8+'11'!AG8+'12'!AG8+'13'!AG8+'14'!AG8+'15'!AG8+'16'!AG8+'17'!AG8+'18'!AG8+'19'!AG8+'20'!AG8+'21'!AG8+'22'!AG8+'23'!AG8 -> 0 | Q2: ='1'!AH8+'2'!AH8+'3'!AH8+'4'!AH8+'5'!AH8+'6'!AH8+'7'!AH8+'8'!AH8+'9'!AH8+'10'!AH8+'11'!AH8+'12'!AH8+'13'!AH8+'14'!AH8+'15'!AH8+'16'!AH8+'17'!AH8+'18'!AH8+'19'!AH8+'20'!AH8+'21'!AH8+'22'!AH8+'23'!AH8 -> 0 | R2: ='1'!AI8+'2'!AI8+'3'!AI8+'4'!AI8+'5'!AI8+'6'!AI8+'7'!AI8+'8'!AI8+'9'!AI8+'10'!AI8+'11'!AI8+'12'!AI8+'13'!AI8+'14'!AI8+'15'!AI8+'16'!AI8+'17'!AI8+'18'!AI8+'19'!AI8+'20'!AI8+'21'!AI8+'22'!AI8+'23'!AI8 -> 0 | S2: ='1'!AJ8+'2'!AJ8+'3'!AJ8+'4'!AJ8+'5'!AJ8+'6'!AJ8+'7'!AJ8+'8'!AJ8+'9'!AJ8+'10'!AJ8+'11'!AJ8+'12'!AJ8+'13'!AJ8+'14'!AJ8+'15'!AJ8+'16'!AJ8+'17'!AJ8+'18'!AJ8+'19'!AJ8+'20'!AJ8+'21'!AJ8+'22'!AJ8+'23'!AJ8 -> 0 | T2: ='1'!AK8+'2'!AK8+'3'!AK8+'4'!AK8+'5'!AK8+'6'!AK8+'7'!AK8+'8'!AK8+'9'!AK8+'10'!AK8+'11'!AK8+'12'!AK8+'13'!AK8+'14'!AK8+'15'!AK8+'16'!AK8+'17'!AK8+'18'!AK8+'19'!AK8+'20'!AK8+'21'!AK8+'22'!AK8+'23'!AK8 -> 0 | U2: ='1'!AL8+'2'!AL8+'3'!AL8+'4'!AL8+'5'!AL8+'6'!AL8+'7'!AL8+'8'!AL8+'9'!AL8+'10'!AL8+'11'!AL8+'12'!AL8+'13'!AL8+'14'!AL8+'15'!AL8+'16'!AL8+'17'!AL8+'18'!AL8+'19'!AL8+'20'!AL8+'21'!AL8+'22'!AL8+'23'!AL8 -> 0 | V2: =SUM(H2:L2) -> 818.3968 | W2: =SUM(M2:U2) -> 0 | X2: =AVERAGE(X4:X27) -> 0.3025839 | AF2: =SUM('1'!AD8:AL8)+'1'!AA8 -> 130.67116 | AG2: =SUM('2'!AD8:AL8)+'2'!AA8 -> 2.4794096 | AH2: =SUM('3'!AD8:AL8)+'3'!AA8 -> 10.604034 | AI2: =SUM('4'!AD8:AL8)+'4'!AA8 -> 0.78928445 | AJ2: =SUM('5'!AD8:AL8)+'5'!AA8 -> 4.875626 | AK2: =SUM('6'!AD8:AL8)+'6'!AA8 -> 125.99565 | AL2: =SUM('7'!AD8:AL8)+'7'!AA8 -> 110.74819 | AM2: =SUM('8'!AD8:AL8)+'8'!AA8 -> 198.59706 | AN2: =SUM('9'!AD8:AL8)+'9'!AA8 -> 60.877048 | AO2: =SUM('10'!AD8:AL8)+'10'!AA8 -> 4.4448391 | AP2: =SUM('11'!AD8:AL8)+'11'!AA8 -> 5.662729 | AQ2: =SUM('12'!AD8:AL8)+'12'!AA8 -> 1.739707 | AR2: =SUM('13'!AD8:AL8)+'13'!AA8 -> 5.06182 | AS2: =SUM('14'!AD8:AL8)+'14'!AA8 -> 3.9221535 | AT2: =SUM('15'!AD8:AL8)+'15'!AA8 -> 54.087615 | AU2: =SUM('16'!AD8:AL8)+'16'!AA8 -> 21.543493 | AV2: =SUM('17'!AD8:AL8)+'17'!AA8 -> 36.664778 | AW2: =SUM('18'!AD8:AL8)+'18'!AA8 -> 9.1562725 | AX2: =SUM('19'!AD8:AL8)+'19'!AA8 -> 23.940915 | AY2: =SUM('20'!AD8:AL8)+'20'!AA8 -> 1.5071681 | AZ2: =SUM('21'!AD8:AL8)+'21'!AA8 -> 0.13750602 | BA2: =SUM('22'!AD8:AL8)+'22'!AA8 -> 0.4486375 | BB2: =SUM('23'!AD8:AL8)+'23'!AA8 -> 4.4417023 | BG2: 2025 | BH2: 0 | BI2: 0 | BK2: ='2 (RU)'!AB8+'6 (RU)'!AB8+'7 (RU)'!AB8+'9 (RU)'!AB8+'11 (RU)'!AB8+'12 (RU)'!AB8+'13 (RU)'!AB8+'16 (RU)'!AB8+'17 (RU)'!AB8+'18 (RU)'!AB8+'22 (RU)'!AB8 -> #DIV/0! | BL2: ='1 (RU)'!AB8+'2 (RU)'!AC8+'5 (RU)'!AB8+'6 (RU)'!AC8+'7 (RU)'!AC8+'9 (RU)'!AC8+'11 (RU)'!AC8+'12 (RU)'!AC8+'13 (RU)'!AC8+'15 (RU)'!AB8+'16 (RU)'!AC8+'17 (RU)'!AC8+'18 (RU)'!AC8+'19 (RU)'!AB8+'22 (RU)'!AC8 -> #DIV/0! | BN2: ='3 (RU)'!AB8+'4 (RU)'!AB8+'10 (RU)'!AB8+'20 (RU)'!AB8+'21 (RU)'!AB8+'23 (RU)'!AB8 -> #DIV/0! | BO2: ='8 (RU)'!AB8+'14 (RU)'!AB8 -> #DIV/0! | BP2: ='1 (RU)'!AD8+'2 (RU)'!AD8+'3 (RU)'!AD8+'4 (RU)'!AD8+'5 (RU)'!AD8+'6 (RU)'!AD8+'7 (RU)'!AD8+'8 (RU)'!AD8+'9 (RU)'!AD8+'10 (RU)'!AD8+'11 (RU)'!AD8+'12 (RU)'!AD8+'13 (RU)'!AD8+'14 (RU)'!AD8+'15 (RU)'!AD8+'16 (RU)'!AD8+'17 (RU)'!AD8+'18 (RU)'!AD8+'19 (RU)'!AD8+'20 (RU)'!AD8+'21 (RU)'!AD8+'22 (RU)'!AD8+'23 (RU)'!AD8 -> #DIV/0! | BQ2: ='1 (RU)'!AE8+'2 (RU)'!AE8+'3 (RU)'!AE8+'4 (RU)'!AE8+'5 (RU)'!AE8+'6 (RU)'!AE8+'7 (RU)'!AE8+'8 (RU)'!AE8+'9 (RU)'!AE8+'10 (RU)'!AE8+'11 (RU)'!AE8+'12 (RU)'!AE8+'13 (RU)'!AE8+'14 (RU)'!AE8+'15 (RU)'!AE8+'16 (RU)'!AE8+'17 (RU)'!AE8+'18 (RU)'!AE8+'19 (RU)'!AE8+'20 (RU)'!AE8+'21 (RU)'!AE8+'22 (RU)'!AE8+'23 (RU)'!AE8 -> #DIV/0! | BR2: ='1 (RU)'!AF8+'2 (RU)'!AF8+'3 (RU)'!AF8+'4 (RU)'!AF8+'5 (RU)'!AF8+'6 (RU)'!AF8+'7 (RU)'!AF8+'8 (RU)'!AF8+'9 (RU)'!AF8+'10 (RU)'!AF8+'11 (RU)'!AF8+'12 (RU)'!AF8+'13 (RU)'!AF8+'14 (RU)'!AF8+'15 (RU)'!AF8+'16 (RU)'!AF8+'17 (RU)'!AF8+'18 (RU)'!AF8+'19 (RU)'!AF8+'20 (RU)'!AF8+'21 (RU)'!AF8+'22 (RU)'!AF8+'23 (RU)'!AF8 -> #DIV/0! | BS2: ='1 (RU)'!AG8+'2 (RU)'!AG8+'3 (RU)'!AG8+'4 (RU)'!AG8+'5 (RU)'!AG8+'6 (RU)'!AG8+'7 (RU)'!AG8+'8 (RU)'!AG8+'9 (RU)'!AG8+'10 (RU)'!AG8+'11 (RU)'!AG8+'12 (RU)'!AG8+'13 (RU)'!AG8+'14 (RU)'!AG8+'15 (RU)'!AG8+'16 (RU)'!AG8+'17 (RU)'!AG8+'18 (RU)'!AG8+'19 (RU)'!AG8+'20 (RU)'!AG8+'21 (RU)'!AG8+'22 (RU)'!AG8+'23 (RU)'!AG8 -> #DIV/0! | BT2: ='1 (RU)'!AH8+'2 (RU)'!AH8+'3 (RU)'!AH8+'4 (RU)'!AH8+'5 (RU)'!AH8+'6 (RU)'!AH8+'7 (RU)'!AH8+'8 (RU)'!AH8+'9 (RU)'!AH8+'10 (RU)'!AH8+'11 (RU)'!AH8+'12 (RU)'!AH8+'13 (RU)'!AH8+'14 (RU)'!AH8+'15 (RU)'!AH8+'16 (RU)'!AH8+'17 (RU)'!AH8+'18 (RU)'!AH8+'19 (RU)'!AH8+'20 (RU)'!AH8+'21 (RU)'!AH8+'22 (RU)'!AH8+'23 (RU)'!AH8 -> #DIV/0! | BU2: ='1 (RU)'!AI8+'2 (RU)'!AI8+'3 (RU)'!AI8+'4 (RU)'!AI8+'5 (RU)'!AI8+'6 (RU)'!AI8+'7 (RU)'!AI8+'8 (RU)'!AI8+'9 (RU)'!AI8+'10 (RU)'!AI8+'11 (RU)'!AI8+'12 (RU)'!AI8+'13 (RU)'!AI8+'14 (RU)'!AI8+'15 (RU)'!AI8+'16 (RU)'!AI8+'17 (RU)'!AI8+'18 (RU)'!AI8+'19 (RU)'!AI8+'20 (RU)'!AI8+'21 (RU)'!AI8+'22 (RU)'!AI8+'23 (RU)'!AI8 -> #DIV/0! | BV2: ='1 (RU)'!AJ8+'2 (RU)'!AJ8+'3 (RU)'!AJ8+'4 (RU)'!AJ8+'5 (RU)'!AJ8+'6 (RU)'!AJ8+'7 (RU)'!AJ8+'8 (RU)'!AJ8+'9 (RU)'!AJ8+'10 (RU)'!AJ8+'11 (RU)'!AJ8+'12 (RU)'!AJ8+'13 (RU)'!AJ8+'14 (RU)'!AJ8+'15 (RU)'!AJ8+'16 (RU)'!AJ8+'17 (RU)'!AJ8+'18 (RU)'!AJ8+'19 (RU)'!AJ8+'20 (RU)'!AJ8+'21 (RU)'!AJ8+'22 (RU)'!AJ8+'23 (RU)'!AJ8 -> #DIV/0! | BW2: ='1 (RU)'!AK8+'2 (RU)'!AK8+'3 (RU)'!AK8+'4 (RU)'!AK8+'5 (RU)'!AK8+'6 (RU)'!AK8+'7 (RU)'!AK8+'8 (RU)'!AK8+'9 (RU)'!AK8+'10 (RU)'!AK8+'11 (RU)'!AK8+'12 (RU)'!AK8+'13 (RU)'!AK8+'14 (RU)'!AK8+'15 (RU)'!AK8+'16 (RU)'!AK8+'17 (RU)'!AK8+'18 (RU)'!AK8+'19 (RU)'!AK8+'20 (RU)'!AK8+'21 (RU)'!AK8+'22 (RU)'!AK8+'23 (RU)'!AK8 -> #DIV/0! | BX2: ='1 (RU)'!AL8+'2 (RU)'!AL8+'3 (RU)'!AL8+'4 (RU)'!AL8+'5 (RU)'!AL8+'6 (RU)'!AL8+'7 (RU)'!AL8+'8 (RU)'!AL8+'9 (RU)'!AL8+'10 (RU)'!AL8+'11 (RU)'!AL8+'12 (RU)'!AL8+'13 (RU)'!AL8+'14 (RU)'!AL8+'15 (RU)'!AL8+'16 (RU)'!AL8+'17 (RU)'!AL8+'18 (RU)'!AL8+'19 (RU)'!AL8+'20 (RU)'!AL8+'21 (RU)'!AL8+'22 (RU)'!AL8+'23 (RU)'!AL8 -> #DIV/0! | BY2: =SUM(BK2:BO2) -> #DIV/0! | BZ2: =SUM(BP2:BX2) -> #DIV/0! | CC2: =VLOOKUP(CC$1,emissions!$A$2:$B$5,2,FALSE)*BK2 -> #DIV/0! | CD2: =VLOOKUP(CD$1,emissions!$A$2:$B$5,2,FALSE)*BL2 -> #DIV/0! | CF2: =VLOOKUP(CF$1,emissions!$A$2:$B$5,2,FALSE)*BN2 -> #DIV/0! | CG2: =VLOOKUP(CG$1,emissions!$A$2:$B$5,2,FALSE)*BO2 -> #DIV/0! | CH2: =BP2*(emissions!$D$3*production!$B$4+emissions!$D$4*production!$C$4+emissions!$D$5*production!$D$4+emissions!$D$6*production!$E$4) -> #DIV/0! | CI2: =BQ2*(emissions!$D$3*production!$B$4+emissions!$D$4*production!$C$4+emissions!$D$5*production!$D$4+emissions!$D$6*production!$E$4) -> #DIV/0! | CJ2: =BR2*(emissions!$D$8*production!$B$6+emissions!$D$9*production!$C$6+emissions!$D$10*production!$D$6) -> #DIV/0! | CK2: =BS2*(emissions!$D$12*production!$B$8+emissions!$D$13*production!$C$8+emissions!$D$14*production!$D$8) -> #DIV/0! | CL2: =BT2*(emissions!$D$16*production!$B$10+production!$C$10*emissions!$D$17) -> #DIV/0! | CM2: =BU2*(emissions!$D$19*production!$B$12+production!$C$12*emissions!$D$20+emissions!$D$21*production!$D$12) -> #DIV/0! | CN2: =BV2*(emissions!$D$23*production!$B$14+production!$C$14*emissions!$D$24+emissions!$D$25*production!$D$14) -> #DIV/0! | CO2: =BW2*(emissions!$D$27*production!$B$16+production!$C$16*emissions!$D$28+production!$D$16*emissions!$D$29) -> #DIV/0! | CP2: 0 | CS2: =SUM(CC2:CP2) -> #DIV/0! | CT2: =SUM(CC2:CP2)/SUM(BK2:BX2) -> #DIV/0! | CU2: =(CT2-CW2) -> #DIV/0! | CV2: =CT2-CX2 -> #DIV/0! | CW2: =93.3*(1-BH2) -> 93.3 | CX2: =93.3*(1-BI2) -> 93.3 | CY2: =IF(G2<2028,0,IF(CT2>=CW2,CU2,IF(AND(CT2<CW2,CT2>=CX2),CV2,0))*SUM(BK2:BX2)) -> 0 | CZ2: =IF(CT2>=CW2,380*CY2,IF(AND(CT2<CW2,CT2>=CX2),100*CY2,0)) -> #DIV/0! | DA2: =IF(G2<2028,"",IF(CT2>=CW2,"Red",IF(AND(CT2<CW2,CT2>=CX2),"Yellow","Green"))) | DB2: =IF(G2<2028,0,IF(CT2<CX2,-CV2*SUM(BK2:BX2),0)) -> 0 | DC2: =DB2*380 -> 0 | DD2: 2025 | DQ2: 18115 | DR2: 7213 | DT2: 602 | DU2: 2049 | DV2: =DQ2*VLOOKUP(DQ$1,emissions!$A$2:$B$5,2,FALSE) -> 2644790 | DW2: =DR2*VLOOKUP(DR$1,emissions!$A$2:$B$5,2,FALSE) -> 1053098 | DY2: =DT2*VLOOKUP(DT$1,emissions!$A$2:$B$5,2,FALSE) -> 87290 | DZ2: =DU2*VLOOKUP(DU$1,emissions!$A$2:$B$5,2,FALSE) -> 231537 | EA2: =SUM(DV2:DZ2) -> 4016715 | EB2: =1/(SUM(DQ2:DU2)/EA2) -> 143.56178 | ED2: =SUM(EE2:ER2) -> #DIV/0! | EE2: =cost!$B$2*BK2 -> #DIV/0! | EF2: =cost!$B$3*BL2 -> #DIV/0! | EH2: =cost!$B$4*BN2 -> #DIV/0! | EI2: =cost!$B$5*$BO$2 -> #DIV/0! | EJ2: =BP2*(cost!$D$3*production!$B$4+production!$C$4*cost!$D$4+cost!$D$5*production!$D$4+production!$E$4*cost!$D$6) -> #DIV/0! | EK2: =BQ2*(cost!$D$3*production!$B$4+production!$C$4*cost!$D$4+cost!$D$5*production!$D$4+production!$E$4*cost!$D$6) -> #DIV/0! | EL2: =BR2*(cost!$D$8*production!$B$6+cost!$D$9*production!$C$6+$D$10*production!$D$6) -> #DIV/0! | EM2: =BS2*(cost!$D$12*production!$B$8+cost!$D$13*production!$C$8+cost!$D$14*production!$D$8) -> #DIV/0! | EN2: =BT2*(cost!$D$16*production!$B$10+production!$C$10*cost!$D$17) -> #DIV/0! | EO2: =BU2*(cost!$D$19*production!$B$12+production!$C$12*cost!$D$20+cost!$D$21*production!$D$12) -> #DIV/0! | EP2: =BV2*(cost!$D$23*production!$B$14+production!$C$14*cost!$D$24+cost!$D$25*production!$D$14) -> #DIV/0! | EQ2: =BW2*(cost!$D$27*production!$B$16+production!$C$16*cost!$D$28+cost!$D$29*production!$D$16) -> #DIV/0! | ER2: =BX2*(re!$H$10*re!$C$10+re!$H$11*re!$C$11+re!$H$12*re!$C$12+re!$H$13*re!$C$13+re!$H$14*re!$C$14) -> #DIV/0!
A3: Operational Measures | B3: k | C3: Savings | D3: t0 | G3: 2026 | H3: ='2'!AB9+'6'!AB9+'7'!AB9+'9'!AB9+'11'!AB9+'12'!AB9+'13'!AB9+'16'!AB9+'17'!AB9+'18'!AB9+'22'!AB9 -> 365.85749 | I3: ='1'!AB9+'2'!AC9+'5'!AB9+'6'!AC9+'7'!AC9+'9'!AC9+'11'!AC9+'12'!AC9+'13'!AC9+'15'!AB9+'16'!AC9+'17'!AC9+'18'!AC9+'19'!AB9+'22'!AC9 -> 235.04122 | K3: ='3'!AB9+'4'!AB9+'10'!AB9+'20'!AB9+'21'!AB9+'23'!AB9 -> 22.230214 | L3: ='8'!AB9+'14'!AB9 -> 205.29775 | M3: ='1'!AD9+'2'!AD9+'3'!AD9+'4'!AD9+'5'!AD9+'6'!AD9+'7'!AD9+'8'!AD9+'9'!AD9+'10'!AD9+'11'!AD9+'12'!AD9+'13'!AD9+'14'!AD9+'15'!AD9+'16'!AD9+'17'!AD9+'18'!AD9+'19'!AD9+'20'!AD9+'21'!AD9+'22'!AD9+'23'!AD9 -> 0.91768432 | N3: ='1'!AE9+'2'!AE9+'3'!AE9+'4'!AE9+'5'!AE9+'6'!AE9+'7'!AE9+'8'!AE9+'9'!AE9+'10'!AE9+'11'!AE9+'12'!AE9+'13'!AE9+'14'!AE9+'15'!AE9+'16'!AE9+'17'!AE9+'18'!AE9+'19'!AE9+'20'!AE9+'21'!AE9+'22'!AE9+'23'!AE9 -> 0.054420464 | O3: ='1'!AF9+'2'!AF9+'3'!AF9+'4'!AF9+'5'!AF9+'6'!AF9+'7'!AF9+'8'!AF9+'9'!AF9+'10'!AF9+'11'!AF9+'12'!AF9+'13'!AF9+'14'!AF9+'15'!AF9+'16'!AF9+'17'!AF9+'18'!AF9+'19'!AF9+'20'!AF9+'21'!AF9+'22'!AF9+'23'!AF9 -> 1.7588069 | P3: ='1'!AG9+'2'!AG9+'3'!AG9+'4'!AG9+'5'!AG9+'6'!AG9+'7'!AG9+'8'!AG9+'9'!AG9+'10'!AG9+'11'!AG9+'12'!AG9+'13'!AG9+'14'!AG9+'15'!AG9+'16'!AG9+'17'!AG9+'18'!AG9+'19'!AG9+'20'!AG9+'21'!AG9+'22'!AG9+'23'!AG9 -> 1.5991443 | Q3: ='1'!AH9+'2'!AH9+'3'!AH9+'4'!AH9+'5'!AH9+'6'!AH9+'7'!AH9+'8'!AH9+'9'!AH9+'10'!AH9+'11'!AH9+'12'!AH9+'13'!AH9+'14'!AH9+'15'!AH9+'16'!AH9+'17'!AH9+'18'!AH9+'19'!AH9+'20'!AH9+'21'!AH9+'22'!AH9+'23'!AH9 -> 0.041408169 | R3: ='1'!AI9+'2'!AI9+'3'!AI9+'4'!AI9+'5'!AI9+'6'!AI9+'7'!AI9+'8'!AI9+'9'!AI9+'10'!AI9+'11'!AI9+'12'!AI9+'13'!AI9+'14'!AI9+'15'!AI9+'16'!AI9+'17'!AI9+'18'!AI9+'19'!AI9+'20'!AI9+'21'!AI9+'22'!AI9+'23'!AI9 -> 0.27757831 | S3: ='1'!AJ9+'2'!AJ9+'3'!AJ9+'4'!AJ9+'5'!AJ9+'6'!AJ9+'7'!AJ9+'8'!AJ9+'9'!AJ9+'10'!AJ9+'11'!AJ9+'12'!AJ9+'13'!AJ9+'14'!AJ9+'15'!AJ9+'16'!AJ9+'17'!AJ9+'18'!AJ9+'19'!AJ9+'20'!AJ9+'21'!AJ9+'22'!AJ9+'23'!AJ9 -> 0.079269728 | T3: ='1'!AK9+'2'!AK9+'3'!AK9+'4'!AK9+'5'!AK9+'6'!AK9+'7'!AK9+'8'!AK9+'9'!AK9+'10'!AK9+'11'!AK9+'12'!AK9+'13'!AK9+'14'!AK9+'15'!AK9+'16'!AK9+'17'!AK9+'18'!AK9+'19'!AK9+'20'!AK9+'21'!AK9+'22'!AK9+'23'!AK9 -> 0.86862644 | U3: ='1'!AL9+'2'!AL9+'3'!AL9+'4'!AL9+'5'!AL9+'6'!AL9+'7'!AL9+'8'!AL9+'9'!AL9+'10'!AL9+'11'!AL9+'12'!AL9+'13'!AL9+'14'!AL9+'15'!AL9+'16'!AL9+'17'!AL9+'18'!AL9+'19'!AL9+'20'!AL9+'21'!AL9+'22'!AL9+'23'!AL9 -> 0.0020934281 | V3: =SUM(H3:L3) -> 828.42668 | W3: =SUM(M3:U3) -> 5.5990321 | Y3: =((M3+N3)*re!$D$2/re!$C$2+O3*re!$D$3/re!$C$3+P3*re!$D$4/re!$C$4+T3*re!$D$5/re!$C$5+U3*re!$D$6/re!$C$6) -> 9.5005286 | Z3: =SUM(AA3:AE3) -> 0.73298413 | AA3: =((Y3*277.8)/(re!$B$10*8760))*re!$C$10 -> 0.41556398 | AB3: =((Y3*277.8)/(re!$B$11*8760))*re!$C$11 -> 0.15450456 | AC3: =((Y3*277.8)/(re!$B$12*8760))*re!$C$12 -> 0.055793312 | AD3: =((Y3*277.8)/(re!$B$13*8760))*re!$C$13 -> 0.016374124 | AE3: =((Y3*277.8)/(re!$B$14*8760))*re!$C$14 -> 0.090748159 | AF3: =SUM('1'!AD9:AL9)+'1'!AA9 -> 133.15948 | AG3: =SUM('2'!AD9:AL9)+'2'!AA9 -> 2.5240186 | AH3: =SUM('3'!AD9:AL9)+'3'!AA9 -> 10.820074 | AI3: =SUM('4'!AD9:AL9)+'4'!AA9 -> 0.80544713 | AJ3: =SUM('5'!AD9:AL9)+'5'!AA9 -> 4.9630813 | AK3: =SUM('6'!AD9:AL9)+'6'!AA9 -> 128.23857 | AL3: =SUM('7'!AD9:AL9)+'7'!AA9 -> 112.73927 | AM3: =SUM('8'!AD9:AL9)+'8'!AA9 -> 202.83089 | AN3: =SUM('9'!AD9:AL9)+'9'!AA9 -> 61.969015 | AO3: =SUM('10'!AD9:AL9)+'10'!AA9 -> 4.5340992 | AP3: =SUM('11'!AD9:AL9)+'11'!AA9 -> 5.7700599 | AQ3: =SUM('12'!AD9:AL9)+'12'!AA9 -> 1.7726812 | AR3: =SUM('13'!AD9:AL9)+'13'!AA9 -> 5.1577613 | AS3: =SUM('14'!AD9:AL9)+'14'!AA9 -> 3.9997874 | AT3: =SUM('15'!AD9:AL9)+'15'!AA9 -> 55.057798 | AU3: =SUM('16'!AD9:AL9)+'16'!AA9 -> 21.951827 | AV3: =SUM('17'!AD9:AL9)+'17'!AA9 -> 37.359718 | AW3: =SUM('18'!AD9:AL9)+'18'!AA9 -> 9.3298196 | AX3: =SUM('19'!AD9:AL9)+'19'!AA9 -> 24.370349 | AY3: =SUM('20'!AD9:AL9)+'20'!AA9 -> 1.5380314 | AZ3: =SUM('21'!AD9:AL9)+'21'!AA9 -> 0.14018182 | BA3: =SUM('22'!AD9:AL9)+'22'!AA9 -> 0.45668482 | BB3: =SUM('23'!AD9:AL9)+'23'!AA9 -> 4.5370614 | BG3: 2026 | BH3: 0 | BI3: 0 | BK3: ='2 (RU)'!AB9+'6 (RU)'!AB9+'7 (RU)'!AB9+'9 (RU)'!AB9+'11 (RU)'!AB9+'12 (RU)'!AB9+'13 (RU)'!AB9+'16 (RU)'!AB9+'17 (RU)'!AB9+'18 (RU)'!AB9+'22 (RU)'!AB9 -> #DIV/0! | BL3: ='1 (RU)'!AB9+'2 (RU)'!AC9+'5 (RU)'!AB9+'6 (RU)'!AC9+'7 (RU)'!AC9+'9 (RU)'!AC9+'11 (RU)'!AC9+'12 (RU)'!AC9+'13 (RU)'!AC9+'15 (RU)'!AB9+'16 (RU)'!AC9+'17 (RU)'!AC9+'18 (RU)'!AC9+'19 (RU)'!AB9+'22 (RU)'!AC9 -> #DIV/0! | BN3: ='3 (RU)'!AB9+'4 (RU)'!AB9+'10 (RU)'!AB9+'20 (RU)'!AB9+'21 (RU)'!AB9+'23 (RU)'!AB9 -> #DIV/0! | BO3: ='8 (RU)'!AB9+'14 (RU)'!AB9 -> #DIV/0! | BP3: ='1 (RU)'!AD9+'2 (RU)'!AD9+'3 (RU)'!AD9+'4 (RU)'!AD9+'5 (RU)'!AD9+'6 (RU)'!AD9+'7 (RU)'!AD9+'8 (RU)'!AD9+'9 (RU)'!AD9+'10 (RU)'!AD9+'11 (RU)'!AD9+'12 (RU)'!AD9+'13 (RU)'!AD9+'14 (RU)'!AD9+'15 (RU)'!AD9+'16 (RU)'!AD9+'17 (RU)'!AD9+'18 (RU)'!AD9+'19 (RU)'!AD9+'20 (RU)'!AD9+'21 (RU)'!AD9+'22 (RU)'!AD9+'23 (RU)'!AD9 -> #DIV/0! | BQ3: ='1 (RU)'!AE9+'2 (RU)'!AE9+'3 (RU)'!AE9+'4 (RU)'!AE9+'5 (RU)'!AE9+'6 (RU)'!AE9+'7 (RU)'!AE9+'8 (RU)'!AE9+'9 (RU)'!AE9+'10 (RU)'!AE9+'11 (RU)'!AE9+'12 (RU)'!AE9+'13 (RU)'!AE9+'14 (RU)'!AE9+'15 (RU)'!AE9+'16 (RU)'!AE9+'17 (RU)'!AE9+'18 (RU)'!AE9+'19 (RU)'!AE9+'20 (RU)'!AE9+'21 (RU)'!AE9+'22 (RU)'!AE9+'23 (RU)'!AE9 -> #DIV/0! | BR3: ='1 (RU)'!AF9+'2 (RU)'!AF9+'3 (RU)'!AF9+'4 (RU)'!AF9+'5 (RU)'!AF9+'6 (RU)'!AF9+'7 (RU)'!AF9+'8 (RU)'!AF9+'9 (RU)'!AF9+'10 (RU)'!AF9+'11 (RU)'!AF9+'12 (RU)'!AF9+'13 (RU)'!AF9+'14 (RU)'!AF9+'15 (RU)'!AF9+'16 (RU)'!AF9+'17 (RU)'!AF9+'18 (RU)'!AF9+'19 (RU)'!AF9+'20 (RU)'!AF9+'21 (RU)'!AF9+'22 (RU)'!AF9+'23 (RU)'!AF9 -> #DIV/0! | BS3: ='1 (RU)'!AG9+'2 (RU)'!AG9+'3 (RU)'!AG9+'4 (RU)'!AG9+'5 (RU)'!AG9+'6 (RU)'!AG9+'7 (RU)'!AG9+'8 (RU)'!AG9+'9 (RU)'!AG9+'10 (RU)'!AG9+'11 (RU)'!AG9+'12 (RU)'!AG9+'13 (RU)'!AG9+'14 (RU)'!AG9+'15 (RU)'!AG9+'16 (RU)'!AG9+'17 (RU)'!AG9+'18 (RU)'!AG9+'19 (RU)'!AG9+'20 (RU)'!AG9+'21 (RU)'!AG9+'22 (RU)'!AG9+'23 (RU)'!AG9 -> #DIV/0! | BT3: ='1 (RU)'!AH9+'2 (RU)'!AH9+'3 (RU)'!AH9+'4 (RU)'!AH9+'5 (RU)'!AH9+'6 (RU)'!AH9+'7 (RU)'!AH9+'8 (RU)'!AH9+'9 (RU)'!AH9+'10 (RU)'!AH9+'11 (RU)'!AH9+'12 (RU)'!AH9+'13 (RU)'!AH9+'14 (RU)'!AH9+'15 (RU)'!AH9+'16 (RU)'!AH9+'17 (RU)'!AH9+'18 (RU)'!AH9+'19 (RU)'!AH9+'20 (RU)'!AH9+'21 (RU)'!AH9+'22 (RU)'!AH9+'23 (RU)'!AH9 -> #DIV/0! | BU3: ='1 (RU)'!AI9+'2 (RU)'!AI9+'3 (RU)'!AI9+'4 (RU)'!AI9+'5 (RU)'!AI9+'6 (RU)'!AI9+'7 (RU)'!AI9+'8 (RU)'!AI9+'9 (RU)'!AI9+'10 (RU)'!AI9+'11 (RU)'!AI9+'12 (RU)'!AI9+'13 (RU)'!AI9+'14 (RU)'!AI9+'15 (RU)'!AI9+'16 (RU)'!AI9+'17 (RU)'!AI9+'18 (RU)'!AI9+'19 (RU)'!AI9+'20 (RU)'!AI9+'21 (RU)'!AI9+'22 (RU)'!AI9+'23 (RU)'!AI9 -> #DIV/0! | BV3: ='1 (RU)'!AJ9+'2 (RU)'!AJ9+'3 (RU)'!AJ9+'4 (RU)'!AJ9+'5 (RU)'!AJ9+'6 (RU)'!AJ9+'7 (RU)'!AJ9+'8 (RU)'!AJ9+'9 (RU)'!AJ9+'10 (RU)'!AJ9+'11 (RU)'!AJ9+'12 (RU)'!AJ9+'13 (RU)'!AJ9+'14 (RU)'!AJ9+'15 (RU)'!AJ9+'16 (RU)'!AJ9+'17 (RU)'!AJ9+'18 (RU)'!AJ9+'19 (RU)'!AJ9+'20 (RU)'!AJ9+'21 (RU)'!AJ9+'22 (RU)'!AJ9+'23 (RU)'!AJ9 -> #DIV/0! | BW3: ='1 (RU)'!AK9+'2 (RU)'!AK9+'3 (RU)'!AK9+'4 (RU)'!AK9+'5 (RU)'!AK9+'6 (RU)'!AK9+'7 (RU)'!AK9+'8 (RU)'!AK9+'9 (RU)'!AK9+'10 (RU)'!AK9+'11 (RU)'!AK9+'12 (RU)'!AK9+'13 (RU)'!AK9+'14 (RU)'!AK9+'15 (RU)'!AK9+'16 (RU)'!AK9+'17 (RU)'!AK9+'18 (RU)'!AK9+'19 (RU)'!AK9+'20 (RU)'!AK9+'21 (RU)'!AK9+'22 (RU)'!AK9+'23 (RU)'!AK9 -> #DIV/0! | BX3: ='1 (RU)'!AL9+'2 (RU)'!AL9+'3 (RU)'!AL9+'4 (RU)'!AL9+'5 (RU)'!AL9+'6 (RU)'!AL9+'7 (RU)'!AL9+'8 (RU)'!AL9+'9 (RU)'!AL9+'10 (RU)'!AL9+'11 (RU)'!AL9+'12 (RU)'!AL9+'13 (RU)'!AL9+'14 (RU)'!AL9+'15 (RU)'!AL9+'16 (RU)'!AL9+'17 (RU)'!AL9+'18 (RU)'!AL9+'19 (RU)'!AL9+'20 (RU)'!AL9+'21 (RU)'!AL9+'22 (RU)'!AL9+'23 (RU)'!AL9 -> #DIV/0! | BY3: =SUM(BK3:BO3) -> #DIV/0! | BZ3: =SUM(BP3:BX3) -> #DIV/0! | CC3: =VLOOKUP(CC$1,emissions!$A$2:$B$5,2,FALSE)*BK3 -> #DIV/0! | CD3: =VLOOKUP(CD$1,emissions!$A$2:$B$5,2,FALSE)*BL3 -> #DIV/0! | CF3: =VLOOKUP(CF$1,emissions!$A$2:$B$5,2,FALSE)*BN3 -> #DIV/0! | CG3: =VLOOKUP(CG$1,emissions!$A$2:$B$5,2,FALSE)*BO3 -> #DIV/0! | CH3: =BP3*(emissions!$D$3*production!$B$4+emissions!$D$4*production!$C$4+emissions!$D$5*production!$D$4+emissions!$D$6*production!$E$4) -> #DIV/0! | CI3: =BQ3*(emissions!$D$3*production!$B$4+emissions!$D$4*production!$C$4+emissions!$D$5*production!$D$4+emissions!$D$6*production!$E$4) -> #DIV/0! | CJ3: =BR3*(emissions!$D$8*production!$B$6+emissions!$D$9*production!$C$6+emissions!$D$10*production!$D$6) -> #DIV/0! | CK3: =BS3*(emissions!$D$12*production!$B$8+emissions!$D$13*production!$C$8+emissions!$D$14*production!$D$8) -> #DIV/0! | CL3: =BT3*(emissions!$D$16*production!$B$10+production!$C$10*emissions!$D$17) -> #DIV/0! | CM3: =BU3*(emissions!$D$19*production!$B$12+production!$C$12*emissions!$D$20+emissions!$D$21*production!$D$12) -> #DIV/0! | CN3: =BV3*(emissions!$D$23*production!$B$14+production!$C$14*emissions!$D$24+emissions!$D$25*production!$D$14) -> #DIV/0! | CO3: =BW3*(emissions!$D$27*production!$B$16+production!$C$16*emissions!$D$28+production!$D$16*emissions!$D$29) -> #DIV/0! | CP3: 0 | CS3: =SUM(CC3:CP3) -> #DIV/0! | CT3: =SUM(CC3:CP3)/SUM(BK3:BX3) -> #DIV/0! | CU3: =(CT3-CW3) -> #DIV/0! | CV3: =CT3-CX3 -> #DIV/0! | CW3: =93.3*(1-BH3) -> 93.3 | CX3: =93.3*(1-BI3) -> 93.3 | CY3: =IF(G3<2028,0,IF(CT3>=CW3,CU3,IF(AND(CT3<CW3,CT3>=CX3),CV3,0))*SUM(BK3:BX3)) -> 0 | CZ3: =IF(CT3>=CW3,380*CY3,IF(AND(CT3<CW3,CT3>=CX3),100*CY3,0)) -> #DIV/0! | DA3: =IF(G3<2028,"",IF(CT3>=CW3,"Red",IF(AND(CT3<CW3,CT3>=CX3),"Yellow","Green"))) | DB3: =IF(G3<2028,0,IF(CT3<CX3,-CV3*SUM(BK3:BX3),0)) -> 0 | DC3: =DB3*380 -> 0 | DD3: 2026 | DO3: op costs (right) | DP3: sum op costs | DQ3: 17960 | DR3: 7825 | DT3: 614 | DU3: 2090 | DV3: =DQ3*VLOOKUP(DQ$1,emissions!$A$2:$B$5,2,FALSE) -> 2622160 | DW3: =DR3*VLOOKUP(DR$1,emissions!$A$2:$B$5,2,FALSE) -> 1142450 | DY3: =DT3*VLOOKUP(DT$1,emissions!$A$2:$B$5,2,FALSE) -> 89030 | DZ3: =DU3*VLOOKUP(DU$1,emissions!$A$2:$B$5,2,FALSE) -> 236170 | EA3: =SUM(DV3:DZ3) -> 4089810 | EB3: =1/(SUM(DQ3:DU3)/EA3) -> 143.55751 | ED3: =SUM(EE3:ER3) -> #DIV/0! | EE3: =cost!$B$2*BK3 -> #DIV/0! | EF3: =cost!$B$3*BL3 -> #DIV/0! | EH3: =cost!$B$4*BN3 -> #DIV/0! | EI3: =cost!$B$5*$BO$2 -> #DIV/0! | EJ3: =BP3*(cost!$D$3*production!$B$4+production!$C$4*cost!$D$4+cost!$D$5*production!$D$4+production!$E$4*cost!$D$6) -> #DIV/0! | EK3: =BQ3*(cost!$D$3*production!$B$4+production!$C$4*cost!$D$4+cost!$D$5*production!$D$4+production!$E$4*cost!$D$6) -> #DIV/0! | EL3: =BR3*(cost!$D$8*production!$B$6+cost!$D$9*production!$C$6+$D$10*production!$D$6) -> #DIV/0! | EM3: =BS3*(cost!$D$12*production!$B$8+cost!$D$13*production!$C$8+cost!$D$14*production!$D$8) -> #DIV/0! | EN3: =BT3*(cost!$D$16*production!$B$10+production!$C$10*cost!$D$17) -> #DIV/0! | EO3: =BU3*(cost!$D$19*production!$B$12+production!$C$12*cost!$D$20+cost!$D$21*production!$D$12) -> #DIV/0! | EP3: =BV3*(cost!$D$23*production!$B$14+production!$C$14*cost!$D$24+cost!$D$25*production!$D$14) -> #DIV/0! | EQ3: =BW3*(cost!$D$27*production!$B$16+production!$C$16*cost!$D$28+cost!$D$29*production!$D$16) -> #DIV/0! | ER3: =BX3*(re!$H$10*re!$C$10+re!$H$11*re!$C$11+re!$H$12*re!$C$12+re!$H$13*re!$C$13+re!$H$14*re!$C$14) -> #DIV/0!
A4: Hull coating + propeller | B4: 0.03 | C4: 0.13 | D4: 5 | G4: 2027 | H4: ='2'!AB10+'6'!AB10+'7'!AB10+'9'!AB10+'11'!AB10+'12'!AB10+'13'!AB10+'16'!AB10+'17'!AB10+'18'!AB10+'22'!AB10 -> 346.44752 | I4: ='1'!AB10+'2'!AC10+'5'!AB10+'6'!AC10+'7'!AC10+'9'!AC10+'11'!AC10+'12'!AC10+'13'!AC10+'15'!AB10+'16'!AC10+'17'!AC10+'18'!AC10+'19'!AB10+'22'!AC10 -> 259.39735 | K4: ='3'!AB10+'4'!AB10+'10'!AB10+'20'!AB10+'21'!AB10+'23'!AB10 -> 22.463129 | L4: ='8'!AB10+'14'!AB10 -> 207.40306 | M4: ='1'!AD10+'2'!AD10+'3'!AD10+'4'!AD10+'5'!AD10+'6'!AD10+'7'!AD10+'8'!AD10+'9'!AD10+'10'!AD10+'11'!AD10+'12'!AD10+'13'!AD10+'14'!AD10+'15'!AD10+'16'!AD10+'17'!AD10+'18'!AD10+'19'!AD10+'20'!AD10+'21'!AD10+'22'!AD10+'23'!AD10 -> 2.3774288 | N4: ='1'!AE10+'2'!AE10+'3'!AE10+'4'!AE10+'5'!AE10+'6'!AE10+'7'!AE10+'8'!AE10+'9'!AE10+'10'!AE10+'11'!AE10+'12'!AE10+'13'!AE10+'14'!AE10+'15'!AE10+'16'!AE10+'17'!AE10+'18'!AE10+'19'!AE10+'20'!AE10+'21'!AE10+'22'!AE10+'23'!AE10 -> 0.1409836 | O4: ='1'!AF10+'2'!AF10+'3'!AF10+'4'!AF10+'5'!AF10+'6'!AF10+'7'!AF10+'8'!AF10+'9'!AF10+'10'!AF10+'11'!AF10+'12'!AF10+'13'!AF10+'14'!AF10+'15'!AF10+'16'!AF10+'17'!AF10+'18'!AF10+'19'!AF10+'20'!AF10+'21'!AF10+'22'!AF10+'23'!AF10 -> 4.5562759 | P4: ='1'!AG10+'2'!AG10+'3'!AG10+'4'!AG10+'5'!AG10+'6'!AG10+'7'!AG10+'8'!AG10+'9'!AG10+'10'!AG10+'11'!AG10+'12'!AG10+'13'!AG10+'14'!AG10+'15'!AG10+'16'!AG10+'17'!AG10+'18'!AG10+'19'!AG10+'20'!AG10+'21'!AG10+'22'!AG10+'23'!AG10 -> 4.1430585 | Q4: ='1'!AH10+'2'!AH10+'3'!AH10+'4'!AH10+'5'!AH10+'6'!AH10+'7'!AH10+'8'!AH10+'9'!AH10+'10'!AH10+'11'!AH10+'12'!AH10+'13'!AH10+'14'!AH10+'15'!AH10+'16'!AH10+'17'!AH10+'18'!AH10+'19'!AH10+'20'!AH10+'21'!AH10+'22'!AH10+'23'!AH10 -> 0.10716314 | R4: ='1'!AI10+'2'!AI10+'3'!AI10+'4'!AI10+'5'!AI10+'6'!AI10+'7'!AI10+'8'!AI10+'9'!AI10+'10'!AI10+'11'!AI10+'12'!AI10+'13'!AI10+'14'!AI10+'15'!AI10+'16'!AI10+'17'!AI10+'18'!AI10+'19'!AI10+'20'!AI10+'21'!AI10+'22'!AI10+'23'!AI10 -> 0.71913032 | S4: ='1'!AJ10+'2'!AJ10+'3'!AJ10+'4'!AJ10+'5'!AJ10+'6'!AJ10+'7'!AJ10+'8'!AJ10+'9'!AJ10+'10'!AJ10+'11'!AJ10+'12'!AJ10+'13'!AJ10+'14'!AJ10+'15'!AJ10+'16'!AJ10+'17'!AJ10+'18'!AJ10+'19'!AJ10+'20'!AJ10+'21'!AJ10+'22'!AJ10+'23'!AJ10 -> 0.20515723 | T4: ='1'!AK10+'2'!AK10+'3'!AK10+'4'!AK10+'5'!AK10+'6'!AK10+'7'!AK10+'8'!AK10+'9'!AK10+'10'!AK10+'11'!AK10+'12'!AK10+'13'!AK10+'14'!AK10+'15'!AK10+'16'!AK10+'17'!AK10+'18'!AK10+'19'!AK10+'20'!AK10+'21'!AK10+'22'!AK10+'23'!AK10 -> 2.2509112 | U4: ='1'!AL10+'2'!AL10+'3'!AL10+'4'!AL10+'5'!AL10+'6'!AL10+'7'!AL10+'8'!AL10+'9'!AL10+'10'!AL10+'11'!AL10+'12'!AL10+'13'!AL10+'14'!AL10+'15'!AL10+'16'!AL10+'17'!AL10+'18'!AL10+'19'!AL10+'20'!AL10+'21'!AL10+'22'!AL10+'23'!AL10 -> 0.0054312862 | V4: =SUM(H4:L4) -> 835.71105 | W4: =SUM(M4:U4) -> 14.50554 | X4: =W4/W3-1 -> 1.5907228 | Y4: =((M4+N4)*re!$D$2/re!$C$2+O4*re!$D$3/re!$C$3+P4*re!$D$4/re!$C$4+T4*re!$D$5/re!$C$5+U4*re!$D$6/re!$C$6) -> 24.613702 | Z4: =SUM(AA4:AE4) -> 1.8989946 | AA4: =((Y4*277.8)/(re!$B$10*8760))*re!$C$10 -> 1.0766314 | AB4: =((Y4*277.8)/(re!$B$11*8760))*re!$C$11 -> 0.40028605 | AC4: =((Y4*277.8)/(re!$B$12*8760))*re!$C$12 -> 0.14454774 | AD4: =((Y4*277.8)/(re!$B$13*8760))*re!$C$13 -> 0.042421619 | AE4: =((Y4*277.8)/(re!$B$14*8760))*re!$C$14 -> 0.23510777 | AF4: =SUM('1'!AD10:AL10)+'1'!AA10 -> 135.69832 | AG4: =SUM('2'!AD10:AL10)+'2'!AA10 -> 2.5701218 | AH4: =SUM('3'!AD10:AL10)+'3'!AA10 -> 11.042625 | AI4: =SUM('4'!AD10:AL10)+'4'!AA10 -> 0.82214346 | AJ4: =SUM('5'!AD10:AL10)+'5'!AA10 -> 5.0533188 | AK4: =SUM('6'!AD10:AL10)+'6'!AA10 -> 130.54335 | AL4: =SUM('7'!AD10:AL10)+'7'!AA10 -> 114.79623 | AM4: =SUM('8'!AD10:AL10)+'8'!AA10 -> 207.29829 | AN4: =SUM('9'!AD10:AL10)+'9'!AA10 -> 63.09572 | AO4: =SUM('10'!AD10:AL10)+'10'!AA10 -> 4.6253186 | AP4: =SUM('11'!AD10:AL10)+'11'!AA10 -> 5.8808457 | AQ4: =SUM('12'!AD10:AL10)+'12'!AA10 -> 1.8067169 | AR4: =SUM('13'!AD10:AL10)+'13'!AA10 -> 5.2567909 | AS4: =SUM('14'!AD10:AL10)+'14'!AA10 -> 4.0817597 | AT4: =SUM('15'!AD10:AL10)+'15'!AA10 -> 56.058845 | AU4: =SUM('16'!AD10:AL10)+'16'!AA10 -> 22.373304 | AV4: =SUM('17'!AD10:AL10)+'17'!AA10 -> 38.07703 | AW4: =SUM('18'!AD10:AL10)+'18'!AA10 -> 9.5089533 | AX4: =SUM('19'!AD10:AL10)+'19'!AA10 -> 24.813444 | AY4: =SUM('20'!AD10:AL10)+'20'!AA10 -> 1.5699136 | AZ4: =SUM('21'!AD10:AL10)+'21'!AA10 -> 0.14294471 | BA4: =SUM('22'!AD10:AL10)+'22'!AA10 -> 0.46498815 | BB4: =SUM('23'!AD10:AL10)+'23'!AA10 -> 4.6356229 | BC4: =('1'!D10+'2'!D10+'3'!D10+'4'!D10+'5'!D10+'6'!D10+'7'!D10+'8'!D10+'9'!D10+'10'!D10+'12'!D10+'13'!D10+'14'!D10+'15'!D10+'16'!D10+'17'!D10+'18'!D10+'19'!D10+'20'!D10+'21'!D10+'22'!D10+'23'!D10)/('1'!D9+'2'!D9+'3'!D9+'4'!D9+'5'!D9+'6'!D9+'7'!D9+'8'!D9+'9'!D9+'10'!D9+'12'!D9+'13'!D9+'14'!D9+'15'!D9+'16'!D9+'17'!D9+'18'!D9+'19'!D9+'20'!D9+'21'!D9+'22'!D9+'23'!D9)-1 -> 1.0438371 | BD4: =('1'!E10+'2'!E10+'3'!E10+'4'!E10+'5'!E10+'6'!E10+'7'!E10+'8'!E10+'9'!E10+'10'!E10+'12'!E10+'13'!E10+'14'!E10+'15'!E10+'16'!E10+'17'!E10+'18'!E10+'19'!E10+'20'!E10+'21'!E10+'22'!E10+'23'!E10)/('1'!E9+'2'!E9+'3'!E9+'4'!E9+'5'!E9+'6'!E9+'7'!E9+'8'!E9+'9'!E9+'10'!E9+'12'!E9+'13'!E9+'14'!E9+'15'!E9+'16'!E9+'17'!E9+'18'!E9+'19'!E9+'20'!E9+'21'!E9+'22'!E9+'23'!E9)-1 -> 1.0438371 | BE4: =('1'!F10+'2'!F10+'3'!F10+'4'!F10+'5'!F10+'6'!F10+'7'!F10+'8'!F10+'9'!F10+'10'!F10+'12'!F10+'13'!F10+'14'!F10+'15'!F10+'16'!F10+'17'!F10+'18'!F10+'19'!F10+'20'!F10+'21'!F10+'22'!F10+'23'!F10)/('1'!F9+'2'!F9+'3'!F9+'4'!F9+'5'!F9+'6'!F9+'7'!F9+'8'!F9+'9'!F9+'10'!F9+'12'!F9+'13'!F9+'14'!F9+'15'!F9+'16'!F9+'17'!F9+'18'!F9+'19'!F9+'20'!F9+'21'!F9+'22'!F9+'23'!F9)-1 -> 1.0424592 | BF4: =W4/W3-1 -> 1.5907228 | BG4: 2027 | BH4: 0 | BI4: 0 | BK4: ='2 (RU)'!AB10+'6 (RU)'!AB10+'7 (RU)'!AB10+'9 (RU)'!AB10+'11 (RU)'!AB10+'12 (RU)'!AB10+'13 (RU)'!AB10+'16 (RU)'!AB10+'17 (RU)'!AB10+'18 (RU)'!AB10+'22 (RU)'!AB10 -> #DIV/0! | BL4: ='1 (RU)'!AB10+'2 (RU)'!AC10+'5 (RU)'!AB10+'6 (RU)'!AC10+'7 (RU)'!AC10+'9 (RU)'!AC10+'11 (RU)'!AC10+'12 (RU)'!AC10+'13 (RU)'!AC10+'15 (RU)'!AB10+'16 (RU)'!AC10+'17 (RU)'!AC10+'18 (RU)'!AC10+'19 (RU)'!AB10+'22 (RU)'!AC10 -> #DIV/0! | BN4: ='3 (RU)'!AB10+'4 (RU)'!AB10+'10 (RU)'!AB10+'20 (RU)'!AB10+'21 (RU)'!AB10+'23 (RU)'!AB10 -> #DIV/0! | BO4: ='8 (RU)'!AB10+'14 (RU)'!AB10 -> #DIV/0! | BP4: ='1 (RU)'!AD10+'2 (RU)'!AD10+'3 (RU)'!AD10+'4 (RU)'!AD10+'5 (RU)'!AD10+'6 (RU)'!AD10+'7 (RU)'!AD10+'8 (RU)'!AD10+'9 (RU)'!AD10+'10 (RU)'!AD10+'11 (RU)'!AD10+'12 (RU)'!AD10+'13 (RU)'!AD10+'14 (RU)'!AD10+'15 (RU)'!AD10+'16 (RU)'!AD10+'17 (RU)'!AD10+'18 (RU)'!AD10+'19 (RU)'!AD10+'20 (RU)'!AD10+'21 (RU)'!AD10+'22 (RU)'!AD10+'23 (RU)'!AD10 -> #DIV/0! | BQ4: ='1 (RU)'!AE10+'2 (RU)'!AE10+'3 (RU)'!AE10+'4 (RU)'!AE10+'5 (RU)'!AE10+'6 (RU)'!AE10+'7 (RU)'!AE10+'8 (RU)'!AE10+'9 (RU)'!AE10+'10 (RU)'!AE10+'11 (RU)'!AE10+'12 (RU)'!AE10+'13 (RU)'!AE10+'14 (RU)'!AE10+'15 (RU)'!AE10+'16 (RU)'!AE10+'17 (RU)'!AE10+'18 (RU)'!AE10+'19 (RU)'!AE10+'20 (RU)'!AE10+'21 (RU)'!AE10+'22 (RU)'!AE10+'23 (RU)'!AE10 -> #DIV/0! | BR4: ='1 (RU)'!AF10+'2 (RU)'!AF10+'3 (RU)'!AF10+'4 (RU)'!AF10+'5 (RU)'!AF10+'6 (RU)'!AF10+'7 (RU)'!AF10+'8 (RU)'!AF10+'9 (RU)'!AF10+'10 (RU)'!AF10+'11 (RU)'!AF10+'12 (RU)'!AF10+'13 (RU)'!AF10+'14 (RU)'!AF10+'15 (RU)'!AF10+'16 (RU)'!AF10+'17 (RU)'!AF10+'18 (RU)'!AF10+'19 (RU)'!AF10+'20 (RU)'!AF10+'21 (RU)'!AF10+'22 (RU)'!AF10+'23 (RU)'!AF10 -> #DIV/0! | BS4: ='1 (RU)'!AG10+'2 (RU)'!AG10+'3 (RU)'!AG10+'4 (RU)'!AG10+'5 (RU)'!AG10+'6 (RU)'!AG10+'7 (RU)'!AG10+'8 (RU)'!AG10+'9 (RU)'!AG10+'10 (RU)'!AG10+'11 (RU)'!AG10+'12 (RU)'!AG10+'13 (RU)'!AG10+'14 (RU)'!AG10+'15 (RU)'!AG10+'16 (RU)'!AG10+'17 (RU)'!AG10+'18 (RU)'!AG10+'19 (RU)'!AG10+'20 (RU)'!AG10+'21 (RU)'!AG10+'22 (RU)'!AG10+'23 (RU)'!AG10 -> #DIV/0! | BT4: ='1 (RU)'!AH10+'2 (RU)'!AH10+'3 (RU)'!AH10+'4 (RU)'!AH10+'5 (RU)'!AH10+'6 (RU)'!AH10+'7 (RU)'!AH10+'8 (RU)'!AH10+'9 (RU)'!AH10+'10 (RU)'!AH10+'11 (RU)'!AH10+'12 (RU)'!AH10+'13 (RU)'!AH10+'14 (RU)'!AH10+'15 (RU)'!AH10+'16 (RU)'!AH10+'17 (RU)'!AH10+'18 (RU)'!AH10+'19 (RU)'!AH10+'20 (RU)'!AH10+'21 (RU)'!AH10+'22 (RU)'!AH10+'23 (RU)'!AH10 -> #DIV/0! | BU4: ='1 (RU)'!AI10+'2 (RU)'!AI10+'3 (RU)'!AI10+'4 (RU)'!AI10+'5 (RU)'!AI10+'6 (RU)'!AI10+'7 (RU)'!AI10+'8 (RU)'!AI10+'9 (RU)'!AI10+'10 (RU)'!AI10+'11 (RU)'!AI10+'12 (RU)'!AI10+'13 (RU)'!AI10+'14 (RU)'!AI10+'15 (RU)'!AI10+'16 (RU)'!AI10+'17 (RU)'!AI10+'18 (RU)'!AI10+'19 (RU)'!AI10+'20 (RU)'!AI10+'21 (RU)'!AI10+'22 (RU)'!AI10+'23 (RU)'!AI10 -> #DIV/0! | BV4: ='1 (RU)'!AJ10+'2 (RU)'!AJ10+'3 (RU)'!AJ10+'4 (RU)'!AJ10+'5 (RU)'!AJ10+'6 (RU)'!AJ10+'7 (RU)'!AJ10+'8 (RU)'!AJ10+'9 (RU)'!AJ10+'10 (RU)'!AJ10+'11 (RU)'!AJ10+'12 (RU)'!AJ10+'13 (RU)'!AJ10+'14 (RU)'!AJ10+'15 (RU)'!AJ10+'16 (RU)'!AJ10+'17 (RU)'!AJ10+'18 (RU)'!AJ10+'19 (RU)'!AJ10+'20 (RU)'!AJ10+'21 (RU)'!AJ10+'22 (RU)'!AJ10+'23 (RU)'!AJ10 -> #DIV/0! | BW4: ='1 (RU)'!AK10+'2 (RU)'!AK10+'3 (RU)'!AK10+'4 (RU)'!AK10+'5 (RU)'!AK10+'6 (RU)'!AK10+'7 (RU)'!AK10+'8 (RU)'!AK10+'9 (RU)'!AK10+'10 (RU)'!AK10+'11 (RU)'!AK10+'12 (RU)'!AK10+'13 (RU)'!AK10+'14 (RU)'!AK10+'15 (RU)'!AK10+'16 (RU)'!AK10+'17 (RU)'!AK10+'18 (RU)'!AK10+'19 (RU)'!AK10+'20 (RU)'!AK10+'21 (RU)'!AK10+'22 (RU)'!AK10+'23 (RU)'!AK10 -> #DIV/0! | BX4: ='1 (RU)'!AL10+'2 (RU)'!AL10+'3 (RU)'!AL10+'4 (RU)'!AL10+'5 (RU)'!AL10+'6 (RU)'!AL10+'7 (RU)'!AL10+'8 (RU)'!AL10+'9 (RU)'!AL10+'10 (RU)'!AL10+'11 (RU)'!AL10+'12 (RU)'!AL10+'13 (RU)'!AL10+'14 (RU)'!AL10+'15 (RU)'!AL10+'16 (RU)'!AL10+'17 (RU)'!AL10+'18 (RU)'!AL10+'19 (RU)'!AL10+'20 (RU)'!AL10+'21 (RU)'!AL10+'22 (RU)'!AL10+'23 (RU)'!AL10 -> #DIV/0! | BY4: =SUM(BK4:BO4) -> #DIV/0! | BZ4: =SUM(BP4:BX4) -> #DIV/0! | CC4: =VLOOKUP(CC$1,emissions!$A$2:$B$5,2,FALSE)*BK4 -> #DIV/0! | CD4: =VLOOKUP(CD$1,emissions!$A$2:$B$5,2,FALSE)*BL4 -> #DIV/0! | CF4: =VLOOKUP(CF$1,emissions!$A$2:$B$5,2,FALSE)*BN4 -> #DIV/0! | CG4: =VLOOKUP(CG$1,emissions!$A$2:$B$5,2,FALSE)*BO4 -> #DIV/0! | CH4: =BP4*(emissions!$D$3*production!$B$4+emissions!$D$4*production!$C$4+emissions!$D$5*production!$D$4+emissions!$D$6*production!$E$4) -> #DIV/0! | CI4: =BQ4*(emissions!$D$3*production!$B$4+emissions!$D$4*production!$C$4+emissions!$D$5*production!$D$4+emissions!$D$6*production!$E$4) -> #DIV/0! | CJ4: =BR4*(emissions!$D$8*production!$B$6+emissions!$D$9*production!$C$6+emissions!$D$10*production!$D$6) -> #DIV/0! | CK4: =BS4*(emissions!$D$12*production!$B$8+emissions!$D$13*production!$C$8+emissions!$D$14*production!$D$8) -> #DIV/0! | CL4: =BT4*(emissions!$D$16*production!$B$10+production!$C$10*emissions!$D$17) -> #DIV/0! | CM4: =BU4*(emissions!$D$19*production!$B$12+production!$C$12*emissions!$D$20+emissions!$D$21*production!$D$12) -> #DIV/0! | CN4: =BV4*(emissions!$D$23*production!$B$14+production!$C$14*emissions!$D$24+emissions!$D$25*production!$D$14) -> #DIV/0! | CO4: =BW4*(emissions!$D$27*production!$B$16+production!$C$16*emissions!$D$28+production!$D$16*emissions!$D$29) -> #DIV/0! | CP4: 0 | CS4: =SUM(CC4:CP4) -> #DIV/0! | CT4: =SUM(CC4:CP4)/SUM(BK4:BX4) -> #DIV/0! | CU4: =(CT4-CW4) -> #DIV/0! | CV4: =CT4-CX4 -> #DIV/0! | CW4: =93.3*(1-BH4) -> 93.3 | CX4: =93.3*(1-BI4) -> 93.3 | CY4: =IF(G4<2028,0,IF(CT4>=CW4,CU4,IF(AND(CT4<CW4,CT4>=CX4),CV4,0))*SUM(BK4:BX4)) -> 0 | CZ4: =IF(CT4>=CW4,380*CY4,IF(AND(CT4<CW4,CT4>=CX4),100*CY4,0)) -> #DIV/0! | DA4: =IF(G4<2028,"",IF(CT4>=CW4,"Red",IF(AND(CT4<CW4,CT4>=CX4),"Yellow","Green"))) | DB4: =IF(G4<2028,0,IF(CT4<CX4,-CV4*SUM(BK4:BX4),0)) -> 0 | DC4: =DB4*380 -> 0 | DD4: 2027 | DQ4: 17666 | DR4: 8584 | DT4: 626 | DU4: 2132 | DV4: =DQ4*VLOOKUP(DQ$1,emissions!$A$2:$B$5,2,FALSE) -> 2579236 | DW4: =DR4*VLOOKUP(DR$1,emissions!$A$2:$B$5,2,FALSE) -> 1253264 | DY4: =DT4*VLOOKUP(DT$1,emissions!$A$2:$B$5,2,FALSE) -> 90770 | DZ4: =DU4*VLOOKUP(DU$1,emissions!$A$2:$B$5,2,FALSE) -> 240916 | EA4: =SUM(DV4:DZ4) -> 4164186 | EB4: =1/(SUM(DQ4:DU4)/EA4) -> 143.55302 | ED4: =SUM(EE4:ER4) -> #DIV/0! | EE4: =cost!$B$2*BK4 -> #DIV/0! | EF4: =cost!$B$3*BL4 -> #DIV/0! | EH4: =cost!$B$4*BN4 -> #DIV/0! | EI4: =cost!$B$5*$BO$2 -> #DIV/0! | EJ4: =BP4*(cost!$D$3*production!$B$4+production!$C$4*cost!$D$4+cost!$D$5*production!$D$4+production!$E$4*cost!$D$6) -> #DIV/0! | EK4: =BQ4*(cost!$D$3*production!$B$4+production!$C$4*cost!$D$4+cost!$D$5*production!$D$4+production!$E$4*cost!$D$6) -> #DIV/0! | EL4: =BR4*(cost!$D$8*production!$B$6+cost!$D$9*production!$C$6+$D$10*production!$D$6) -> #DIV/0! | EM4: =BS4*(cost!$D$12*production!$B$8+cost!$D$13*production!$C$8+cost!$D$14*production!$D$8) -> #DIV/0! | EN4: =BT4*(cost!$D$16*production!$B$10+production!$C$10*cost!$D$17) -> #DIV/0! | EO4: =BU4*(cost!$D$19*production!$B$12+production!$C$12*cost!$D$20+cost!$D$21*production!$D$12) -> #DIV/0! | EP4: =BV4*(cost!$D$23*production!$B$14+production!$C$14*cost!$D$24+cost!$D$25*production!$D$14) -> #DIV/0! | EQ4: =BW4*(cost!$D$27*production!$B$16+production!$C$16*cost!$D$28+cost!$D$29*production!$D$16) -> #DIV/0! | ER4: =BX4*(re!$H$10*re!$C$10+re!$H$11*re!$C$11+re!$H$12*re!$C$12+re!$H$13*re!$C$13+re!$H$14*re!$C$14) -> #DIV/0!
A5: Slow steaming | B5: 0.03 | C5: 0.2 | D5: 5 | G5: 2028 | H5: ='2'!AB11+'6'!AB11+'7'!AB11+'9'!AB11+'11'!AB11+'12'!AB11+'13'!AB11+'16'!AB11+'17'!AB11+'18'!AB11+'22'!AB11 -> 321.98847 | I5: ='1'!AB11+'2'!AC11+'5'!AB11+'6'!AC11+'7'!AC11+'9'!AC11+'11'!AC11+'12'!AC11+'13'!AC11+'15'!AB11+'16'!AC11+'17'!AC11+'18'!AC11+'19'!AB11+'22'!AC11 -> 285.63699 | K5: ='3'!AB11+'4'!AB11+'10'!AB11+'20'!AB11+'21'!AB11+'23'!AB11 -> 22.579446 | L5: ='8'!AB11+'14'!AB11 -> 208.43099 | M5: ='1'!AD11+'2'!AD11+'3'!AD11+'4'!AD11+'5'!AD11+'6'!AD11+'7'!AD11+'8'!AD11+'9'!AD11+'10'!AD11+'11'!AD11+'12'!AD11+'13'!AD11+'14'!AD11+'15'!AD11+'16'!AD11+'17'!AD11+'18'!AD11+'19'!AD11+'20'!AD11+'21'!AD11+'22'!AD11+'23'!AD11 -> 4.6698485 | N5: ='1'!AE11+'2'!AE11+'3'!AE11+'4'!AE11+'5'!AE11+'6'!AE11+'7'!AE11+'8'!AE11+'9'!AE11+'10'!AE11+'11'!AE11+'12'!AE11+'13'!AE11+'14'!AE11+'15'!AE11+'16'!AE11+'17'!AE11+'18'!AE11+'19'!AE11+'20'!AE11+'21'!AE11+'22'!AE11+'23'!AE11 -> 0.27692102 | O5: ='1'!AF11+'2'!AF11+'3'!AF11+'4'!AF11+'5'!AF11+'6'!AF11+'7'!AF11+'8'!AF11+'9'!AF11+'10'!AF11+'11'!AF11+'12'!AF11+'13'!AF11+'14'!AF11+'15'!AF11+'16'!AF11+'17'!AF11+'18'!AF11+'19'!AF11+'20'!AF11+'21'!AF11+'22'!AF11+'23'!AF11 -> 8.9491719 | P5: ='1'!AG11+'2'!AG11+'3'!AG11+'4'!AG11+'5'!AG11+'6'!AG11+'7'!AG11+'8'!AG11+'9'!AG11+'10'!AG11+'11'!AG11+'12'!AG11+'13'!AG11+'14'!AG11+'15'!AG11+'16'!AG11+'17'!AG11+'18'!AG11+'19'!AG11+'20'!AG11+'21'!AG11+'22'!AG11+'23'!AG11 -> 8.1383354 | Q5: ='1'!AH11+'2'!AH11+'3'!AH11+'4'!AH11+'5'!AH11+'6'!AH11+'7'!AH11+'8'!AH11+'9'!AH11+'10'!AH11+'11'!AH11+'12'!AH11+'13'!AH11+'14'!AH11+'15'!AH11+'16'!AH11+'17'!AH11+'18'!AH11+'19'!AH11+'20'!AH11+'21'!AH11+'22'!AH11+'23'!AH11 -> 0.21027338 | R5: ='1'!AI11+'2'!AI11+'3'!AI11+'4'!AI11+'5'!AI11+'6'!AI11+'7'!AI11+'8'!AI11+'9'!AI11+'10'!AI11+'11'!AI11+'12'!AI11+'13'!AI11+'14'!AI11+'15'!AI11+'16'!AI11+'17'!AI11+'18'!AI11+'19'!AI11+'20'!AI11+'21'!AI11+'22'!AI11+'23'!AI11 -> 1.4125725 | S5: ='1'!AJ11+'2'!AJ11+'3'!AJ11+'4'!AJ11+'5'!AJ11+'6'!AJ11+'7'!AJ11+'8'!AJ11+'9'!AJ11+'10'!AJ11+'11'!AJ11+'12'!AJ11+'13'!AJ11+'14'!AJ11+'15'!AJ11+'16'!AJ11+'17'!AJ11+'18'!AJ11+'19'!AJ11+'20'!AJ11+'21'!AJ11+'22'!AJ11+'23'!AJ11 -> 0.40257414 | T5: ='1'!AK11+'2'!AK11+'3'!AK11+'4'!AK11+'5'!AK11+'6'!AK11+'7'!AK11+'8'!AK11+'9'!AK11+'10'!AK11+'11'!AK11+'12'!AK11+'13'!AK11+'14'!AK11+'15'!AK11+'16'!AK11+'17'!AK11+'18'!AK11+'19'!AK11+'20'!AK11+'21'!AK11+'22'!AK11+'23'!AK11 -> 4.4224708 | U5: ='1'!AL11+'2'!AL11+'3'!AL11+'4'!AL11+'5'!AL11+'6'!AL11+'7'!AL11+'8'!AL11+'9'!AL11+'10'!AL11+'11'!AL11+'12'!AL11+'13'!AL11+'14'!AL11+'15'!AL11+'16'!AL11+'17'!AL11+'18'!AL11+'19'!AL11+'20'!AL11+'21'!AL11+'22'!AL11+'23'!AL11 -> 0.010683887 | V5: =SUM(H5:L5) -> 838.6359 | W5: =SUM(M5:U5) -> 28.492852 | X5: =W5/W4-1 -> 0.96427376 | Y5: =((M5+N5)*re!$D$2/re!$C$2+O5*re!$D$3/re!$C$3+P5*re!$D$4/re!$C$4+T5*re!$D$5/re!$C$5+U5*re!$D$6/re!$C$6) -> 48.348965 | Z5: =SUM(AA5:AE5) -> 3.7302161 | AA5: =((Y5*277.8)/(re!$B$10*8760))*re!$C$10 -> 2.114839 | AB5: =((Y5*277.8)/(re!$B$11*8760))*re!$C$11 -> 0.7862863 | AC5: =((Y5*277.8)/(re!$B$12*8760))*re!$C$12 -> 0.28393672 | AD5: =((Y5*277.8)/(re!$B$13*8760))*re!$C$13 -> 0.083329254 | AE5: =((Y5*277.8)/(re!$B$14*8760))*re!$C$14 -> 0.46182478 | AF5: =SUM('1'!AD11:AL11)+'1'!AA11 -> 138.29074 | AG5: =SUM('2'!AD11:AL11)+'2'!AA11 -> 2.6181408 | AH5: =SUM('3'!AD11:AL11)+'3'!AA11 -> 11.273012 | AI5: =SUM('4'!AD11:AL11)+'4'!AA11 -> 0.83949839 | AJ5: =SUM('5'!AD11:AL11)+'5'!AA11 -> 5.1470838 | AK5: =SUM('6'!AD11:AL11)+'6'!AA11 -> 132.92387 | AL5: =SUM('7'!AD11:AL11)+'7'!AA11 -> 116.93743 | AM5: =SUM('8'!AD11:AL11)+'8'!AA11 -> 212.08417 | AN5: =SUM('9'!AD11:AL11)+'9'!AA11 -> 64.266469 | AO5: =SUM('10'!AD11:AL11)+'10'!AA11 -> 4.7186374 | AP5: =SUM('11'!AD11:AL11)+'11'!AA11 -> 5.9959651 | AQ5: =SUM('12'!AD11:AL11)+'12'!AA11 -> 1.8420839 | AR5: =SUM('13'!AD11:AL11)+'13'!AA11 -> 5.3596942 | AS5: =SUM('14'!AD11:AL11)+'14'!AA11 -> 4.1697212 | AT5: =SUM('15'!AD11:AL11)+'15'!AA11 -> 57.099024 | AU5: =SUM('16'!AD11:AL11)+'16'!AA11 -> 22.811268 | AV5: =SUM('17'!AD11:AL11)+'17'!AA11 -> 38.822399 | AW5: =SUM('18'!AD11:AL11)+'18'!AA11 -> 9.6950939 | AX5: =SUM('19'!AD11:AL11)+'19'!AA11 -> 25.273861 | AY5: =SUM('20'!AD11:AL11)+'20'!AA11 -> 1.6030535 | AZ5: =SUM('21'!AD11:AL11)+'21'!AA11 -> 0.14581614 | BA5: =SUM('22'!AD11:AL11)+'22'!AA11 -> 0.47361606 | BB5: =SUM('23'!AD11:AL11)+'23'!AA11 -> 4.7381 | BC5: =('1'!D11+'2'!D11+'3'!D11+'4'!D11+'5'!D11+'6'!D11+'7'!D11+'8'!D11+'9'!D11+'10'!D11+'12'!D11+'13'!D11+'14'!D11+'15'!D11+'16'!D11+'17'!D11+'18'!D11+'19'!D11+'20'!D11+'21'!D11+'22'!D11+'23'!D11)/('1'!D10+'2'!D10+'3'!D10+'4'!D10+'5'!D10+'6'!D10+'7'!D10+'8'!D10+'9'!D10+'10'!D10+'12'!D10+'13'!D10+'14'!D10+'15'!D10+'16'!D10+'17'!D10+'18'!D10+'19'!D10+'20'!D10+'21'!D10+'22'!D10+'23'!D10)-1 -> 0.53264861 | BD5: =('1'!E11+'2'!E11+'3'!E11+'4'!E11+'5'!E11+'6'!E11+'7'!E11+'8'!E11+'9'!E11+'10'!E11+'12'!E11+'13'!E11+'14'!E11+'15'!E11+'16'!E11+'17'!E11+'18'!E11+'19'!E11+'20'!E11+'21'!E11+'22'!E11+'23'!E11)/('1'!E10+'2'!E10+'3'!E10+'4'!E10+'5'!E10+'6'!E10+'7'!E10+'8'!E10+'9'!E10+'10'!E10+'12'!E10+'13'!E10+'14'!E10+'15'!E10+'16'!E10+'17'!E10+'18'!E10+'19'!E10+'20'!E10+'21'!E10+'22'!E10+'23'!E10)-1 -> 0.53264861 | BE5: =('1'!F11+'2'!F11+'3'!F11+'4'!F11+'5'!F11+'6'!F11+'7'!F11+'8'!F11+'9'!F11+'10'!F11+'12'!F11+'13'!F11+'14'!F11+'15'!F11+'16'!F11+'17'!F11+'18'!F11+'19'!F11+'20'!F11+'21'!F11+'22'!F11+'23'!F11)/('1'!F10+'2'!F10+'3'!F10+'4'!F10+'5'!F10+'6'!F10+'7'!F10+'8'!F10+'9'!F10+'10'!F10+'12'!F10+'13'!F10+'14'!F10+'15'!F10+'16'!F10+'17'!F10+'18'!F10+'19'!F10+'20'!F10+'21'!F10+'22'!F10+'23'!F10)-1 -> 0.53181896 | BF5: =W5/W4-1 -> 0.96427376 | BG5: 2028 | BH5: 0.04 | BI5: 0.17 | BJ5: =BI5-BH5 -> 0.13 | BK5: ='2 (RU)'!AB11+'6 (RU)'!AB11+'7 (RU)'!AB11+'9 (RU)'!AB11+'11 (RU)'!AB11+'12 (RU)'!AB11+'13 (RU)'!AB11+'16 (RU)'!AB11+'17 (RU)'!AB11+'18 (RU)'!AB11+'22 (RU)'!AB11 -> #DIV/0! | BL5: ='1 (RU)'!AB11+'2 (RU)'!AC11+'5 (RU)'!AB11+'6 (RU)'!AC11+'7 (RU)'!AC11+'9 (RU)'!AC11+'11 (RU)'!AC11+'12 (RU)'!AC11+'13 (RU)'!AC11+'15 (RU)'!AB11+'16 (RU)'!AC11+'17 (RU)'!AC11+'18 (RU)'!AC11+'19 (RU)'!AB11+'22 (RU)'!AC11 -> #DIV/0! | BN5: ='3 (RU)'!AB11+'4 (RU)'!AB11+'10 (RU)'!AB11+'20 (RU)'!AB11+'21 (RU)'!AB11+'23 (RU)'!AB11 -> #DIV/0! | BO5: ='8 (RU)'!AB11+'14 (RU)'!AB11 -> #DIV/0! | BP5: ='1 (RU)'!AD11+'2 (RU)'!AD11+'3 (RU)'!AD11+'4 (RU)'!AD11+'5 (RU)'!AD11+'6 (RU)'!AD11+'7 (RU)'!AD11+'8 (RU)'!AD11+'9 (RU)'!AD11+'10 (RU)'!AD11+'11 (RU)'!AD11+'12 (RU)'!AD11+'13 (RU)'!AD11+'14 (RU)'!AD11+'15 (RU)'!AD11+'16 (RU)'!AD11+'17 (RU)'!AD11+'18 (RU)'!AD11+'19 (RU)'!AD11+'20 (RU)'!AD11+'21 (RU)'!AD11+'22 (RU)'!AD11+'23 (RU)'!AD11 -> #DIV/0! | BQ5: ='1 (RU)'!AE11+'2 (RU)'!AE11+'3 (RU)'!AE11+'4 (RU)'!AE11+'5 (RU)'!AE11+'6 (RU)'!AE11+'7 (RU)'!AE11+'8 (RU)'!AE11+'9 (RU)'!AE11+'10 (RU)'!AE11+'11 (RU)'!AE11+'12 (RU)'!AE11+'13 (RU)'!AE11+'14 (RU)'!AE11+'15 (RU)'!AE11+'16 (RU)'!AE11+'17 (RU)'!AE11+'18 (RU)'!AE11+'19 (RU)'!AE11+'20 (RU)'!AE11+'21 (RU)'!AE11+'22 (RU)'!AE11+'23 (RU)'!AE11 -> #DIV/0! | BR5: ='1 (RU)'!AF11+'2 (RU)'!AF11+'3 (RU)'!AF11+'4 (RU)'!AF11+'5 (RU)'!AF11+'6 (RU)'!AF11+'7 (RU)'!AF11+'8 (RU)'!AF11+'9 (RU)'!AF11+'10 (RU)'!AF11+'11 (RU)'!AF11+'12 (RU)'!AF11+'13 (RU)'!AF11+'14 (RU)'!AF11+'15 (RU)'!AF11+'16 (RU)'!AF11+'17 (RU)'!AF11+'18 (RU)'!AF11+'19 (RU)'!AF11+'20 (RU)'!AF11+'21 (RU)'!AF11+'22 (RU)'!AF11+'23 (RU)'!AF11 -> #DIV/0! | BS5: ='1 (RU)'!AG11+'2 (RU)'!AG11+'3 (RU)'!AG11+'4 (RU)'!AG11+'5 (RU)'!AG11+'6 (RU)'!AG11+'7 (RU)'!AG11+'8 (RU)'!AG11+'9 (RU)'!AG11+'10 (RU)'!AG11+'11 (RU)'!AG11+'12 (RU)'!AG11+'13 (RU)'!AG11+'14 (RU)'!AG11+'15 (RU)'!AG11+'16 (RU)'!AG11+'17 (RU)'!AG11+'18 (RU)'!AG11+'19 (RU)'!AG11+'20 (RU)'!AG11+'21 (RU)'!AG11+'22 (RU)'!AG11+'23 (RU)'!AG11 -> #DIV/0! | BT5: ='1 (RU)'!AH11+'2 (RU)'!AH11+'3 (RU)'!AH11+'4 (RU)'!AH11+'5 (RU)'!AH11+'6 (RU)'!AH11+'7 (RU)'!AH11+'8 (RU)'!AH11+'9 (RU)'!AH11+'10 (RU)'!AH11+'11 (RU)'!AH11+'12 (RU)'!AH11+'13 (RU)'!AH11+'14 (RU)'!AH11+'15 (RU)'!AH11+'16 (RU)'!AH11+'17 (RU)'!AH11+'18 (RU)'!AH11+'19 (RU)'!AH11+'20 (RU)'!AH11+'21 (RU)'!AH11+'22 (RU)'!AH11+'23 (RU)'!AH11 -> #DIV/0! | BU5: ='1 (RU)'!AI11+'2 (RU)'!AI11+'3 (RU)'!AI11+'4 (RU)'!AI11+'5 (RU)'!AI11+'6 (RU)'!AI11+'7 (RU)'!AI11+'8 (RU)'!AI11+'9 (RU)'!AI11+'10 (RU)'!AI11+'11 (RU)'!AI11+'12 (RU)'!AI11+'13 (RU)'!AI11+'14 (RU)'!AI11+'15 (RU)'!AI11+'16 (RU)'!AI11+'17 (RU)'!AI11+'18 (RU)'!AI11+'19 (RU)'!AI11+'20 (RU)'!AI11+'21 (RU)'!AI11+'22 (RU)'!AI11+'23 (RU)'!AI11 -> #DIV/0! | BV5: ='1 (RU)'!AJ11+'2 (RU)'!AJ11+'3 (RU)'!AJ11+'4 (RU)'!AJ11+'5 (RU)'!AJ11+'6 (RU)'!AJ11+'7 (RU)'!AJ11+'8 (RU)'!AJ11+'9 (RU)'!AJ11+'10 (RU)'!AJ11+'11 (RU)'!AJ11+'12 (RU)'!AJ11+'13 (RU)'!AJ11+'14 (RU)'!AJ11+'15 (RU)'!AJ11+'16 (RU)'!AJ11+'17 (RU)'!AJ11+'18 (RU)'!AJ11+'19 (RU)'!AJ11+'20 (RU)'!AJ11+'21 (RU)'!AJ11+'22 (RU)'!AJ11+'23 (RU)'!AJ11 -> #DIV/0! | BW5: ='1 (RU)'!AK11+'2 (RU)'!AK11+'3 (RU)'!AK11+'4 (RU)'!AK11+'5 (RU)'!AK11+'6 (RU)'!AK11+'7 (RU)'!AK11+'8 (RU)'!AK11+'9 (RU)'!AK11+'10 (RU)'!AK11+'11 (RU)'!AK11+'12 (RU)'!AK11+'13 (RU)'!AK11+'14 (RU)'!AK11+'15 (RU)'!AK11+'16 (RU)'!AK11+'17 (RU)'!AK11+'18 (RU)'!AK11+'19 (RU)'!AK11+'20 (RU)'!AK11+'21 (RU)'!AK11+'22 (RU)'!AK11+'23 (RU)'!AK11 -> #DIV/0! | BX5: ='1 (RU)'!AL11+'2 (RU)'!AL11+'3 (RU)'!AL11+'4 (RU)'!AL11+'5 (RU)'!AL11+'6 (RU)'!AL11+'7 (RU)'!AL11+'8 (RU)'!AL11+'9 (RU)'!AL11+'10 (RU)'!AL11+'11 (RU)'!AL11+'12 (RU)'!AL11+'13 (RU)'!AL11+'14 (RU)'!AL11+'15 (RU)'!AL11+'16 (RU)'!AL11+'17 (RU)'!AL11+'18 (RU)'!AL11+'19 (RU)'!AL11+'20 (RU)'!AL11+'21 (RU)'!AL11+'22 (RU)'!AL11+'23 (RU)'!AL11 -> #DIV/0! | BY5: =SUM(BK5:BO5) -> #DIV/0! | BZ5: =SUM(BP5:BX5) -> #DIV/0! | CC5: =VLOOKUP(CC$1,emissions!$A$2:$B$5,2,FALSE)*BK5 -> #DIV/0! | CD5: =VLOOKUP(CD$1,emissions!$A$2:$B$5,2,FALSE)*BL5 -> #DIV/0! | CF5: =VLOOKUP(CF$1,emissions!$A$2:$B$5,2,FALSE)*BN5 -> #DIV/0! | CG5: =VLOOKUP(CG$1,emissions!$A$2:$B$5,2,FALSE)*BO5 -> #DIV/0! | CH5: =BP5*(emissions!$D$3*production!$B$4+emissions!$D$4*production!$C$4+emissions!$D$5*production!$D$4+emissions!$D$6*production!$E$4) -> #DIV/0! | CI5: =BQ5*(emissions!$D$3*production!$B$4+emissions!$D$4*production!$C$4+emissions!$D$5*production!$D$4+emissions!$D$6*production!$E$4) -> #DIV/0! | CJ5: =BR5*(emissions!$D$8*production!$B$6+emissions!$D$9*production!$C$6+emissions!$D$10*production!$D$6) -> #DIV/0! | CK5: =BS5*(emissions!$D$12*production!$B$8+emissions!$D$13*production!$C$8+emissions!$D$14*production!$D$8) -> #DIV/0! | CL5: =BT5*(emissions!$D$16*production!$B$10+production!$C$10*emissions!$D$17) -> #DIV/0! | CM5: =BU5*(emissions!$D$19*production!$B$12+production!$C$12*emissions!$D$20+emissions!$D$21*production!$D$12) -> #DIV/0! | CN5: =BV5*(emissions!$D$23*production!$B$14+production!$C$14*emissions!$D$24+emissions!$D$25*production!$D$14) -> #DIV/0! | CO5: =BW5*(emissions!$D$27*production!$B$16+production!$C$16*emissions!$D$28+production!$D$16*emissions!$D$29) -> #DIV/0! | CP5: 0 | CS5: =SUM(CC5:CP5) -> #DIV/0! | CT5: =SUM(CC5:CP5)/SUM(BK5:BX5) -> #DIV/0! | CU5: =(CT5-CW5) -> #DIV/0! | CV5: =CT5-CX5 -> #DIV/0! | CW5: =93.3*(1-BH5) -> 89.568 | CX5: =93.3*(1-BI5) -> 77.439 | CY5: =IF(G5<2028,0,IF(CT5>=CW5,CU5,IF(AND(CT5<CW5,CT5>=CX5),CV5,0))*SUM(BK5:BX5)) -> #DIV/0! | CZ5: =IF(CT5>=CW5,380*CY5,IF(AND(CT5<CW5,CT5>=CX5),100*CY5,0)) -> #DIV/0! | DA5: =IF(G5<2028,"",IF(CT5>=CW5,"Red",IF(AND(CT5<CW5,CT5>=CX5),"Yellow","Green"))) -> #DIV/0! | DB5: =IF(G5<2028,0,IF(CT5<CX5,-CV5*SUM(BK5:BX5),0)) -> #DIV/0! | DC5: =DB5*380 -> #DIV/0! | DD5: 2028 | DE5: =CY5-DB5 -> #DIV/0! | DF5: =CS5 -> #DIV/0! | DG5: 2028 | DH5: =CW5*SUM(BK5:BX5) -> #DIV/0! | DI5: =CX5*SUM(BK5:BX5) -> #DIV/0! | DJ5: =DI5 -> #DIV/0! | DK5: =DH5-DI5 -> #DIV/0! | DL5: =MAX(DH5:DK5) -> #DIV/0! | DM5: =(CZ5-DC5)/1000000 -> #DIV/0! | DN5: =DE5/1000000 -> #DIV/0! | DO5: =ED5/1000000 -> #DIV/0! | DP5: =DM5+DO5 -> #DIV/0! | DQ5: 17206 | DR5: 9518 | DT5: 639 | DU5: 2174 | DV5: =DQ5*VLOOKUP(DQ$1,emissions!$A$2:$B$5,2,FALSE) -> 2512076 | DW5: =DR5*VLOOKUP(DR$1,emissions!$A$2:$B$5,2,FALSE) -> 1389628 | DY5: =DT5*VLOOKUP(DT$1,emissions!$A$2:$B$5,2,FALSE) -> 92655 | DZ5: =DU5*VLOOKUP(DU$1,emissions!$A$2:$B$5,2,FALSE) -> 245662 | EA5: =SUM(DV5:DZ5) -> 4240021 | EB5: =1/(SUM(DQ5:DU5)/EA5) -> 143.54948 | ED5: =SUM(EE5:ER5) -> #DIV/0! | EE5: =cost!$B$2*BK5 -> #DIV/0! | EF5: =cost!$B$3*BL5 -> #DIV/0! | EH5: =cost!$B$4*BN5 -> #DIV/0! | EI5: =cost!$B$5*$BO$2 -> #DIV/0! | EJ5: =BP5*(cost!$D$3*production!$B$4+production!$C$4*cost!$D$4+cost!$D$5*production!$D$4+production!$E$4*cost!$D$6) -> #DIV/0! | EK5: =BQ5*(cost!$D$3*production!$B$4+production!$C$4*cost!$D$4+cost!$D$5*production!$D$4+production!$E$4*cost!$D$6) -> #DIV/0! | EL5: =BR5*(cost!$D$8*production!$B$6+cost!$D$9*production!$C$6+$D$10*production!$D$6) -> #DIV/0! | EM5: =BS5*(cost!$D$12*production!$B$8+cost!$D$13*production!$C$8+cost!$D$14*production!$D$8) -> #DIV/0! | EN5: =BT5*(cost!$D$16*production!$B$10+production!$C$10*cost!$D$17) -> #DIV/0! | EO5: =BU5*(cost!$D$19*production!$B$12+production!$C$12*cost!$D$20+cost!$D$21*production!$D$12) -> #DIV/0! | EP5: =BV5*(cost!$D$23*production!$B$14+production!$C$14*cost!$D$24+cost!$D$25*production!$D$14) -> #DIV/0! | EQ5: =BW5*(cost!$D$27*production!$B$16+production!$C$16*cost!$D$28+cost!$D$29*production!$D$16) -> #DIV/0! | ER5: =BX5*(re!$H$10*re!$C$10+re!$H$11*re!$C$11+re!$H$12*re!$C$12+re!$H$13*re!$C$13+re!$H$14*re!$C$14) -> #DIV/0!
A6: Sailing & hybrid | B6: 0.01 | C6: 0.4 | D6: 10 | G6: 2029 | H6: ='2'!AB12+'6'!AB12+'7'!AB12+'9'!AB12+'11'!AB12+'12'!AB12+'13'!AB12+'16'!AB12+'17'!AB12+'18'!AB12+'22'!AB12 -> 292.73834 | I6: ='1'!AB12+'2'!AC12+'5'!AB12+'6'!AC12+'7'!AC12+'9'!AC12+'11'!AC12+'12'!AC12+'13'!AC12+'15'!AB12+'16'!AC12+'17'!AC12+'18'!AC12+'19'!AB12+'22'!AC12 -> 311.82228 | K6: ='3'!AB12+'4'!AB12+'10'!AB12+'20'!AB12+'21'!AB12+'23'!AB12 -> 22.515804 | L6: ='8'!AB12+'14'!AB12 -> 207.79749 | M6: ='1'!AD12+'2'!AD12+'3'!AD12+'4'!AD12+'5'!AD12+'6'!AD12+'7'!AD12+'8'!AD12+'9'!AD12+'10'!AD12+'11'!AD12+'12'!AD12+'13'!AD12+'14'!AD12+'15'!AD12+'16'!AD12+'17'!AD12+'18'!AD12+'19'!AD12+'20'!AD12+'21'!AD12+'22'!AD12+'23'!AD12 -> 8.2135826 | N6: ='1'!AE12+'2'!AE12+'3'!AE12+'4'!AE12+'5'!AE12+'6'!AE12+'7'!AE12+'8'!AE12+'9'!AE12+'10'!AE12+'11'!AE12+'12'!AE12+'13'!AE12+'14'!AE12+'15'!AE12+'16'!AE12+'17'!AE12+'18'!AE12+'19'!AE12+'20'!AE12+'21'!AE12+'22'!AE12+'23'!AE12 -> 0.48705465 | O6: ='1'!AF12+'2'!AF12+'3'!AF12+'4'!AF12+'5'!AF12+'6'!AF12+'7'!AF12+'8'!AF12+'9'!AF12+'10'!AF12+'11'!AF12+'12'!AF12+'13'!AF12+'14'!AF12+'15'!AF12+'16'!AF12+'17'!AF12+'18'!AF12+'19'!AF12+'20'!AF12+'21'!AF12+'22'!AF12+'23'!AF12 -> 15.739472 | P6: ='1'!AG12+'2'!AG12+'3'!AG12+'4'!AG12+'5'!AG12+'6'!AG12+'7'!AG12+'8'!AG12+'9'!AG12+'10'!AG12+'11'!AG12+'12'!AG12+'13'!AG12+'14'!AG12+'15'!AG12+'16'!AG12+'17'!AG12+'18'!AG12+'19'!AG12+'20'!AG12+'21'!AG12+'22'!AG12+'23'!AG12 -> 14.314782 | Q6: ='1'!AH12+'2'!AH12+'3'!AH12+'4'!AH12+'5'!AH12+'6'!AH12+'7'!AH12+'8'!AH12+'9'!AH12+'10'!AH12+'11'!AH12+'12'!AH12+'13'!AH12+'14'!AH12+'15'!AH12+'16'!AH12+'17'!AH12+'18'!AH12+'19'!AH12+'20'!AH12+'21'!AH12+'22'!AH12+'23'!AH12 -> 0.36945054 | R6: ='1'!AI12+'2'!AI12+'3'!AI12+'4'!AI12+'5'!AI12+'6'!AI12+'7'!AI12+'8'!AI12+'9'!AI12+'10'!AI12+'11'!AI12+'12'!AI12+'13'!AI12+'14'!AI12+'15'!AI12+'16'!AI12+'17'!AI12+'18'!AI12+'19'!AI12+'20'!AI12+'21'!AI12+'22'!AI12+'23'!AI12 -> 2.4845542 | S6: ='1'!AJ12+'2'!AJ12+'3'!AJ12+'4'!AJ12+'5'!AJ12+'6'!AJ12+'7'!AJ12+'8'!AJ12+'9'!AJ12+'10'!AJ12+'11'!AJ12+'12'!AJ12+'13'!AJ12+'14'!AJ12+'15'!AJ12+'16'!AJ12+'17'!AJ12+'18'!AJ12+'19'!AJ12+'20'!AJ12+'21'!AJ12+'22'!AJ12+'23'!AJ12 -> 0.70735616 | T6: ='1'!AK12+'2'!AK12+'3'!AK12+'4'!AK12+'5'!AK12+'6'!AK12+'7'!AK12+'8'!AK12+'9'!AK12+'10'!AK12+'11'!AK12+'12'!AK12+'13'!AK12+'14'!AK12+'15'!AK12+'16'!AK12+'17'!AK12+'18'!AK12+'19'!AK12+'20'!AK12+'21'!AK12+'22'!AK12+'23'!AK12 -> 7.7804794 | U6: ='1'!AL12+'2'!AL12+'3'!AL12+'4'!AL12+'5'!AL12+'6'!AL12+'7'!AL12+'8'!AL12+'9'!AL12+'10'!AL12+'11'!AL12+'12'!AL12+'13'!AL12+'14'!AL12+'15'!AL12+'16'!AL12+'17'!AL12+'18'!AL12+'19'!AL12+'20'!AL12+'21'!AL12+'22'!AL12+'23'!AL12 -> 0.018818768 | V6: =SUM(H6:L6) -> 834.87391 | W6: =SUM(M6:U6) -> 50.11555 | X6: =W6/W5-1 -> 0.75888153 | Y6: =((M6+N6)*re!$D$2/re!$C$2+O6*re!$D$3/re!$C$3+P6*re!$D$4/re!$C$4+T6*re!$D$5/re!$C$5+U6*re!$D$6/re!$C$6) -> 85.041719 | Z6: =SUM(AA6:AE6) -> 6.5611329 | AA6: =((Y6*277.8)/(re!$B$10*8760))*re!$C$10 -> 3.719822 | AB6: =((Y6*277.8)/(re!$B$11*8760))*re!$C$11 -> 1.3830108 | AC6: =((Y6*277.8)/(re!$B$12*8760))*re!$C$12 -> 0.49942055 | AD6: =((Y6*277.8)/(re!$B$13*8760))*re!$C$13 -> 0.14656907 | AE6: =((Y6*277.8)/(re!$B$14*8760))*re!$C$14 -> 0.81231053 | AF6: =SUM('1'!AD12:AL12)+'1'!AA12 -> 140.94076 | AG6: =SUM('2'!AD12:AL12)+'2'!AA12 -> 2.6686758 | AH6: =SUM('3'!AD12:AL12)+'3'!AA12 -> 11.513111 | AI6: =SUM('4'!AD12:AL12)+'4'!AA12 -> 0.85768956 | AJ6: =SUM('5'!AD12:AL12)+'5'!AA12 -> 5.2454362 | AK6: =SUM('6'!AD12:AL12)+'6'!AA12 -> 135.39979 | AL6: =SUM('7'!AD12:AL12)+'7'!AA12 -> 119.18902 | AM6: =SUM('8'!AD12:AL12)+'8'!AA12 -> 217.31045 | AN6: =SUM('9'!AD12:AL12)+'9'!AA12 -> 65.494497 | AO6: =SUM('10'!AD12:AL12)+'10'!AA12 -> 4.8142428 | AP6: =SUM('11'!AD12:AL12)+'11'!AA12 -> 6.1166668 | AQ6: =SUM('12'!AD12:AL12)+'12'!AA12 -> 1.879166 | AR6: =SUM('13'!AD12:AL12)+'13'!AA12 -> 5.4675875 | AS6: =SUM('14'!AD12:AL12)+'14'!AA12 -> 4.2660391 | AT6: =SUM('15'!AD12:AL12)+'15'!AA12 -> 58.190094 | AU6: =SUM('16'!AD12:AL12)+'16'!AA12 -> 23.270471 | AV6: =SUM('17'!AD12:AL12)+'17'!AA12 -> 39.603913 | AW6: =SUM('18'!AD12:AL12)+'18'!AA12 -> 9.890261 | AX6: =SUM('19'!AD12:AL12)+'19'!AA12 -> 25.756804 | AY6: =SUM('20'!AD12:AL12)+'20'!AA12 -> 1.6377902 | AZ6: =SUM('21'!AD12:AL12)+'21'!AA12 -> 0.14882658 | BA6: =SUM('22'!AD12:AL12)+'22'!AA12 -> 0.4826661 | BB6: =SUM('23'!AD12:AL12)+'23'!AA12 -> 4.8455061 | BC6: =('1'!D12+'2'!D12+'3'!D12+'4'!D12+'5'!D12+'6'!D12+'7'!D12+'8'!D12+'9'!D12+'10'!D12+'12'!D12+'13'!D12+'14'!D12+'15'!D12+'16'!D12+'17'!D12+'18'!D12+'19'!D12+'20'!D12+'21'!D12+'22'!D12+'23'!D12)/('1'!D11+'2'!D11+'3'!D11+'4'!D11+'5'!D11+'6'!D11+'7'!D11+'8'!D11+'9'!D11+'10'!D11+'12'!D11+'13'!D11+'14'!D11+'15'!D11+'16'!D11+'17'!D11+'18'!D11+'19'!D11+'20'!D11+'21'!D11+'22'!D11+'23'!D11)-1 -> 0.36215023 | BD6: =('1'!E12+'2'!E12+'3'!E12+'4'!E12+'5'!E12+'6'!E12+'7'!E12+'8'!E12+'9'!E12+'10'!E12+'12'!E12+'13'!E12+'14'!E12+'15'!E12+'16'!E12+'17'!E12+'18'!E12+'19'!E12+'20'!E12+'21'!E12+'22'!E12+'23'!E12)/('1'!E11+'2'!E11+'3'!E11+'4'!E11+'5'!E11+'6'!E11+'7'!E11+'8'!E11+'9'!E11+'10'!E11+'12'!E11+'13'!E11+'14'!E11+'15'!E11+'16'!E11+'17'!E11+'18'!E11+'19'!E11+'20'!E11+'21'!E11+'22'!E11+'23'!E11)-1 -> 0.36215023 | BE6: =('1'!F12+'2'!F12+'3'!F12+'4'!F12+'5'!F12+'6'!F12+'7'!F12+'8'!F12+'9'!F12+'10'!F12+'12'!F12+'13'!F12+'14'!F12+'15'!F12+'16'!F12+'17'!F12+'18'!F12+'19'!F12+'20'!F12+'21'!F12+'22'!F12+'23'!F12)/('1'!F11+'2'!F11+'3'!F11+'4'!F11+'5'!F11+'6'!F11+'7'!F11+'8'!F11+'9'!F11+'10'!F11+'12'!F11+'13'!F11+'14'!F11+'15'!F11+'16'!F11+'17'!F11+'18'!F11+'19'!F11+'20'!F11+'21'!F11+'22'!F11+'23'!F11)-1 -> 0.3615942 | BF6: =W6/W5-1 -> 0.75888153 | BG6: 2029 | BH6: 0.06 | BI6: 0.19 | BJ6: =BI6-BH6 -> 0.13 | BK6: ='2 (RU)'!AB12+'6 (RU)'!AB12+'7 (RU)'!AB12+'9 (RU)'!AB12+'11 (RU)'!AB12+'12 (RU)'!AB12+'13 (RU)'!AB12+'16 (RU)'!AB12+'17 (RU)'!AB12+'18 (RU)'!AB12+'22 (RU)'!AB12 -> #DIV/0! | BL6: ='1 (RU)'!AB12+'2 (RU)'!AC12+'5 (RU)'!AB12+'6 (RU)'!AC12+'7 (RU)'!AC12+'9 (RU)'!AC12+'11 (RU)'!AC12+'12 (RU)'!AC12+'13 (RU)'!AC12+'15 (RU)'!AB12+'16 (RU)'!AC12+'17 (RU)'!AC12+'18 (RU)'!AC12+'19 (RU)'!AB12+'22 (RU)'!AC12 -> #DIV/0! | BN6: ='3 (RU)'!AB12+'4 (RU)'!AB12+'10 (RU)'!AB12+'20 (RU)'!AB12+'21 (RU)'!AB12+'23 (RU)'!AB12 -> #DIV/0! | BO6: ='8 (RU)'!AB12+'14 (RU)'!AB12 -> #DIV/0! | BP6: ='1 (RU)'!AD12+'2 (RU)'!AD12+'3 (RU)'!AD12+'4 (RU)'!AD12+'5 (RU)'!AD12+'6 (RU)'!AD12+'7 (RU)'!AD12+'8 (RU)'!AD12+'9 (RU)'!AD12+'10 (RU)'!AD12+'11 (RU)'!AD12+'12 (RU)'!AD12+'13 (RU)'!AD12+'14 (RU)'!AD12+'15 (RU)'!AD12+'16 (RU)'!AD12+'17 (RU)'!AD12+'18 (RU)'!AD12+'19 (RU)'!AD12+'20 (RU)'!AD12+'21 (RU)'!AD12+'22 (RU)'!AD12+'23 (RU)'!AD12 -> #DIV/0! | BQ6: ='1 (RU)'!AE12+'2 (RU)'!AE12+'3 (RU)'!AE12+'4 (RU)'!AE12+'5 (RU)'!AE12+'6 (RU)'!AE12+'7 (RU)'!AE12+'8 (RU)'!AE12+'9 (RU)'!AE12+'10 (RU)'!AE12+'11 (RU)'!AE12+'12 (RU)'!AE12+'13 (RU)'!AE12+'14 (RU)'!AE12+'15 (RU)'!AE12+'16 (RU)'!AE12+'17 (RU)'!AE12+'18 (RU)'!AE12+'19 (RU)'!AE12+'20 (RU)'!AE12+'21 (RU)'!AE12+'22 (RU)'!AE12+'23 (RU)'!AE12 -> #DIV/0! | BR6: ='1 (RU)'!AF12+'2 (RU)'!AF12+'3 (RU)'!AF12+'4 (RU)'!AF12+'5 (RU)'!AF12+'6 (RU)'!AF12+'7 (RU)'!AF12+'8 (RU)'!AF12+'9 (RU)'!AF12+'10 (RU)'!AF12+'11 (RU)'!AF12+'12 (RU)'!AF12+'13 (RU)'!AF12+'14 (RU)'!AF12+'15 (RU)'!AF12+'16 (RU)'!AF12+'17 (RU)'!AF12+'18 (RU)'!AF12+'19 (RU)'!AF12+'20 (RU)'!AF12+'21 (RU)'!AF12+'22 (RU)'!AF12+'23 (RU)'!AF12 -> #DIV/0! | BS6: ='1 (RU)'!AG12+'2 (RU)'!AG12+'3 (RU)'!AG12+'4 (RU)'!AG12+'5 (RU)'!AG12+'6 (RU)'!AG12+'7 (RU)'!AG12+'8 (RU)'!AG12+'9 (RU)'!AG12+'10 (RU)'!AG12+'11 (RU)'!AG12+'12 (RU)'!AG12+'13 (RU)'!AG12+'14 (RU)'!AG12+'15 (RU)'!AG12+'16 (RU)'!AG12+'17 (RU)'!AG12+'18 (RU)'!AG12+'19 (RU)'!AG12+'20 (RU)'!AG12+'21 (RU)'!AG12+'22 (RU)'!AG12+'23 (RU)'!AG12 -> #DIV/0! | BT6: ='1 (RU)'!AH12+'2 (RU)'!AH12+'3 (RU)'!AH12+'4 (RU)'!AH12+'5 (RU)'!AH12+'6 (RU)'!AH12+'7 (RU)'!AH12+'8 (RU)'!AH12+'9 (RU)'!AH12+'10 (RU)'!AH12+'11 (RU)'!AH12+'12 (RU)'!AH12+'13 (RU)'!AH12+'14 (RU)'!AH12+'15 (RU)'!AH12+'16 (RU)'!AH12+'17 (RU)'!AH12+'18 (RU)'!AH12+'19 (RU)'!AH12+'20 (RU)'!AH12+'21 (RU)'!AH12+'22 (RU)'!AH12+'23 (RU)'!AH12 -> #DIV/0! | BU6: ='1 (RU)'!AI12+'2 (RU)'!AI12+'3 (RU)'!AI12+'4 (RU)'!AI12+'5 (RU)'!AI12+'6 (RU)'!AI12+'7 (RU)'!AI12+'8 (RU)'!AI12+'9 (RU)'!AI12+'10 (RU)'!AI12+'11 (RU)'!AI12+'12 (RU)'!AI12+'13 (RU)'!AI12+'14 (RU)'!AI12+'15 (RU)'!AI12+'16 (RU)'!AI12+'17 (RU)'!AI12+'18 (RU)'!AI12+'19 (RU)'!AI12+'20 (RU)'!AI12+'21 (RU)'!AI12+'22 (RU)'!AI12+'23 (RU)'!AI12 -> #DIV/0! | BV6: ='1 (RU)'!AJ12+'2 (RU)'!AJ12+'3 (RU)'!AJ12+'4 (RU)'!AJ12+'5 (RU)'!AJ12+'6 (RU)'!AJ12+'7 (RU)'!AJ12+'8 (RU)'!AJ12+'9 (RU)'!AJ12+'10 (RU)'!AJ12+'11 (RU)'!AJ12+'12 (RU)'!AJ12+'13 (RU)'!AJ12+'14 (RU)'!AJ12+'15 (RU)'!AJ12+'16 (RU)'!AJ12+'17 (RU)'!AJ12+'18 (RU)'!AJ12+'19 (RU)'!AJ12+'20 (RU)'!AJ12+'21 (RU)'!AJ12+'22 (RU)'!AJ12+'23 (RU)'!AJ12 -> #DIV/0! | BW6: ='1 (RU)'!AK12+'2 (RU)'!AK12+'3 (RU)'!AK12+'4 (RU)'!AK12+'5 (RU)'!AK12+'6 (RU)'!AK12+'7 (RU)'!AK12+'8 (RU)'!AK12+'9 (RU)'!AK12+'10 (RU)'!AK12+'11 (RU)'!AK12+'12 (RU)'!AK12+'13 (RU)'!AK12+'14 (RU)'!AK12+'15 (RU)'!AK12+'16 (RU)'!AK12+'17 (RU)'!AK12+'18 (RU)'!AK12+'19 (RU)'!AK12+'20 (RU)'!AK12+'21 (RU)'!AK12+'22 (RU)'!AK12+'23 (RU)'!AK12 -> #DIV/0! | BX6: ='1 (RU)'!AL12+'2 (RU)'!AL12+'3 (RU)'!AL12+'4 (RU)'!AL12+'5 (RU)'!AL12+'6 (RU)'!AL12+'7 (RU)'!AL12+'8 (RU)'!AL12+'9 (RU)'!AL12+'10 (RU)'!AL12+'11 (RU)'!AL12+'12 (RU)'!AL12+'13 (RU)'!AL12+'14 (RU)'!AL12+'15 (RU)'!AL12+'16 (RU)'!AL12+'17 (RU)'!AL12+'18 (RU)'!AL12+'19 (RU)'!AL12+'20 (RU)'!AL12+'21 (RU)'!AL12+'22 (RU)'!AL12+'23 (RU)'!AL12 -> #DIV/0! | BY6: =SUM(BK6:BO6) -> #DIV/0! | BZ6: =SUM(BP6:BX6) -> #DIV/0! | CC6: =VLOOKUP(CC$1,emissions!$A$2:$B$5,2,FALSE)*BK6 -> #DIV/0! | CD6: =VLOOKUP(CD$1,emissions!$A$2:$B$5,2,FALSE)*BL6 -> #DIV/0! | CF6: =VLOOKUP(CF$1,emissions!$A$2:$B$5,2,FALSE)*BN6 -> #DIV/0! | CG6: =VLOOKUP(CG$1,emissions!$A$2:$B$5,2,FALSE)*BO6 -> #DIV/0! | CH6: =BP6*(emissions!$D$3*production!$B$4+emissions!$D$4*production!$C$4+emissions!$D$5*production!$D$4+emissions!$D$6*production!$E$4) -> #DIV/0! | CI6: =BQ6*(emissions!$D$3*production!$B$4+emissions!$D$4*production!$C$4+emissions!$D$5*production!$D$4+emissions!$D$6*production!$E$4) -> #DIV/0! | CJ6: =BR6*(emissions!$D$8*production!$B$6+emissions!$D$9*production!$C$6+emissions!$D$10*production!$D$6) -> #DIV/0! | CK6: =BS6*(emissions!$D$12*production!$B$8+emissions!$D$13*production!$C$8+emissions!$D$14*production!$D$8) -> #DIV/0! | CL6: =BT6*(emissions!$D$16*production!$B$10+production!$C$10*emissions!$D$17) -> #DIV/0! | CM6: =BU6*(emissions!$D$19*production!$B$12+production!$C$12*emissions!$D$20+emissions!$D$21*production!$D$12) -> #DIV/0! | CN6: =BV6*(emissions!$D$23*production!$B$14+production!$C$14*emissions!$D$24+emissions!$D$25*production!$D$14) -> #DIV/0! | CO6: =BW6*(emissions!$D$27*production!$B$16+production!$C$16*emissions!$D$28+production!$D$16*emissions!$D$29) -> #DIV/0! | CP6: 0 | CS6: =SUM(CC6:CP6) -> #DIV/0! | CT6: =SUM(CC6:CP6)/SUM(BK6:BX6) -> #DIV/0! | CU6: =(CT6-CW6) -> #DIV/0! | CV6: =CT6-CX6 -> #DIV/0! | CW6: =93.3*(1-BH6) -> 87.702 | CX6: =93.3*(1-BI6) -> 75.573 | CY6: =IF(G6<2028,0,IF(CT6>=CW6,CU6,IF(AND(CT6<CW6,CT6>=CX6),CV6,0))*SUM(BK6:BX6)) -> #DIV/0! | CZ6: =IF(CT6>=CW6,380*CY6,IF(AND(CT6<CW6,CT6>=CX6),100*CY6,0)) -> #DIV/0! | DA6: =IF(G6<2028,"",IF(CT6>=CW6,"Red",IF(AND(CT6<CW6,CT6>=CX6),"Yellow","Green"))) -> #DIV/0! | DB6: =IF(G6<2028,0,IF(CT6<CX6,-CV6*SUM(BK6:BX6),0)) -> #DIV/0! | DC6: =DB6*380 -> #DIV/0! | DD6: 2029 | DE6: =CY6-DB6 -> #DIV/0! | DF6: =CS6 -> #DIV/0! | DG6: 2029 | DH6: =CW6*SUM(BK6:BX6) -> #DIV/0! | DI6: =CX6*SUM(BK6:BX6) -> #DIV/0! | DJ6: =DI6 -> #DIV/0! | DK6: =DH6-DI6 -> #DIV/0! | DL6: =MAX(DH6:DK6) -> #DIV/0! | DM6: =(CZ6-DC6)/1000000 -> #DIV/0! | DN6: =DE6/1000000 -> #DIV/0! | DO6: =ED6/1000000 -> #DIV/0! | DP6: =DM6+DO6 -> #DIV/0! | DQ6: 16559 | DR6: 10647 | DT6: 651 | DU6: 2218 | DV6: =DQ6*VLOOKUP(DQ$1,emissions!$A$2:$B$5,2,FALSE) -> 2417614 | DW6: =DR6*VLOOKUP(DR$1,emissions!$A$2:$B$5,2,FALSE) -> 1554462 | DY6: =DT6*VLOOKUP(DT$1,emissions!$A$2:$B$5,2,FALSE) -> 94395 | DZ6: =DU6*VLOOKUP(DU$1,emissions!$A$2:$B$5,2,FALSE) -> 250634 | EA6: =SUM(DV6:DZ6) -> 4317105 | EB6: =1/(SUM(DQ6:DU6)/EA6) -> 143.54464 | ED6: =SUM(EE6:ER6) -> #DIV/0! | EE6: =cost!$B$2*BK6 -> #DIV/0! | EF6: =cost!$B$3*BL6 -> #DIV/0! | EH6: =cost!$B$4*BN6 -> #DIV/0! | EI6: =cost!$B$5*$BO$2 -> #DIV/0! | EJ6: =BP6*(cost!$D$3*production!$B$4+production!$C$4*cost!$D$4+cost!$D$5*production!$D$4+production!$E$4*cost!$D$6) -> #DIV/0! | EK6: =BQ6*(cost!$D$3*production!$B$4+production!$C$4*cost!$D$4+cost!$D$5*production!$D$4+production!$E$4*cost!$D$6) -> #DIV/0! | EL6: =BR6*(cost!$D$8*production!$B$6+cost!$D$9*production!$C$6+$D$10*production!$D$6) -> #DIV/0! | EM6: =BS6*(cost!$D$12*production!$B$8+cost!$D$13*production!$C$8+cost!$D$14*production!$D$8) -> #DIV/0! | EN6: =BT6*(cost!$D$16*production!$B$10+production!$C$10*cost!$D$17) -> #DIV/0! | EO6: =BU6*(cost!$D$19*production!$B$12+production!$C$12*cost!$D$20+cost!$D$21*production!$D$12) -> #DIV/0! | EP6: =BV6*(cost!$D$23*production!$B$14+production!$C$14*cost!$D$24+cost!$D$25*production!$D$14) -> #DIV/0! | EQ6: =BW6*(cost!$D$27*production!$B$16+production!$C$16*cost!$D$28+cost!$D$29*production!$D$16) -> #DIV/0! | ER6: =BX6*(re!$H$10*re!$C$10+re!$H$11*re!$C$11+re!$H$12*re!$C$12+re!$H$13*re!$C$13+re!$H$14*re!$C$14) -> #DIV/0!
B7: k | G7: 2030 | H7: ='2'!AB13+'6'!AB13+'7'!AB13+'9'!AB13+'11'!AB13+'12'!AB13+'13'!AB13+'16'!AB13+'17'!AB13+'18'!AB13+'22'!AB13 -> 259.43242 | I7: ='1'!AB13+'2'!AC13+'5'!AB13+'6'!AC13+'7'!AC13+'9'!AC13+'11'!AC13+'12'!AC13+'13'!AC13+'15'!AB13+'16'!AC13+'17'!AC13+'18'!AC13+'19'!AB13+'22'!AC13 -> 334.94359 | K7: ='3'!AB13+'4'!AB13+'10'!AB13+'20'!AB13+'21'!AB13+'23'!AB13 -> 22.186085 | L7: ='8'!AB13+'14'!AB13 -> 204.7091 | M7: ='1'!AD13+'2'!AD13+'3'!AD13+'4'!AD13+'5'!AD13+'6'!AD13+'7'!AD13+'8'!AD13+'9'!AD13+'10'!AD13+'11'!AD13+'12'!AD13+'13'!AD13+'14'!AD13+'15'!AD13+'16'!AD13+'17'!AD13+'18'!AD13+'19'!AD13+'20'!AD13+'21'!AD13+'22'!AD13+'23'!AD13 -> 13.575637 | N7: ='1'!AE13+'2'!AE13+'3'!AE13+'4'!AE13+'5'!AE13+'6'!AE13+'7'!AE13+'8'!AE13+'9'!AE13+'10'!AE13+'11'!AE13+'12'!AE13+'13'!AE13+'14'!AE13+'15'!AE13+'16'!AE13+'17'!AE13+'18'!AE13+'19'!AE13+'20'!AE13+'21'!AE13+'22'!AE13+'23'!AE13 -> 0.80500206 | O7: ='1'!AF13+'2'!AF13+'3'!AF13+'4'!AF13+'5'!AF13+'6'!AF13+'7'!AF13+'8'!AF13+'9'!AF13+'10'!AF13+'11'!AF13+'12'!AF13+'13'!AF13+'14'!AF13+'15'!AF13+'16'!AF13+'17'!AF13+'18'!AF13+'19'!AF13+'20'!AF13+'21'!AF13+'22'!AF13+'23'!AF13 -> 26.01328 | P7: ='1'!AG13+'2'!AG13+'3'!AG13+'4'!AG13+'5'!AG13+'6'!AG13+'7'!AG13+'8'!AG13+'9'!AG13+'10'!AG13+'11'!AG13+'12'!AG13+'13'!AG13+'14'!AG13+'15'!AG13+'16'!AG13+'17'!AG13+'18'!AG13+'19'!AG13+'20'!AG13+'21'!AG13+'22'!AG13+'23'!AG13 -> 23.660924 | Q7: ='1'!AH13+'2'!AH13+'3'!AH13+'4'!AH13+'5'!AH13+'6'!AH13+'7'!AH13+'8'!AH13+'9'!AH13+'10'!AH13+'11'!AH13+'12'!AH13+'13'!AH13+'14'!AH13+'15'!AH13+'16'!AH13+'17'!AH13+'18'!AH13+'19'!AH13+'20'!AH13+'21'!AH13+'22'!AH13+'23'!AH13 -> 0.60999285 | R7: ='1'!AI13+'2'!AI13+'3'!AI13+'4'!AI13+'5'!AI13+'6'!AI13+'7'!AI13+'8'!AI13+'9'!AI13+'10'!AI13+'11'!AI13+'12'!AI13+'13'!AI13+'14'!AI13+'15'!AI13+'16'!AI13+'17'!AI13+'18'!AI13+'19'!AI13+'20'!AI13+'21'!AI13+'22'!AI13+'23'!AI13 -> 4.1066145 | S7: ='1'!AJ13+'2'!AJ13+'3'!AJ13+'4'!AJ13+'5'!AJ13+'6'!AJ13+'7'!AJ13+'8'!AJ13+'9'!AJ13+'10'!AJ13+'11'!AJ13+'12'!AJ13+'13'!AJ13+'14'!AJ13+'15'!AJ13+'16'!AJ13+'17'!AJ13+'18'!AJ13+'19'!AJ13+'20'!AJ13+'21'!AJ13+'22'!AJ13+'23'!AJ13 -> 1.1679572 | T7: ='1'!AK13+'2'!AK13+'3'!AK13+'4'!AK13+'5'!AK13+'6'!AK13+'7'!AK13+'8'!AK13+'9'!AK13+'10'!AK13+'11'!AK13+'12'!AK13+'13'!AK13+'14'!AK13+'15'!AK13+'16'!AK13+'17'!AK13+'18'!AK13+'19'!AK13+'20'!AK13+'21'!AK13+'22'!AK13+'23'!AK13 -> 12.8631 | U7: ='1'!AL13+'2'!AL13+'3'!AL13+'4'!AL13+'5'!AL13+'6'!AL13+'7'!AL13+'8'!AL13+'9'!AL13+'10'!AL13+'11'!AL13+'12'!AL13+'13'!AL13+'14'!AL13+'15'!AL13+'16'!AL13+'17'!AL13+'18'!AL13+'19'!AL13+'20'!AL13+'21'!AL13+'22'!AL13+'23'!AL13 -> 0.03114952 | V7: =SUM(H7:L7) -> 821.2712 | W7: =SUM(M7:U7) -> 82.833657 | X7: =W7/W6-1 -> 0.65285338 | Y7: =((M7+N7)*re!$D$2/re!$C$2+O7*re!$D$3/re!$C$3+P7*re!$D$4/re!$C$4+T7*re!$D$5/re!$C$5+U7*re!$D$6/re!$C$6) -> 140.56417 | Z7: =SUM(AA7:AE7) -> 10.844798 | AA7: =((Y7*277.8)/(re!$B$10*8760))*re!$C$10 -> 6.1484377 | AB7: =((Y7*277.8)/(re!$B$11*8760))*re!$C$11 -> 2.2859576 | AC7: =((Y7*277.8)/(re!$B$12*8760))*re!$C$12 -> 0.82548469 | AD7: =((Y7*277.8)/(re!$B$13*8760))*re!$C$13 -> 0.24226181 | AE7: =((Y7*277.8)/(re!$B$14*8760))*re!$C$14 -> 1.3426558 | AF7: =SUM('1'!AD13:AL13)+'1'!AA13 -> 143.6535 | AG7: =SUM('2'!AD13:AL13)+'2'!AA13 -> 2.722533 | AH7: =SUM('3'!AD13:AL13)+'3'!AA13 -> 11.765438 | AI7: =SUM('4'!AD13:AL13)+'4'!AA13 -> 0.87695591 | AJ7: =SUM('5'!AD13:AL13)+'5'!AA13 -> 5.3497996 | AK7: =SUM('6'!AD13:AL13)+'6'!AA13 -> 137.99747 | AL7: =SUM('7'!AD13:AL13)+'7'!AA13 -> 121.58611 | AM7: =SUM('8'!AD13:AL13)+'8'!AA13 -> 223.14203 | AN7: =SUM('9'!AD13:AL13)+'9'!AA13 -> 66.797577 | AO7: =SUM('10'!AD13:AL13)+'10'!AA13 -> 4.9123762 | AP7: =SUM('11'!AD13:AL13)+'11'!AA13 -> 6.2446291 | AQ7: =SUM('12'!AD13:AL13)+'12'!AA13 -> 1.9184786 | AR7: =SUM('13'!AD13:AL13)+'13'!AA13 -> 5.5819709 | AS7: =SUM('14'!AD13:AL13)+'14'!AA13 -> 4.3739096 | AT7: =SUM('15'!AD13:AL13)+'15'!AA13 -> 59.347845 | AU7: =SUM('16'!AD13:AL13)+'16'!AA13 -> 23.757295 | AV7: =SUM('17'!AD13:AL13)+'17'!AA13 -> 40.432437 | AW7: =SUM('18'!AD13:AL13)+'18'!AA13 -> 10.097168 | AX7: =SUM('19'!AD13:AL13)+'19'!AA13 -> 26.269262 | AY7: =SUM('20'!AD13:AL13)+'20'!AA13 -> 1.67458 | AZ7: =SUM('21'!AD13:AL13)+'21'!AA13 -> 0.15201701 | BA7: =SUM('22'!AD13:AL13)+'22'!AA13 -> 0.49226924 | BB7: =SUM('23'!AD13:AL13)+'23'!AA13 -> 4.9592048 | BC7: =('1'!D13+'2'!D13+'3'!D13+'4'!D13+'5'!D13+'6'!D13+'7'!D13+'8'!D13+'9'!D13+'10'!D13+'12'!D13+'13'!D13+'14'!D13+'15'!D13+'16'!D13+'17'!D13+'18'!D13+'19'!D13+'20'!D13+'21'!D13+'22'!D13+'23'!D13)/('1'!D12+'2'!D12+'3'!D12+'4'!D12+'5'!D12+'6'!D12+'7'!D12+'8'!D12+'9'!D12+'10'!D12+'12'!D12+'13'!D12+'14'!D12+'15'!D12+'16'!D12+'17'!D12+'18'!D12+'19'!D12+'20'!D12+'21'!D12+'22'!D12+'23'!D12)-1 -> 0.2768243 | BD7: =('1'!E13+'2'!E13+'3'!E13+'4'!E13+'5'!E13+'6'!E13+'7'!E13+'8'!E13+'9'!E13+'10'!E13+'12'!E13+'13'!E13+'14'!E13+'15'!E13+'16'!E13+'17'!E13+'18'!E13+'19'!E13+'20'!E13+'21'!E13+'22'!E13+'23'!E13)/('1'!E12+'2'!E12+'3'!E12+'4'!E12+'5'!E12+'6'!E12+'7'!E12+'8'!E12+'9'!E12+'10'!E12+'12'!E12+'13'!E12+'14'!E12+'15'!E12+'16'!E12+'17'!E12+'18'!E12+'19'!E12+'20'!E12+'21'!E12+'22'!E12+'23'!E12)-1 -> 0.2768243 | BE7: =('1'!F13+'2'!F13+'3'!F13+'4'!F13+'5'!F13+'6'!F13+'7'!F13+'8'!F13+'9'!F13+'10'!F13+'12'!F13+'13'!F13+'14'!F13+'15'!F13+'16'!F13+'17'!F13+'18'!F13+'19'!F13+'20'!F13+'21'!F13+'22'!F13+'23'!F13)/('1'!F12+'2'!F12+'3'!F12+'4'!F12+'5'!F12+'6'!F12+'7'!F12+'8'!F12+'9'!F12+'10'!F12+'12'!F12+'13'!F12+'14'!F12+'15'!F12+'16'!F12+'17'!F12+'18'!F12+'19'!F12+'20'!F12+'21'!F12+'22'!F12+'23'!F12)-1 -> 0.27647332 | BF7: =W7/W6-1 -> 0.65285338 | BG7: 2030 | BH7: 0.08 | BI7: 0.21 | BJ7: =BI7-BH7 -> 0.13 | BK7: ='2 (RU)'!AB13+'6 (RU)'!AB13+'7 (RU)'!AB13+'9 (RU)'!AB13+'11 (RU)'!AB13+'12 (RU)'!AB13+'13 (RU)'!AB13+'16 (RU)'!AB13+'17 (RU)'!AB13+'18 (RU)'!AB13+'22 (RU)'!AB13 -> #DIV/0! | BL7: ='1 (RU)'!AB13+'2 (RU)'!AC13+'5 (RU)'!AB13+'6 (RU)'!AC13+'7 (RU)'!AC13+'9 (RU)'!AC13+'11 (RU)'!AC13+'12 (RU)'!AC13+'13 (RU)'!AC13+'15 (RU)'!AB13+'16 (RU)'!AC13+'17 (RU)'!AC13+'18 (RU)'!AC13+'19 (RU)'!AB13+'22 (RU)'!AC13 -> #DIV/0! | BN7: ='3 (RU)'!AB13+'4 (RU)'!AB13+'10 (RU)'!AB13+'20 (RU)'!AB13+'21 (RU)'!AB13+'23 (RU)'!AB13 -> #DIV/0! | BO7: ='8 (RU)'!AB13+'14 (RU)'!AB13 -> #DIV/0! | BP7: ='1 (RU)'!AD13+'2 (RU)'!AD13+'3 (RU)'!AD13+'4 (RU)'!AD13+'5 (RU)'!AD13+'6 (RU)'!AD13+'7 (RU)'!AD13+'8 (RU)'!AD13+'9 (RU)'!AD13+'10 (RU)'!AD13+'11 (RU)'!AD13+'12 (RU)'!AD13+'13 (RU)'!AD13+'14 (RU)'!AD13+'15 (RU)'!AD13+'16 (RU)'!AD13+'17 (RU)'!AD13+'18 (RU)'!AD13+'19 (RU)'!AD13+'20 (RU)'!AD13+'21 (RU)'!AD13+'22 (RU)'!AD13+'23 (RU)'!AD13 -> #DIV/0! | BQ7: ='1 (RU)'!AE13+'2 (RU)'!AE13+'3 (RU)'!AE13+'4 (RU)'!AE13+'5 (RU)'!AE13+'6 (RU)'!AE13+'7 (RU)'!AE13+'8 (RU)'!AE13+'9 (RU)'!AE13+'10 (RU)'!AE13+'11 (RU)'!AE13+'12 (RU)'!AE13+'13 (RU)'!AE13+'14 (RU)'!AE13+'15 (RU)'!AE13+'16 (RU)'!AE13+'17 (RU)'!AE13+'18 (RU)'!AE13+'19 (RU)'!AE13+'20 (RU)'!AE13+'21 (RU)'!AE13+'22 (RU)'!AE13+'23 (RU)'!AE13 -> #DIV/0! | BR7: ='1 (RU)'!AF13+'2 (RU)'!AF13+'3 (RU)'!AF13+'4 (RU)'!AF13+'5 (RU)'!AF13+'6 (RU)'!AF13+'7 (RU)'!AF13+'8 (RU)'!AF13+'9 (RU)'!AF13+'10 (RU)'!AF13+'11 (RU)'!AF13+'12 (RU)'!AF13+'13 (RU)'!AF13+'14 (RU)'!AF13+'15 (RU)'!AF13+'16 (RU)'!AF13+'17 (RU)'!AF13+'18 (RU)'!AF13+'19 (RU)'!AF13+'20 (RU)'!AF13+'21 (RU)'!AF13+'22 (RU)'!AF13+'23 (RU)'!AF13 -> #DIV/0! | BS7: ='1 (RU)'!AG13+'2 (RU)'!AG13+'3 (RU)'!AG13+'4 (RU)'!AG13+'5 (RU)'!AG13+'6 (RU)'!AG13+'7 (RU)'!AG13+'8 (RU)'!AG13+'9 (RU)'!AG13+'10 (RU)'!AG13+'11 (RU)'!AG13+'12 (RU)'!AG13+'13 (RU)'!AG13+'14 (RU)'!AG13+'15 (RU)'!AG13+'16 (RU)'!AG13+'17 (RU)'!AG13+'18 (RU)'!AG13+'19 (RU)'!AG13+'20 (RU)'!AG13+'21 (RU)'!AG13+'22 (RU)'!AG13+'23 (RU)'!AG13 -> #DIV/0! | BT7: ='1 (RU)'!AH13+'2 (RU)'!AH13+'3 (RU)'!AH13+'4 (RU)'!AH13+'5 (RU)'!AH13+'6 (RU)'!AH13+'7 (RU)'!AH13+'8 (RU)'!AH13+'9 (RU)'!AH13+'10 (RU)'!AH13+'11 (RU)'!AH13+'12 (RU)'!AH13+'13 (RU)'!AH13+'14 (RU)'!AH13+'15 (RU)'!AH13+'16 (RU)'!AH13+'17 (RU)'!AH13+'18 (RU)'!AH13+'19 (RU)'!AH13+'20 (RU)'!AH13+'21 (RU)'!AH13+'22 (RU)'!AH13+'23 (RU)'!AH13 -> #DIV/0! | BU7: ='1 (RU)'!AI13+'2 (RU)'!AI13+'3 (RU)'!AI13+'4 (RU)'!AI13+'5 (RU)'!AI13+'6 (RU)'!AI13+'7 (RU)'!AI13+'8 (RU)'!AI13+'9 (RU)'!AI13+'10 (RU)'!AI13+'11 (RU)'!AI13+'12 (RU)'!AI13+'13 (RU)'!AI13+'14 (RU)'!AI13+'15 (RU)'!AI13+'16 (RU)'!AI13+'17 (RU)'!AI13+'18 (RU)'!AI13+'19 (RU)'!AI13+'20 (RU)'!AI13+'21 (RU)'!AI13+'22 (RU)'!AI13+'23 (RU)'!AI13 -> #DIV/0! | BV7: ='1 (RU)'!AJ13+'2 (RU)'!AJ13+'3 (RU)'!AJ13+'4 (RU)'!AJ13+'5 (RU)'!AJ13+'6 (RU)'!AJ13+'7 (RU)'!AJ13+'8 (RU)'!AJ13+'9 (RU)'!AJ13+'10 (RU)'!AJ13+'11 (RU)'!AJ13+'12 (RU)'!AJ13+'13 (RU)'!AJ13+'14 (RU)'!AJ13+'15 (RU)'!AJ13+'16 (RU)'!AJ13+'17 (RU)'!AJ13+'18 (RU)'!AJ13+'19 (RU)'!AJ13+'20 (RU)'!AJ13+'21 (RU)'!AJ13+'22 (RU)'!AJ13+'23 (RU)'!AJ13 -> #DIV/0! | BW7: ='1 (RU)'!AK13+'2 (RU)'!AK13+'3 (RU)'!AK13+'4 (RU)'!AK13+'5 (RU)'!AK13+'6 (RU)'!AK13+'7 (RU)'!AK13+'8 (RU)'!AK13+'9 (RU)'!AK13+'10 (RU)'!AK13+'11 (RU)'!AK13+'12 (RU)'!AK13+'13 (RU)'!AK13+'14 (RU)'!AK13+'15 (RU)'!AK13+'16 (RU)'!AK13+'17 (RU)'!AK13+'18 (RU)'!AK13+'19 (RU)'!AK13+'20 (RU)'!AK13+'21 (RU)'!AK13+'22 (RU)'!AK13+'23 (RU)'!AK13 -> #DIV/0! | BX7: ='1 (RU)'!AL13+'2 (RU)'!AL13+'3 (RU)'!AL13+'4 (RU)'!AL13+'5 (RU)'!AL13+'6 (RU)'!AL13+'7 (RU)'!AL13+'8 (RU)'!AL13+'9 (RU)'!AL13+'10 (RU)'!AL13+'11 (RU)'!AL13+'12 (RU)'!AL13+'13 (RU)'!AL13+'14 (RU)'!AL13+'15 (RU)'!AL13+'16 (RU)'!AL13+'17 (RU)'!AL13+'18 (RU)'!AL13+'19 (RU)'!AL13+'20 (RU)'!AL13+'21 (RU)'!AL13+'22 (RU)'!AL13+'23 (RU)'!AL13 -> #DIV/0! | BY7: =SUM(BK7:BO7) -> #DIV/0! | BZ7: =SUM(BP7:BX7) -> #DIV/0! | CC7: =VLOOKUP(CC$1,emissions!$A$2:$B$5,2,FALSE)*BK7 -> #DIV/0! | CD7: =VLOOKUP(CD$1,emissions!$A$2:$B$5,2,FALSE)*BL7 -> #DIV/0! | CF7: =VLOOKUP(CF$1,emissions!$A$2:$B$5,2,FALSE)*BN7 -> #DIV/0! | CG7: =VLOOKUP(CG$1,emissions!$A$2:$B$5,2,FALSE)*BO7 -> #DIV/0! | CH7: =BP7*(emissions!$D$3*production!$B$4+emissions!$D$4*production!$C$4+emissions!$D$5*production!$D$4+emissions!$D$6*production!$E$4) -> #DIV/0! | CI7: =BQ7*(emissions!$D$3*production!$B$4+emissions!$D$4*production!$C$4+emissions!$D$5*production!$D$4+emissions!$D$6*production!$E$4) -> #DIV/0! | CJ7: =BR7*(emissions!$D$8*production!$B$6+emissions!$D$9*production!$C$6+emissions!$D$10*production!$D$6) -> #DIV/0! | CK7: =BS7*(emissions!$D$12*production!$B$8+emissions!$D$13*production!$C$8+emissions!$D$14*production!$D$8) -> #DIV/0! | CL7: =BT7*(emissions!$D$16*production!$B$10+production!$C$10*emissions!$D$17) -> #DIV/0! | CM7: =BU7*(emissions!$D$19*production!$B$12+production!$C$12*emissions!$D$20+emissions!$D$21*production!$D$12) -> #DIV/0! | CN7: =BV7*(emissions!$D$23*production!$B$14+production!$C$14*emissions!$D$24+emissions!$D$25*production!$D$14) -> #DIV/0! | CO7: =BW7*(emissions!$D$27*production!$B$16+production!$C$16*emissions!$D$28+production!$D$16*emissions!$D$29) -> #DIV/0! | CP7: 0 | CS7: =SUM(CC7:CP7) -> #DIV/0! | CT7: =SUM(CC7:CP7)/SUM(BK7:BX7) -> #DIV/0! | CU7: =(CT7-CW7) -> #DIV/0! | CV7: =CT7-CX7 -> #DIV/0! | CW7: =93.3*(1-BH7) -> 85.836 | CX7: =93.3*(1-BI7) -> 73.707 | CY7: =IF(G7<2028,0,IF(CT7>=CW7,CU7,IF(AND(CT7<CW7,CT7>=CX7),CV7,0))*SUM(BK7:BX7)) -> #DIV/0! | CZ7: =IF(CT7>=CW7,380*CY7,IF(AND(CT7<CW7,CT7>=CX7),100*CY7,0)) -> #DIV/0! | DA7: =IF(G7<2028,"",IF(CT7>=CW7,"Red",IF(AND(CT7<CW7,CT7>=CX7),"Yellow","Green"))) -> #DIV/0! | DB7: =IF(G7<2028,0,IF(CT7<CX7,-CV7*SUM(BK7:BX7),0)) -> #DIV/0! | DC7: =DB7*380 -> #DIV/0! | DD7: 2030 | DE7: =CY7-DB7 -> #DIV/0! | DF7: =CS7 -> #DIV/0! | DG7: 2030 | DH7: =CW7*SUM(BK7:BX7) -> #DIV/0! | DI7: =CX7*SUM(BK7:BX7) -> #DIV/0! | DJ7: =DI7 -> #DIV/0! | DK7: =DH7-DI7 -> #DIV/0! | DL7: =MAX(DH7:DK7) -> #DIV/0! | DM7: =(CZ7-DC7)/1000000 -> #DIV/0! | DN7: =DE7/1000000 -> #DIV/0! | DO7: =ED7/1000000 -> #DIV/0! | DP7: =DM7+DO7 -> #DIV/0! | DQ7: 15715 | DR7: 11981 | DT7: 664 | DU7: 2262 | DV7: =DQ7*VLOOKUP(DQ$1,emissions!$A$2:$B$5,2,FALSE) -> 2294390 | DW7: =DR7*VLOOKUP(DR$1,emissions!$A$2:$B$5,2,FALSE) -> 1749226 | DY7: =DT7*VLOOKUP(DT$1,emissions!$A$2:$B$5,2,FALSE) -> 96280 | DZ7: =DU7*VLOOKUP(DU$1,emissions!$A$2:$B$5,2,FALSE) -> 255606 | EA7: =SUM(DV7:DZ7) -> 4395502 | EB7: =1/(SUM(DQ7:DU7)/EA7) -> 143.54066 | ED7: =SUM(EE7:ER7) -> #DIV/0! | EE7: =cost!$B$2*BK7 -> #DIV/0! | EF7: =cost!$B$3*BL7 -> #DIV/0! | EH7: =cost!$B$4*BN7 -> #DIV/0! | EI7: =cost!$B$5*$BO$2 -> #DIV/0! | EJ7: =BP7*(cost!$D$3*production!$B$4+production!$C$4*cost!$D$4+cost!$D$5*production!$D$4+production!$E$4*cost!$D$6) -> #DIV/0! | EK7: =BQ7*(cost!$D$3*production!$B$4+production!$C$4*cost!$D$4+cost!$D$5*production!$D$4+production!$E$4*cost!$D$6) -> #DIV/0! | EL7: =BR7*(cost!$D$8*production!$B$6+cost!$D$9*production!$C$6+$D$10*production!$D$6) -> #DIV/0! | EM7: =BS7*(cost!$D$12*production!$B$8+cost!$D$13*production!$C$8+cost!$D$14*production!$D$8) -> #DIV/0! | EN7: =BT7*(cost!$D$16*production!$B$10+production!$C$10*cost!$D$17) -> #DIV/0! | EO7: =BU7*(cost!$D$19*production!$B$12+production!$C$12*cost!$D$20+cost!$D$21*production!$D$12) -> #DIV/0! | EP7: =BV7*(cost!$D$23*production!$B$14+production!$C$14*cost!$D$24+cost!$D$25*production!$D$14) -> #DIV/0! | EQ7: =BW7*(cost!$D$27*production!$B$16+production!$C$16*cost!$D$28+cost!$D$29*production!$D$16) -> #DIV/0! | ER7: =BX7*(re!$H$10*re!$C$10+re!$H$11*re!$C$11+re!$H$12*re!$C$12+re!$H$13*re!$C$13+re!$H$14*re!$C$14) -> #DIV/0!
A8: Clean Fuels | B8: 0.45 | C8: 10 | G8: 2031 | H8: ='2'!AB14+'6'!AB14+'7'!AB14+'9'!AB14+'11'!AB14+'12'!AB14+'13'!AB14+'16'!AB14+'17'!AB14+'18'!AB14+'22'!AB14 -> 223.26638 | I8: ='1'!AB14+'2'!AC14+'5'!AB14+'6'!AC14+'7'!AC14+'9'!AC14+'11'!AC14+'12'!AC14+'13'!AC14+'15'!AB14+'16'!AC14+'17'!AC14+'18'!AC14+'19'!AB14+'22'!AC14 -> 351.03034 | K8: ='3'!AB14+'4'!AB14+'10'!AB14+'20'!AB14+'21'!AB14+'23'!AB14 -> 21.484673 | L8: ='8'!AB14+'14'!AB14 -> 198.19318 | M8: ='1'!AD14+'2'!AD14+'3'!AD14+'4'!AD14+'5'!AD14+'6'!AD14+'7'!AD14+'8'!AD14+'9'!AD14+'10'!AD14+'11'!AD14+'12'!AD14+'13'!AD14+'14'!AD14+'15'!AD14+'16'!AD14+'17'!AD14+'18'!AD14+'19'!AD14+'20'!AD14+'21'!AD14+'22'!AD14+'23'!AD14 -> 21.448571 | N8: ='1'!AE14+'2'!AE14+'3'!AE14+'4'!AE14+'5'!AE14+'6'!AE14+'7'!AE14+'8'!AE14+'9'!AE14+'10'!AE14+'11'!AE14+'12'!AE14+'13'!AE14+'14'!AE14+'15'!AE14+'16'!AE14+'17'!AE14+'18'!AE14+'19'!AE14+'20'!AE14+'21'!AE14+'22'!AE14+'23'!AE14 -> 1.2718227 | O8: ='1'!AF14+'2'!AF14+'3'!AF14+'4'!AF14+'5'!AF14+'6'!AF14+'7'!AF14+'8'!AF14+'9'!AF14+'10'!AF14+'11'!AF14+'12'!AF14+'13'!AF14+'14'!AF14+'15'!AF14+'16'!AF14+'17'!AF14+'18'!AF14+'19'!AF14+'20'!AF14+'21'!AF14+'22'!AF14+'23'!AF14 -> 41.097039 | P8: ='1'!AG14+'2'!AG14+'3'!AG14+'4'!AG14+'5'!AG14+'6'!AG14+'7'!AG14+'8'!AG14+'9'!AG14+'10'!AG14+'11'!AG14+'12'!AG14+'13'!AG14+'14'!AG14+'15'!AG14+'16'!AG14+'17'!AG14+'18'!AG14+'19'!AG14+'20'!AG14+'21'!AG14+'22'!AG14+'23'!AG14 -> 37.384306 | Q8: ='1'!AH14+'2'!AH14+'3'!AH14+'4'!AH14+'5'!AH14+'6'!AH14+'7'!AH14+'8'!AH14+'9'!AH14+'10'!AH14+'11'!AH14+'12'!AH14+'13'!AH14+'14'!AH14+'15'!AH14+'16'!AH14+'17'!AH14+'18'!AH14+'19'!AH14+'20'!AH14+'21'!AH14+'22'!AH14+'23'!AH14 -> 0.96272571 | R8: ='1'!AI14+'2'!AI14+'3'!AI14+'4'!AI14+'5'!AI14+'6'!AI14+'7'!AI14+'8'!AI14+'9'!AI14+'10'!AI14+'11'!AI14+'12'!AI14+'13'!AI14+'14'!AI14+'15'!AI14+'16'!AI14+'17'!AI14+'18'!AI14+'19'!AI14+'20'!AI14+'21'!AI14+'22'!AI14+'23'!AI14 -> 6.4882855 | S8: ='1'!AJ14+'2'!AJ14+'3'!AJ14+'4'!AJ14+'5'!AJ14+'6'!AJ14+'7'!AJ14+'8'!AJ14+'9'!AJ14+'10'!AJ14+'11'!AJ14+'12'!AJ14+'13'!AJ14+'14'!AJ14+'15'!AJ14+'16'!AJ14+'17'!AJ14+'18'!AJ14+'19'!AJ14+'20'!AJ14+'21'!AJ14+'22'!AJ14+'23'!AJ14 -> 1.8434237 | T8: ='1'!AK14+'2'!AK14+'3'!AK14+'4'!AK14+'5'!AK14+'6'!AK14+'7'!AK14+'8'!AK14+'9'!AK14+'10'!AK14+'11'!AK14+'12'!AK14+'13'!AK14+'14'!AK14+'15'!AK14+'16'!AK14+'17'!AK14+'18'!AK14+'19'!AK14+'20'!AK14+'21'!AK14+'22'!AK14+'23'!AK14 -> 20.328044 | U8: ='1'!AL14+'2'!AL14+'3'!AL14+'4'!AL14+'5'!AL14+'6'!AL14+'7'!AL14+'8'!AL14+'9'!AL14+'10'!AL14+'11'!AL14+'12'!AL14+'13'!AL14+'14'!AL14+'15'!AL14+'16'!AL14+'17'!AL14+'18'!AL14+'19'!AL14+'20'!AL14+'21'!AL14+'22'!AL14+'23'!AL14 -> 0.049285873 | V8: =SUM(H8:L8) -> 793.97458 | W8: =SUM(M8:U8) -> 130.8735 | X8: =W8/W7-1 -> 0.57995564 | Y8: =((M8+N8)*re!$D$2/re!$C$2+O8*re!$D$3/re!$C$3+P8*re!$D$4/re!$C$4+T8*re!$D$5/re!$C$5+U8*re!$D$6/re!$C$6) -> 222.08941 | Z8: =SUM(AA8:AE8) -> 17.134627 | AA8: =((Y8*277.8)/(re!$B$10*8760))*re!$C$10 -> 9.7144445 | AB8: =((Y8*277.8)/(re!$B$11*8760))*re!$C$11 -> 3.6117807 | AC8: =((Y8*277.8)/(re!$B$12*8760))*re!$C$12 -> 1.3042541 | AD8: =((Y8*277.8)/(re!$B$13*8760))*re!$C$13 -> 0.38277023 | AE8: =((Y8*277.8)/(re!$B$14*8760))*re!$C$14 -> 2.1213772 | AF8: =SUM('1'!AD14:AL14)+'1'!AA14 -> 146.43503 | AG8: =SUM('2'!AD14:AL14)+'2'!AA14 -> 2.780692 | AH8: =SUM('3'!AD14:AL14)+'3'!AA14 -> 12.033057 | AI8: =SUM('4'!AD14:AL14)+'4'!AA14 -> 0.89758883 | AJ8: =SUM('5'!AD14:AL14)+'5'!AA14 -> 5.4619022 | AK8: =SUM('6'!AD14:AL14)+'6'!AA14 -> 140.74885 | AL8: =SUM('7'!AD14:AL14)+'7'!AA14 -> 124.17136 | AM8: =SUM('8'!AD14:AL14)+'8'!AA14 -> 229.78069 | AN8: =SUM('9'!AD14:AL14)+'9'!AA14 -> 68.19729 | AO8: =SUM('10'!AD14:AL14)+'10'!AA14 -> 5.0133254 | AP8: =SUM('11'!AD14:AL14)+'11'!AA14 -> 6.3818931 | AQ8: =SUM('12'!AD14:AL14)+'12'!AA14 -> 1.960649 | AR8: =SUM('13'!AD14:AL14)+'13'!AA14 -> 5.7046689 | AS8: =SUM('14'!AD14:AL14)+'14'!AA14 -> 4.4972305 | AT8: =SUM('15'!AD14:AL14)+'15'!AA14 -> 60.591453 | AU8: =SUM('16'!AD14:AL14)+'16'!AA14 -> 24.279507 | AV8: =SUM('17'!AD14:AL14)+'17'!AA14 -> 41.321188 | AW8: =SUM('18'!AD14:AL14)+'18'!AA14 -> 10.319115 | AX8: =SUM('19'!AD14:AL14)+'19'!AA14 -> 26.819722 | AY8: =SUM('20'!AD14:AL14)+'20'!AA14 -> 1.7139794 | AZ8: =SUM('21'!AD14:AL14)+'21'!AA14 -> 0.15543736 | BA8: =SUM('22'!AD14:AL14)+'22'!AA14 -> 0.50258452 | BB8: =SUM('23'!AD14:AL14)+'23'!AA14 -> 5.0808621 | BC8: =('1'!D14+'2'!D14+'3'!D14+'4'!D14+'5'!D14+'6'!D14+'7'!D14+'8'!D14+'9'!D14+'10'!D14+'12'!D14+'13'!D14+'14'!D14+'15'!D14+'16'!D14+'17'!D14+'18'!D14+'19'!D14+'20'!D14+'21'!D14+'22'!D14+'23'!D14)/('1'!D13+'2'!D13+'3'!D13+'4'!D13+'5'!D13+'6'!D13+'7'!D13+'8'!D13+'9'!D13+'10'!D13+'12'!D13+'13'!D13+'14'!D13+'15'!D13+'16'!D13+'17'!D13+'18'!D13+'19'!D13+'20'!D13+'21'!D13+'22'!D13+'23'!D13)-1 -> 0.22556739 | BD8: =('1'!E14+'2'!E14+'3'!E14+'4'!E14+'5'!E14+'6'!E14+'7'!E14+'8'!E14+'9'!E14+'10'!E14+'12'!E14+'13'!E14+'14'!E14+'15'!E14+'16'!E14+'17'!E14+'18'!E14+'19'!E14+'20'!E14+'21'!E14+'22'!E14+'23'!E14)/('1'!E13+'2'!E13+'3'!E13+'4'!E13+'5'!E13+'6'!E13+'7'!E13+'8'!E13+'9'!E13+'10'!E13+'12'!E13+'13'!E13+'14'!E13+'15'!E13+'16'!E13+'17'!E13+'18'!E13+'19'!E13+'20'!E13+'21'!E13+'22'!E13+'23'!E13)-1 -> 0.22556739 | BE8: =('1'!F14+'2'!F14+'3'!F14+'4'!F14+'5'!F14+'6'!F14+'7'!F14+'8'!F14+'9'!F14+'10'!F14+'12'!F14+'13'!F14+'14'!F14+'15'!F14+'16'!F14+'17'!F14+'18'!F14+'19'!F14+'20'!F14+'21'!F14+'22'!F14+'23'!F14)/('1'!F13+'2'!F13+'3'!F13+'4'!F13+'5'!F13+'6'!F13+'7'!F13+'8'!F13+'9'!F13+'10'!F13+'12'!F13+'13'!F13+'14'!F13+'15'!F13+'16'!F13+'17'!F13+'18'!F13+'19'!F13+'20'!F13+'21'!F13+'22'!F13+'23'!F13)-1 -> 0.22539398 | BF8: =W8/W7-1 -> 0.57995564 | BG8: 2031 | BH8: 0.12 | BI8: 0.25 | BJ8: =BI8-BH8 -> 0.13 | BK8: ='2 (RU)'!AB14+'6 (RU)'!AB14+'7 (RU)'!AB14+'9 (RU)'!AB14+'11 (RU)'!AB14+'12 (RU)'!AB14+'13 (RU)'!AB14+'16 (RU)'!AB14+'17 (RU)'!AB14+'18 (RU)'!AB14+'22 (RU)'!AB14 -> #DIV/0! | BL8: ='1 (RU)'!AB14+'2 (RU)'!AC14+'5 (RU)'!AB14+'6 (RU)'!AC14+'7 (RU)'!AC14+'9 (RU)'!AC14+'11 (RU)'!AC14+'12 (RU)'!AC14+'13 (RU)'!AC14+'15 (RU)'!AB14+'16 (RU)'!AC14+'17 (RU)'!AC14+'18 (RU)'!AC14+'19 (RU)'!AB14+'22 (RU)'!AC14 -> #DIV/0! | BN8: ='3 (RU)'!AB14+'4 (RU)'!AB14+'10 (RU)'!AB14+'20 (RU)'!AB14+'21 (RU)'!AB14+'23 (RU)'!AB14 -> #DIV/0! | BO8: ='8 (RU)'!AB14+'14 (RU)'!AB14 -> #DIV/0! | BP8: ='1 (RU)'!AD14+'2 (RU)'!AD14+'3 (RU)'!AD14+'4 (RU)'!AD14+'5 (RU)'!AD14+'6 (RU)'!AD14+'7 (RU)'!AD14+'8 (RU)'!AD14+'9 (RU)'!AD14+'10 (RU)'!AD14+'11 (RU)'!AD14+'12 (RU)'!AD14+'13 (RU)'!AD14+'14 (RU)'!AD14+'15 (RU)'!AD14+'16 (RU)'!AD14+'17 (RU)'!AD14+'18 (RU)'!AD14+'19 (RU)'!AD14+'20 (RU)'!AD14+'21 (RU)'!AD14+'22 (RU)'!AD14+'23 (RU)'!AD14 -> #DIV/0! | BQ8: ='1 (RU)'!AE14+'2 (RU)'!AE14+'3 (RU)'!AE14+'4 (RU)'!AE14+'5 (RU)'!AE14+'6 (RU)'!AE14+'7 (RU)'!AE14+'8 (RU)'!AE14+'9 (RU)'!AE14+'10 (RU)'!AE14+'11 (RU)'!AE14+'12 (RU)'!AE14+'13 (RU)'!AE14+'14 (RU)'!AE14+'15 (RU)'!AE14+'16 (RU)'!AE14+'17 (RU)'!AE14+'18 (RU)'!AE14+'19 (RU)'!AE14+'20 (RU)'!AE14+'21 (RU)'!AE14+'22 (RU)'!AE14+'23 (RU)'!AE14 -> #DIV/0! | BR8: ='1 (RU)'!AF14+'2 (RU)'!AF14+'3 (RU)'!AF14+'4 (RU)'!AF14+'5 (RU)'!AF14+'6 (RU)'!AF14+'7 (RU)'!AF14+'8 (RU)'!AF14+'9 (RU)'!AF14+'10 (RU)'!AF14+'11 (RU)'!AF14+'12 (RU)'!AF14+'13 (RU)'!AF14+'14 (RU)'!AF14+'15 (RU)'!AF14+'16 (RU)'!AF14+'17 (RU)'!AF14+'18 (RU)'!AF14+'19 (RU)'!AF14+'20 (RU)'!AF14+'21 (RU)'!AF14+'22 (RU)'!AF14+'23 (RU)'!AF14 -> #DIV/0! | BS8: ='1 (RU)'!AG14+'2 (RU)'!AG14+'3 (RU)'!AG14+'4 (RU)'!AG14+'5 (RU)'!AG14+'6 (RU)'!AG14+'7 (RU)'!AG14+'8 (RU)'!AG14+'9 (RU)'!AG14+'10 (RU)'!AG14+'11 (RU)'!AG14+'12 (RU)'!AG14+'13 (RU)'!AG14+'14 (RU)'!AG14+'15 (RU)'!AG14+'16 (RU)'!AG14+'17 (RU)'!AG14+'18 (RU)'!AG14+'19 (RU)'!AG14+'20 (RU)'!AG14+'21 (RU)'!AG14+'22 (RU)'!AG14+'23 (RU)'!AG14 -> #DIV/0! | BT8: ='1 (RU)'!AH14+'2 (RU)'!AH14+'3 (RU)'!AH14+'4 (RU)'!AH14+'5 (RU)'!AH14+'6 (RU)'!AH14+'7 (RU)'!AH14+'8 (RU)'!AH14+'9 (RU)'!AH14+'10 (RU)'!AH14+'11 (RU)'!AH14+'12 (RU)'!AH14+'13 (RU)'!AH14+'14 (RU)'!AH14+'15 (RU)'!AH14+'16 (RU)'!AH14+'17 (RU)'!AH14+'18 (RU)'!AH14+'19 (RU)'!AH14+'20 (RU)'!AH14+'21 (RU)'!AH14+'22 (RU)'!AH14+'23 (RU)'!AH14 -> #DIV/0! | BU8: ='1 (RU)'!AI14+'2 (RU)'!AI14+'3 (RU)'!AI14+'4 (RU)'!AI14+'5 (RU)'!AI14+'6 (RU)'!AI14+'7 (RU)'!AI14+'8 (RU)'!AI14+'9 (RU)'!AI14+'10 (RU)'!AI14+'11 (RU)'!AI14+'12 (RU)'!AI14+'13 (RU)'!AI14+'14 (RU)'!AI14+'15 (RU)'!AI14+'16 (RU)'!AI14+'17 (RU)'!AI14+'18 (RU)'!AI14+'19 (RU)'!AI14+'20 (RU)'!AI14+'21 (RU)'!AI14+'22 (RU)'!AI14+'23 (RU)'!AI14 -> #DIV/0! | BV8: ='1 (RU)'!AJ14+'2 (RU)'!AJ14+'3 (RU)'!AJ14+'4 (RU)'!AJ14+'5 (RU)'!AJ14+'6 (RU)'!AJ14+'7 (RU)'!AJ14+'8 (RU)'!AJ14+'9 (RU)'!AJ14+'10 (RU)'!AJ14+'11 (RU)'!AJ14+'12 (RU)'!AJ14+'13 (RU)'!AJ14+'14 (RU)'!AJ14+'15 (RU)'!AJ14+'16 (RU)'!AJ14+'17 (RU)'!AJ14+'18 (RU)'!AJ14+'19 (RU)'!AJ14+'20 (RU)'!AJ14+'21 (RU)'!AJ14+'22 (RU)'!AJ14+'23 (RU)'!AJ14 -> #DIV/0! | BW8: ='1 (RU)'!AK14+'2 (RU)'!AK14+'3 (RU)'!AK14+'4 (RU)'!AK14+'5 (RU)'!AK14+'6 (RU)'!AK14+'7 (RU)'!AK14+'8 (RU)'!AK14+'9 (RU)'!AK14+'10 (RU)'!AK14+'11 (RU)'!AK14+'12 (RU)'!AK14+'13 (RU)'!AK14+'14 (RU)'!AK14+'15 (RU)'!AK14+'16 (RU)'!AK14+'17 (RU)'!AK14+'18 (RU)'!AK14+'19 (RU)'!AK14+'20 (RU)'!AK14+'21 (RU)'!AK14+'22 (RU)'!AK14+'23 (RU)'!AK14 -> #DIV/0! | BX8: ='1 (RU)'!AL14+'2 (RU)'!AL14+'3 (RU)'!AL14+'4 (RU)'!AL14+'5 (RU)'!AL14+'6 (RU)'!AL14+'7 (RU)'!AL14+'8 (RU)'!AL14+'9 (RU)'!AL14+'10 (RU)'!AL14+'11 (RU)'!AL14+'12 (RU)'!AL14+'13 (RU)'!AL14+'14 (RU)'!AL14+'15 (RU)'!AL14+'16 (RU)'!AL14+'17 (RU)'!AL14+'18 (RU)'!AL14+'19 (RU)'!AL14+'20 (RU)'!AL14+'21 (RU)'!AL14+'22 (RU)'!AL14+'23 (RU)'!AL14 -> #DIV/0! | BY8: =SUM(BK8:BO8) -> #DIV/0! | BZ8: =SUM(BP8:BX8) -> #DIV/0! | CC8: =VLOOKUP(CC$1,emissions!$A$2:$B$5,2,FALSE)*BK8 -> #DIV/0! | CD8: =VLOOKUP(CD$1,emissions!$A$2:$B$5,2,FALSE)*BL8 -> #DIV/0! | CF8: =VLOOKUP(CF$1,emissions!$A$2:$B$5,2,FALSE)*BN8 -> #DIV/0! | CG8: =VLOOKUP(CG$1,emissions!$A$2:$B$5,2,FALSE)*BO8 -> #DIV/0! | CH8: =BP8*(emissions!$D$3*production!$B$4+emissions!$D$4*production!$C$4+emissions!$D$5*production!$D$4+emissions!$D$6*production!$E$4) -> #DIV/0! | CI8: =BQ8*(emissions!$D$3*production!$B$4+emissions!$D$4*production!$C$4+emissions!$D$5*production!$D$4+emissions!$D$6*production!$E$4) -> #DIV/0! | CJ8: =BR8*(emissions!$D$8*production!$B$6+emissions!$D$9*production!$C$6+emissions!$D$10*production!$D$6) -> #DIV/0! | CK8: =BS8*(emissions!$D$12*production!$B$8+emissions!$D$13*production!$C$8+emissions!$D$14*production!$D$8) -> #DIV/0! | CL8: =BT8*(emissions!$D$16*production!$B$10+production!$C$10*emissions!$D$17) -> #DIV/0! | CM8: =BU8*(emissions!$D$19*production!$B$12+production!$C$12*emissions!$D$20+emissions!$D$21*production!$D$12) -> #DIV/0! | CN8: =BV8*(emissions!$D$23*production!$B$14+production!$C$14*emissions!$D$24+emissions!$D$25*production!$D$14) -> #DIV/0! | CO8: =BW8*(emissions!$D$27*production!$B$16+production!$C$16*emissions!$D$28+production!$D$16*emissions!$D$29) -> #DIV/0! | CP8: 0 | CS8: =SUM(CC8:CP8) -> #DIV/0! | CT8: =SUM(CC8:CP8)/SUM(BK8:BX8) -> #DIV/0! | CU8: =(CT8-CW8) -> #DIV/0! | CV8: =CT8-CX8 -> #DIV/0! | CW8: =93.3*(1-BH8) -> 82.104 | CX8: =93.3*(1-BI8) -> 69.975 | CY8: =IF(G8<2028,0,IF(CT8>=CW8,CU8,IF(AND(CT8<CW8,CT8>=CX8),CV8,0))*SUM(BK8:BX8)) -> #DIV/0! | CZ8: =IF(CT8>=CW8,380*CY8,IF(AND(CT8<CW8,CT8>=CX8),100*CY8,0)) -> #DIV/0! | DA8: =IF(G8<2028,"",IF(CT8>=CW8,"Red",IF(AND(CT8<CW8,CT8>=CX8),"Yellow","Green"))) -> #DIV/0! | DB8: =IF(G8<2028,0,IF(CT8<CX8,-CV8*SUM(BK8:BX8),0)) -> #DIV/0! | DC8: =DB8*380 -> #DIV/0! | DD8: 2031 | DE8: =CY8-DB8 -> #DIV/0! | DF8: =CS8 -> #DIV/0! | DG8: 2031 | DH8: =CW8*SUM(BK8:BX8) -> #DIV/0! | DI8: =CX8*SUM(BK8:BX8) -> #DIV/0! | DJ8: =DI8 -> #DIV/0! | DK8: =DH8-DI8 -> #DIV/0! | DL8: =MAX(DH8:DK8) -> #DIV/0! | DM8: =(CZ8-DC8)/1000000 -> #DIV/0! | DN8: =DE8/1000000 -> #DIV/0! | DO8: =ED8/1000000 -> #DIV/0! | DP8: =DM8+DO8 -> #DIV/0! | DQ8: 14680 | DR8: 13516 | DT8: 677 | DU8: 2307 | DV8: =DQ8*VLOOKUP(DQ$1,emissions!$A$2:$B$5,2,FALSE) -> 2143280 | DW8: =DR8*VLOOKUP(DR$1,emissions!$A$2:$B$5,2,FALSE) -> 1973336 | DY8: =DT8*VLOOKUP(DT$1,emissions!$A$2:$B$5,2,FALSE) -> 98165 | DZ8: =DU8*VLOOKUP(DU$1,emissions!$A$2:$B$5,2,FALSE) -> 260691 | EA8: =SUM(DV8:DZ8) -> 4475472 | EB8: =1/(SUM(DQ8:DU8)/EA8) -> 143.53663 | ED8: =SUM(EE8:ER8) -> #DIV/0! | EE8: =cost!$B$2*BK8 -> #DIV/0! | EF8: =cost!$B$3*BL8 -> #DIV/0! | EH8: =cost!$B$4*BN8 -> #DIV/0! | EI8: =cost!$B$5*$BO$2 -> #DIV/0! | EJ8: =BP8*(cost!$D$3*production!$B$4+production!$C$4*cost!$D$4+cost!$D$5*production!$D$4+production!$E$4*cost!$D$6) -> #DIV/0! | EK8: =BQ8*(cost!$D$3*production!$B$4+production!$C$4*cost!$D$4+cost!$D$5*production!$D$4+production!$E$4*cost!$D$6) -> #DIV/0! | EL8: =BR8*(cost!$D$8*production!$B$6+cost!$D$9*production!$C$6+$D$10*production!$D$6) -> #DIV/0! | EM8: =BS8*(cost!$D$12*production!$B$8+cost!$D$13*production!$C$8+cost!$D$14*production!$D$8) -> #DIV/0! | EN8: =BT8*(cost!$D$16*production!$B$10+production!$C$10*cost!$D$17) -> #DIV/0! | EO8: =BU8*(cost!$D$19*production!$B$12+production!$C$12*cost!$D$20+cost!$D$21*production!$D$12) -> #DIV/0! | EP8: =BV8*(cost!$D$23*production!$B$14+production!$C$14*cost!$D$24+cost!$D$25*production!$D$14) -> #DIV/0! | EQ8: =BW8*(cost!$D$27*production!$B$16+production!$C$16*cost!$D$28+cost!$D$29*production!$D$16) -> #DIV/0! | ER8: =BX8*(re!$H$10*re!$C$10+re!$H$11*re!$C$11+re!$H$12*re!$C$12+re!$H$13*re!$C$13+re!$H$14*re!$C$14) -> #DIV/0!
G9: 2032 | H9: ='2'!AB15+'6'!AB15+'7'!AB15+'9'!AB15+'11'!AB15+'12'!AB15+'13'!AB15+'16'!AB15+'17'!AB15+'18'!AB15+'22'!AB15 -> 185.81813 | I9: ='1'!AB15+'2'!AC15+'5'!AB15+'6'!AC15+'7'!AC15+'9'!AC15+'11'!AC15+'12'!AC15+'13'!AC15+'15'!AB15+'16'!AC15+'17'!AC15+'18'!AC15+'19'!AB15+'22'!AC15 -> 355.70539 | K9: ='3'!AB15+'4'!AB15+'10'!AB15+'20'!AB15+'21'!AB15+'23'!AB15 -> 20.304097 | L9: ='8'!AB15+'14'!AB15 -> 187.26086 | M9: ='1'!AD15+'2'!AD15+'3'!AD15+'4'!AD15+'5'!AD15+'6'!AD15+'7'!AD15+'8'!AD15+'9'!AD15+'10'!AD15+'11'!AD15+'12'!AD15+'13'!AD15+'14'!AD15+'15'!AD15+'16'!AD15+'17'!AD15+'18'!AD15+'19'!AD15+'20'!AD15+'21'!AD15+'22'!AD15+'23'!AD15 -> 32.532648 | N9: ='1'!AE15+'2'!AE15+'3'!AE15+'4'!AE15+'5'!AE15+'6'!AE15+'7'!AE15+'8'!AE15+'9'!AE15+'10'!AE15+'11'!AE15+'12'!AE15+'13'!AE15+'14'!AE15+'15'!AE15+'16'!AE15+'17'!AE15+'18'!AE15+'19'!AE15+'20'!AE15+'21'!AE15+'22'!AE15+'23'!AE15 -> 1.9290288 | O9: ='1'!AF15+'2'!AF15+'3'!AF15+'4'!AF15+'5'!AF15+'6'!AF15+'7'!AF15+'8'!AF15+'9'!AF15+'10'!AF15+'11'!AF15+'12'!AF15+'13'!AF15+'14'!AF15+'15'!AF15+'16'!AF15+'17'!AF15+'18'!AF15+'19'!AF15+'20'!AF15+'21'!AF15+'22'!AF15+'23'!AF15 -> 62.331657 | P9: ='1'!AG15+'2'!AG15+'3'!AG15+'4'!AG15+'5'!AG15+'6'!AG15+'7'!AG15+'8'!AG15+'9'!AG15+'10'!AG15+'11'!AG15+'12'!AG15+'13'!AG15+'14'!AG15+'15'!AG15+'16'!AG15+'17'!AG15+'18'!AG15+'19'!AG15+'20'!AG15+'21'!AG15+'22'!AG15+'23'!AG15 -> 56.706117 | Q9: ='1'!AH15+'2'!AH15+'3'!AH15+'4'!AH15+'5'!AH15+'6'!AH15+'7'!AH15+'8'!AH15+'9'!AH15+'10'!AH15+'11'!AH15+'12'!AH15+'13'!AH15+'14'!AH15+'15'!AH15+'16'!AH15+'17'!AH15+'18'!AH15+'19'!AH15+'20'!AH15+'21'!AH15+'22'!AH15+'23'!AH15 -> 1.4586874 | R9: ='1'!AI15+'2'!AI15+'3'!AI15+'4'!AI15+'5'!AI15+'6'!AI15+'7'!AI15+'8'!AI15+'9'!AI15+'10'!AI15+'11'!AI15+'12'!AI15+'13'!AI15+'14'!AI15+'15'!AI15+'16'!AI15+'17'!AI15+'18'!AI15+'19'!AI15+'20'!AI15+'21'!AI15+'22'!AI15+'23'!AI15 -> 9.8414443 | S9: ='1'!AJ15+'2'!AJ15+'3'!AJ15+'4'!AJ15+'5'!AJ15+'6'!AJ15+'7'!AJ15+'8'!AJ15+'9'!AJ15+'10'!AJ15+'11'!AJ15+'12'!AJ15+'13'!AJ15+'14'!AJ15+'15'!AJ15+'16'!AJ15+'17'!AJ15+'18'!AJ15+'19'!AJ15+'20'!AJ15+'21'!AJ15+'22'!AJ15+'23'!AJ15 -> 2.7932211 | T9: ='1'!AK15+'2'!AK15+'3'!AK15+'4'!AK15+'5'!AK15+'6'!AK15+'7'!AK15+'8'!AK15+'9'!AK15+'10'!AK15+'11'!AK15+'12'!AK15+'13'!AK15+'14'!AK15+'15'!AK15+'16'!AK15+'17'!AK15+'18'!AK15+'19'!AK15+'20'!AK15+'21'!AK15+'22'!AK15+'23'!AK15 -> 30.841004 | U9: ='1'!AL15+'2'!AL15+'3'!AL15+'4'!AL15+'5'!AL15+'6'!AL15+'7'!AL15+'8'!AL15+'9'!AL15+'10'!AL15+'11'!AL15+'12'!AL15+'13'!AL15+'14'!AL15+'15'!AL15+'16'!AL15+'17'!AL15+'18'!AL15+'19'!AL15+'20'!AL15+'21'!AL15+'22'!AL15+'23'!AL15 -> 0.074864616 | V9: =SUM(H9:L9) -> 749.08848 | W9: =SUM(M9:U9) -> 198.50867 | X9: =W9/W8-1 -> 0.51679803 | Y9: =((M9+N9)*re!$D$2/re!$C$2+O9*re!$D$3/re!$C$3+P9*re!$D$4/re!$C$4+T9*re!$D$5/re!$C$5+U9*re!$D$6/re!$C$6) -> 336.87123 | Z9: =SUM(AA9:AE9) -> 25.990266 | AA9: =((Y9*277.8)/(re!$B$10*8760))*re!$C$10 -> 14.735133 | AB9: =((Y9*277.8)/(re!$B$11*8760))*re!$C$11 -> 5.4784468 | AC9: =((Y9*277.8)/(re!$B$12*8760))*re!$C$12 -> 1.978328 | AD9: =((Y9*277.8)/(re!$B$13*8760))*re!$C$13 -> 0.58059627 | AE9: =((Y9*277.8)/(re!$B$14*8760))*re!$C$14 -> 3.2177624 | AF9: =SUM('1'!AD15:AL15)+'1'!AA15 -> 149.29152 | AG9: =SUM('2'!AD15:AL15)+'2'!AA15 -> 2.8441397 | AH9: =SUM('3'!AD15:AL15)+'3'!AA15 -> 12.319084 | AI9: =SUM('4'!AD15:AL15)+'4'!AA15 -> 0.91988468 | AJ9: =SUM('5'!AD15:AL15)+'5'!AA15 -> 5.5834852 | AK9: =SUM('6'!AD15:AL15)+'6'!AA15 -> 143.68611 | AL9: =SUM('7'!AD15:AL15)+'7'!AA15 -> 126.98774 | AM9: =SUM('8'!AD15:AL15)+'8'!AA15 -> 237.43159 | AN9: =SUM('9'!AD15:AL15)+'9'!AA15 -> 69.715375 | AO9: =SUM('10'!AD15:AL15)+'10'!AA15 -> 5.1173837 | AP9: =SUM('11'!AD15:AL15)+'11'!AA15 -> 6.5305231 | AQ9: =SUM('12'!AD15:AL15)+'12'!AA15 -> 2.0063112 | AR9: =SUM('13'!AD15:AL15)+'13'!AA15 -> 5.8375268 | AS9: =SUM('14'!AD15:AL15)+'14'!AA15 -> 4.6399427 | AT9: =SUM('15'!AD15:AL15)+'15'!AA15 -> 61.94023 | AU9: =SUM('16'!AD15:AL15)+'16'!AA15 -> 24.844961 | AV9: =SUM('17'!AD15:AL15)+'17'!AA15 -> 42.283531 | AW9: =SUM('18'!AD15:AL15)+'18'!AA15 -> 10.55944 | AX9: =SUM('19'!AD15:AL15)+'19'!AA15 -> 27.416734 | AY9: =SUM('20'!AD15:AL15)+'20'!AA15 -> 1.7565541 | AZ9: =SUM('21'!AD15:AL15)+'21'!AA15 -> 0.15913817 | BA9: =SUM('22'!AD15:AL15)+'22'!AA15 -> 0.51377214 | BB9: =SUM('23'!AD15:AL15)+'23'!AA15 -> 5.2121783 | BC9: =('1'!D15+'2'!D15+'3'!D15+'4'!D15+'5'!D15+'6'!D15+'7'!D15+'8'!D15+'9'!D15+'10'!D15+'12'!D15+'13'!D15+'14'!D15+'15'!D15+'16'!D15+'17'!D15+'18'!D15+'19'!D15+'20'!D15+'21'!D15+'22'!D15+'23'!D15)/('1'!D14+'2'!D14+'3'!D14+'4'!D14+'5'!D14+'6'!D14+'7'!D14+'8'!D14+'9'!D14+'10'!D14+'12'!D14+'13'!D14+'14'!D14+'15'!D14+'16'!D14+'17'!D14+'18'!D14+'19'!D14+'20'!D14+'21'!D14+'22'!D14+'23'!D14)-1 -> 0.19134506 | BD9: =('1'!E15+'2'!E15+'3'!E15+'4'!E15+'5'!E15+'6'!E15+'7'!E15+'8'!E15+'9'!E15+'10'!E15+'12'!E15+'13'!E15+'14'!E15+'15'!E15+'16'!E15+'17'!E15+'18'!E15+'19'!E15+'20'!E15+'21'!E15+'22'!E15+'23'!E15)/('1'!E14+'2'!E14+'3'!E14+'4'!E14+'5'!E14+'6'!E14+'7'!E14+'8'!E14+'9'!E14+'10'!E14+'12'!E14+'13'!E14+'14'!E14+'15'!E14+'16'!E14+'17'!E14+'18'!E14+'19'!E14+'20'!E14+'21'!E14+'22'!E14+'23'!E14)-1 -> 0.19134506 | BE9: =('1'!F15+'2'!F15+'3'!F15+'4'!F15+'5'!F15+'6'!F15+'7'!F15+'8'!F15+'9'!F15+'10'!F15+'12'!F15+'13'!F15+'14'!F15+'15'!F15+'16'!F15+'17'!F15+'18'!F15+'19'!F15+'20'!F15+'21'!F15+'22'!F15+'23'!F15)/('1'!F14+'2'!F14+'3'!F14+'4'!F14+'5'!F14+'6'!F14+'7'!F14+'8'!F14+'9'!F14+'10'!F14+'12'!F14+'13'!F14+'14'!F14+'15'!F14+'16'!F14+'17'!F14+'18'!F14+'19'!F14+'20'!F14+'21'!F14+'22'!F14+'23'!F14)-1 -> 0.19133541 | BF9: =W9/W8-1 -> 0.51679803 | BG9: 2032 | BH9: 0.17 | BI9: 0.3 | BJ9: =BI9-BH9 -> 0.13 | BK9: ='2 (RU)'!AB15+'6 (RU)'!AB15+'7 (RU)'!AB15+'9 (RU)'!AB15+'11 (RU)'!AB15+'12 (RU)'!AB15+'13 (RU)'!AB15+'16 (RU)'!AB15+'17 (RU)'!AB15+'18 (RU)'!AB15+'22 (RU)'!AB15 -> #DIV/0! | BL9: ='1 (RU)'!AB15+'2 (RU)'!AC15+'5 (RU)'!AB15+'6 (RU)'!AC15+'7 (RU)'!AC15+'9 (RU)'!AC15+'11 (RU)'!AC15+'12 (RU)'!AC15+'13 (RU)'!AC15+'15 (RU)'!AB15+'16 (RU)'!AC15+'17 (RU)'!AC15+'18 (RU)'!AC15+'19 (RU)'!AB15+'22 (RU)'!AC15 -> #DIV/0! | BN9: ='3 (RU)'!AB15+'4 (RU)'!AB15+'10 (RU)'!AB15+'20 (RU)'!AB15+'21 (RU)'!AB15+'23 (RU)'!AB15 -> #DIV/0! | BO9: ='8 (RU)'!AB15+'14 (RU)'!AB15 -> #DIV/0! | BP9: ='1 (RU)'!AD15+'2 (RU)'!AD15+'3 (RU)'!AD15+'4 (RU)'!AD15+'5 (RU)'!AD15+'6 (RU)'!AD15+'7 (RU)'!AD15+'8 (RU)'!AD15+'9 (RU)'!AD15+'10 (RU)'!AD15+'11 (RU)'!AD15+'12 (RU)'!AD15+'13 (RU)'!AD15+'14 (RU)'!AD15+'15 (RU)'!AD15+'16 (RU)'!AD15+'17 (RU)'!AD15+'18 (RU)'!AD15+'19 (RU)'!AD15+'20 (RU)'!AD15+'21 (RU)'!AD15+'22 (RU)'!AD15+'23 (RU)'!AD15 -> #DIV/0! | BQ9: ='1 (RU)'!AE15+'2 (RU)'!AE15+'3 (RU)'!AE15+'4 (RU)'!AE15+'5 (RU)'!AE15+'6 (RU)'!AE15+'7 (RU)'!AE15+'8 (RU)'!AE15+'9 (RU)'!AE15+'10 (RU)'!AE15+'11 (RU)'!AE15+'12 (RU)'!AE15+'13 (RU)'!AE15+'14 (RU)'!AE15+'15 (RU)'!AE15+'16 (RU)'!AE15+'17 (RU)'!AE15+'18 (RU)'!AE15+'19 (RU)'!AE15+'20 (RU)'!AE15+'21 (RU)'!AE15+'22 (RU)'!AE15+'23 (RU)'!AE15 -> #DIV/0! | BR9: ='1 (RU)'!AF15+'2 (RU)'!AF15+'3 (RU)'!AF15+'4 (RU)'!AF15+'5 (RU)'!AF15+'6 (RU)'!AF15+'7 (RU)'!AF15+'8 (RU)'!AF15+'9 (RU)'!AF15+'10 (RU)'!AF15+'11 (RU)'!AF15+'12 (RU)'!AF15+'13 (RU)'!AF15+'14 (RU)'!AF15+'15 (RU)'!AF15+'16 (RU)'!AF15+'17 (RU)'!AF15+'18 (RU)'!AF15+'19 (RU)'!AF15+'20 (RU)'!AF15+'21 (RU)'!AF15+'22 (RU)'!AF15+'23 (RU)'!AF15 -> #DIV/0! | BS9: ='1 (RU)'!AG15+'2 (RU)'!AG15+'3 (RU)'!AG15+'4 (RU)'!AG15+'5 (RU)'!AG15+'6 (RU)'!AG15+'7 (RU)'!AG15+'8 (RU)'!AG15+'9 (RU)'!AG15+'10 (RU)'!AG15+'11 (RU)'!AG15+'12 (RU)'!AG15+'13 (RU)'!AG15+'14 (RU)'!AG15+'15 (RU)'!AG15+'16 (RU)'!AG15+'17 (RU)'!AG15+'18 (RU)'!AG15+'19 (RU)'!AG15+'20 (RU)'!AG15+'21 (RU)'!AG15+'22 (RU)'!AG15+'23 (RU)'!AG15 -> #DIV/0! | BT9: ='1 (RU)'!AH15+'2 (RU)'!AH15+'3 (RU)'!AH15+'4 (RU)'!AH15+'5 (RU)'!AH15+'6 (RU)'!AH15+'7 (RU)'!AH15+'8 (RU)'!AH15+'9 (RU)'!AH15+'10 (RU)'!AH15+'11 (RU)'!AH15+'12 (RU)'!AH15+'13 (RU)'!AH15+'14 (RU)'!AH15+'15 (RU)'!AH15+'16 (RU)'!AH15+'17 (RU)'!AH15+'18 (RU)'!AH15+'19 (RU)'!AH15+'20 (RU)'!AH15+'21 (RU)'!AH15+'22 (RU)'!AH15+'23 (RU)'!AH15 -> #DIV/0! | BU9: ='1 (RU)'!AI15+'2 (RU)'!AI15+'3 (RU)'!AI15+'4 (RU)'!AI15+'5 (RU)'!AI15+'6 (RU)'!AI15+'7 (RU)'!AI15+'8 (RU)'!AI15+'9 (RU)'!AI15+'10 (RU)'!AI15+'11 (RU)'!AI15+'12 (RU)'!AI15+'13 (RU)'!AI15+'14 (RU)'!AI15+'15 (RU)'!AI15+'16 (RU)'!AI15+'17 (RU)'!AI15+'18 (RU)'!AI15+'19 (RU)'!AI15+'20 (RU)'!AI15+'21 (RU)'!AI15+'22 (RU)'!AI15+'23 (RU)'!AI15 -> #DIV/0! | BV9: ='1 (RU)'!AJ15+'2 (RU)'!AJ15+'3 (RU)'!AJ15+'4 (RU)'!AJ15+'5 (RU)'!AJ15+'6 (RU)'!AJ15+'7 (RU)'!AJ15+'8 (RU)'!AJ15+'9 (RU)'!AJ15+'10 (RU)'!AJ15+'11 (RU)'!AJ15+'12 (RU)'!AJ15+'13 (RU)'!AJ15+'14 (RU)'!AJ15+'15 (RU)'!AJ15+'16 (RU)'!AJ15+'17 (RU)'!AJ15+'18 (RU)'!AJ15+'19 (RU)'!AJ15+'20 (RU)'!AJ15+'21 (RU)'!AJ15+'22 (RU)'!AJ15+'23 (RU)'!AJ15 -> #DIV/0! | BW9: ='1 (RU)'!AK15+'2 (RU)'!AK15+'3 (RU)'!AK15+'4 (RU)'!AK15+'5 (RU)'!AK15+'6 (RU)'!AK15+'7 (RU)'!AK15+'8 (RU)'!AK15+'9 (RU)'!AK15+'10 (RU)'!AK15+'11 (RU)'!AK15+'12 (RU)'!AK15+'13 (RU)'!AK15+'14 (RU)'!AK15+'15 (RU)'!AK15+'16 (RU)'!AK15+'17 (RU)'!AK15+'18 (RU)'!AK15+'19 (RU)'!AK15+'20 (RU)'!AK15+'21 (RU)'!AK15+'22 (RU)'!AK15+'23 (RU)'!AK15 -> #DIV/0! | BX9: ='1 (RU)'!AL15+'2 (RU)'!AL15+'3 (RU)'!AL15+'4 (RU)'!AL15+'5 (RU)'!AL15+'6 (RU)'!AL15+'7 (RU)'!AL15+'8 (RU)'!AL15+'9 (RU)'!AL15+'10 (RU)'!AL15+'11 (RU)'!AL15+'12 (RU)'!AL15+'13 (RU)'!AL15+'14 (RU)'!AL15+'15 (RU)'!AL15+'16 (RU)'!AL15+'17 (RU)'!AL15+'18 (RU)'!AL15+'19 (RU)'!AL15+'20 (RU)'!AL15+'21 (RU)'!AL15+'22 (RU)'!AL15+'23 (RU)'!AL15 -> #DIV/0! | BY9: =SUM(BK9:BO9) -> #DIV/0! | BZ9: =SUM(BP9:BX9) -> #DIV/0! | CC9: =VLOOKUP(CC$1,emissions!$A$2:$B$5,2,FALSE)*BK9 -> #DIV/0! | CD9: =VLOOKUP(CD$1,emissions!$A$2:$B$5,2,FALSE)*BL9 -> #DIV/0! | CF9: =VLOOKUP(CF$1,emissions!$A$2:$B$5,2,FALSE)*BN9 -> #DIV/0! | CG9: =VLOOKUP(CG$1,emissions!$A$2:$B$5,2,FALSE)*BO9 -> #DIV/0! | CH9: =BP9*(emissions!$D$3*production!$B$4+emissions!$D$4*production!$C$4+emissions!$D$5*production!$D$4+emissions!$D$6*production!$E$4) -> #DIV/0! | CI9: =BQ9*(emissions!$D$3*production!$B$4+emissions!$D$4*production!$C$4+emissions!$D$5*production!$D$4+emissions!$D$6*production!$E$4) -> #DIV/0! | CJ9: =BR9*(emissions!$D$8*production!$B$6+emissions!$D$9*production!$C$6+emissions!$D$10*production!$D$6) -> #DIV/0! | CK9: =BS9*(emissions!$D$12*production!$B$8+emissions!$D$13*production!$C$8+emissions!$D$14*production!$D$8) -> #DIV/0! | CL9: =BT9*(emissions!$D$16*production!$B$10+production!$C$10*emissions!$D$17) -> #DIV/0! | CM9: =BU9*(emissions!$D$19*production!$B$12+production!$C$12*emissions!$D$20+emissions!$D$21*production!$D$12) -> #DIV/0! | CN9: =BV9*(emissions!$D$23*production!$B$14+production!$C$14*emissions!$D$24+emissions!$D$25*production!$D$14) -> #DIV/0! | CO9: =BW9*(emissions!$D$27*production!$B$16+production!$C$16*emissions!$D$28+production!$D$16*emissions!$D$29) -> #DIV/0! | CP9: 0 | CS9: =SUM(CC9:CP9) -> #DIV/0! | CT9: =SUM(CC9:CP9)/SUM(BK9:BX9) -> #DIV/0! | CU9: =(CT9-CW9) -> #DIV/0! | CV9: =CT9-CX9 -> #DIV/0! | CW9: =93.3*(1-BH9) -> 77.439 | CX9: =93.3*(1-BI9) -> 65.31 | CY9: =IF(G9<2028,0,IF(CT9>=CW9,CU9,IF(AND(CT9<CW9,CT9>=CX9),CV9,0))*SUM(BK9:BX9)) -> #DIV/0! | CZ9: =IF(CT9>=CW9,380*CY9,IF(AND(CT9<CW9,CT9>=CX9),100*CY9,0)) -> #DIV/0! | DA9: =IF(G9<2028,"",IF(CT9>=CW9,"Red",IF(AND(CT9<CW9,CT9>=CX9),"Yellow","Green"))) -> #DIV/0! | DB9: =IF(G9<2028,0,IF(CT9<CX9,-CV9*SUM(BK9:BX9),0)) -> #DIV/0! | DC9: =DB9*380 -> #DIV/0! | DD9: 2032 | DE9: =CY9-DB9 -> #DIV/0! | DF9: =CS9 -> #DIV/0! | DG9: 2032 | DH9: =CW9*SUM(BK9:BX9) -> #DIV/0! | DI9: =CX9*SUM(BK9:BX9) -> #DIV/0! | DJ9: =DI9 -> #DIV/0! | DK9: =DH9-DI9 -> #DIV/0! | DL9: =MAX(DH9:DK9) -> #DIV/0! | DM9: =(CZ9-DC9)/1000000 -> #DIV/0! | DN9: =DE9/1000000 -> #DIV/0! | DO9: =ED9/1000000 -> #DIV/0! | DP9: =DM9+DO9 -> #DIV/0! | DQ9: 13482 | DR9: 15222 | DT9: 691 | DU9: 2353 | DV9: =DQ9*VLOOKUP(DQ$1,emissions!$A$2:$B$5,2,FALSE) -> 1968372 | DW9: =DR9*VLOOKUP(DR$1,emissions!$A$2:$B$5,2,FALSE) -> 2222412 | DY9: =DT9*VLOOKUP(DT$1,emissions!$A$2:$B$5,2,FALSE) -> 100195 | DZ9: =DU9*VLOOKUP(DU$1,emissions!$A$2:$B$5,2,FALSE) -> 265889 | EA9: =SUM(DV9:DZ9) -> 4556868 | EB9: =1/(SUM(DQ9:DU9)/EA9) -> 143.53244 | ED9: =SUM(EE9:ER9) -> #DIV/0! | EE9: =cost!$B$2*BK9 -> #DIV/0! | EF9: =cost!$B$3*BL9 -> #DIV/0! | EH9: =cost!$B$4*BN9 -> #DIV/0! | EI9: =cost!$B$5*$BO$2 -> #DIV/0! | EJ9: =BP9*(cost!$D$3*production!$B$4+production!$C$4*cost!$D$4+cost!$D$5*production!$D$4+production!$E$4*cost!$D$6) -> #DIV/0! | EK9: =BQ9*(cost!$D$3*production!$B$4+production!$C$4*cost!$D$4+cost!$D$5*production!$D$4+production!$E$4*cost!$D$6) -> #DIV/0! | EL9: =BR9*(cost!$D$8*production!$B$6+cost!$D$9*production!$C$6+$D$10*production!$D$6) -> #DIV/0! | EM9: =BS9*(cost!$D$12*production!$B$8+cost!$D$13*production!$C$8+cost!$D$14*production!$D$8) -> #DIV/0! | EN9: =BT9*(cost!$D$16*production!$B$10+production!$C$10*cost!$D$17) -> #DIV/0! | EO9: =BU9*(cost!$D$19*production!$B$12+production!$C$12*cost!$D$20+cost!$D$21*production!$D$12) -> #DIV/0! | EP9: =BV9*(cost!$D$23*production!$B$14+production!$C$14*cost!$D$24+cost!$D$25*production!$D$14) -> #DIV/0! | EQ9: =BW9*(cost!$D$27*production!$B$16+production!$C$16*cost!$D$28+cost!$D$29*production!$D$16) -> #DIV/0! | ER9: =BX9*(re!$H$10*re!$C$10+re!$H$11*re!$C$11+re!$H$12*re!$C$12+re!$H$13*re!$C$13+re!$H$14*re!$C$14) -> #DIV/0!
A10: Fuel Swaps | B10: k | C10: t0 | G10: 2033 | H10: ='2'!AB16+'6'!AB16+'7'!AB16+'9'!AB16+'11'!AB16+'12'!AB16+'13'!AB16+'16'!AB16+'17'!AB16+'18'!AB16+'22'!AB16 -> 148.9351 | I10: ='1'!AB16+'2'!AC16+'5'!AB16+'6'!AC16+'7'!AC16+'9'!AC16+'11'!AC16+'12'!AC16+'13'!AC16+'15'!AB16+'16'!AC16+'17'!AC16+'18'!AC16+'19'!AB16+'22'!AC16 -> 345.33783 | K10: ='3'!AB16+'4'!AB16+'10'!AB16+'20'!AB16+'21'!AB16+'23'!AB16 -> 18.574099 | L10: ='8'!AB16+'14'!AB16 -> 171.26729 | M10: ='1'!AD16+'2'!AD16+'3'!AD16+'4'!AD16+'5'!AD16+'6'!AD16+'7'!AD16+'8'!AD16+'9'!AD16+'10'!AD16+'11'!AD16+'12'!AD16+'13'!AD16+'14'!AD16+'15'!AD16+'16'!AD16+'17'!AD16+'18'!AD16+'19'!AD16+'20'!AD16+'21'!AD16+'22'!AD16+'23'!AD16 -> 47.277586 | N10: ='1'!AE16+'2'!AE16+'3'!AE16+'4'!AE16+'5'!AE16+'6'!AE16+'7'!AE16+'8'!AE16+'9'!AE16+'10'!AE16+'11'!AE16+'12'!AE16+'13'!AE16+'14'!AE16+'15'!AE16+'16'!AE16+'17'!AE16+'18'!AE16+'19'!AE16+'20'!AE16+'21'!AE16+'22'!AE16+'23'!AE16 -> 2.803272 | O10: ='1'!AF16+'2'!AF16+'3'!AF16+'4'!AF16+'5'!AF16+'6'!AF16+'7'!AF16+'8'!AF16+'9'!AF16+'10'!AF16+'11'!AF16+'12'!AF16+'13'!AF16+'14'!AF16+'15'!AF16+'16'!AF16+'17'!AF16+'18'!AF16+'19'!AF16+'20'!AF16+'21'!AF16+'22'!AF16+'23'!AF16 -> 90.577741 | P10: ='1'!AG16+'2'!AG16+'3'!AG16+'4'!AG16+'5'!AG16+'6'!AG16+'7'!AG16+'8'!AG16+'9'!AG16+'10'!AG16+'11'!AG16+'12'!AG16+'13'!AG16+'14'!AG16+'15'!AG16+'16'!AG16+'17'!AG16+'18'!AG16+'19'!AG16+'20'!AG16+'21'!AG16+'22'!AG16+'23'!AG16 -> 82.411043 | Q10: ='1'!AH16+'2'!AH16+'3'!AH16+'4'!AH16+'5'!AH16+'6'!AH16+'7'!AH16+'8'!AH16+'9'!AH16+'10'!AH16+'11'!AH16+'12'!AH16+'13'!AH16+'14'!AH16+'15'!AH16+'16'!AH16+'17'!AH16+'18'!AH16+'19'!AH16+'20'!AH16+'21'!AH16+'22'!AH16+'23'!AH16 -> 2.1175602 | R10: ='1'!AI16+'2'!AI16+'3'!AI16+'4'!AI16+'5'!AI16+'6'!AI16+'7'!AI16+'8'!AI16+'9'!AI16+'10'!AI16+'11'!AI16+'12'!AI16+'13'!AI16+'14'!AI16+'15'!AI16+'16'!AI16+'17'!AI16+'18'!AI16+'19'!AI16+'20'!AI16+'21'!AI16+'22'!AI16+'23'!AI16 -> 14.302189 | S10: ='1'!AJ16+'2'!AJ16+'3'!AJ16+'4'!AJ16+'5'!AJ16+'6'!AJ16+'7'!AJ16+'8'!AJ16+'9'!AJ16+'10'!AJ16+'11'!AJ16+'12'!AJ16+'13'!AJ16+'14'!AJ16+'15'!AJ16+'16'!AJ16+'17'!AJ16+'18'!AJ16+'19'!AJ16+'20'!AJ16+'21'!AJ16+'22'!AJ16+'23'!AJ16 -> 4.05508 | T10: ='1'!AK16+'2'!AK16+'3'!AK16+'4'!AK16+'5'!AK16+'6'!AK16+'7'!AK16+'8'!AK16+'9'!AK16+'10'!AK16+'11'!AK16+'12'!AK16+'13'!AK16+'14'!AK16+'15'!AK16+'16'!AK16+'17'!AK16+'18'!AK16+'19'!AK16+'20'!AK16+'21'!AK16+'22'!AK16+'23'!AK16 -> 44.830778 | U10: ='1'!AL16+'2'!AL16+'3'!AL16+'4'!AL16+'5'!AL16+'6'!AL16+'7'!AL16+'8'!AL16+'9'!AL16+'10'!AL16+'11'!AL16+'12'!AL16+'13'!AL16+'14'!AL16+'15'!AL16+'16'!AL16+'17'!AL16+'18'!AL16+'19'!AL16+'20'!AL16+'21'!AL16+'22'!AL16+'23'!AL16 -> 0.1089546 | V10: =SUM(H10:L10) -> 684.11432 | W10: =SUM(M10:U10) -> 288.4842 | X10: =W10/W9-1 -> 0.45325743 | Y10: =((M10+N10)*re!$D$2/re!$C$2+O10*re!$D$3/re!$C$3+P10*re!$D$4/re!$C$4+T10*re!$D$5/re!$C$5+U10*re!$D$6/re!$C$6) -> 489.57004 | Z10: =SUM(AA10:AE10) -> 37.771274 | AA10: =((Y10*277.8)/(re!$B$10*8760))*re!$C$10 -> 21.414353 | AB10: =((Y10*277.8)/(re!$B$11*8760))*re!$C$11 -> 7.9617466 | AC10: =((Y10*277.8)/(re!$B$12*8760))*re!$C$12 -> 2.8750752 | AD10: =((Y10*277.8)/(re!$B$13*8760))*re!$C$13 -> 0.84377206 | AE10: =((Y10*277.8)/(re!$B$14*8760))*re!$C$14 -> 4.6763271 | AF10: =SUM('1'!AD16:AL16)+'1'!AA16 -> 152.22733 | AG10: =SUM('2'!AD16:AL16)+'2'!AA16 -> 2.9135082 | AH10: =SUM('3'!AD16:AL16)+'3'!AA16 -> 12.625589 | AI10: =SUM('4'!AD16:AL16)+'4'!AA16 -> 0.94403963 | AJ10: =SUM('5'!AD16:AL16)+'5'!AA16 -> 5.7156654 | AK10: =SUM('6'!AD16:AL16)+'6'!AA16 -> 146.82999 | AL10: =SUM('7'!AD16:AL16)+'7'!AA16 -> 130.0628 | AM10: =SUM('8'!AD16:AL16)+'8'!AA16 -> 246.22937 | AN10: =SUM('9'!AD16:AL16)+'9'!AA16 -> 71.365777 | AO10: =SUM('10'!AD16:AL16)+'10'!AA16 -> 5.2247573 | AP10: =SUM('11'!AD16:AL16)+'11'!AA16 -> 6.691861 | AQ10: =SUM('12'!AD16:AL16)+'12'!AA16 -> 2.0558775 | AR10: =SUM('13'!AD16:AL16)+'13'!AA16 -> 5.981744 | AS10: =SUM('14'!AD16:AL16)+'14'!AA16 -> 4.804587 | AT10: =SUM('15'!AD16:AL16)+'15'!AA16 -> 63.406568 | AU10: =SUM('16'!AD16:AL16)+'16'!AA16 -> 25.45876 | AV10: =SUM('17'!AD16:AL16)+'17'!AA16 -> 43.328154 | AW10: =SUM('18'!AD16:AL16)+'18'!AA16 -> 10.820313 | AX10: =SUM('19'!AD16:AL16)+'19'!AA16 -> 28.065782 | AY10: =SUM('20'!AD16:AL16)+'20'!AA16 -> 1.8026789 | AZ10: =SUM('21'!AD16:AL16)+'21'!AA16 -> 0.16315249 | BA10: =SUM('22'!AD16:AL16)+'22'!AA16 -> 0.52593489 | BB10: =SUM('23'!AD16:AL16)+'23'!AA16 -> 5.354292 | BC10: =('1'!D16+'2'!D16+'3'!D16+'4'!D16+'5'!D16+'6'!D16+'7'!D16+'8'!D16+'9'!D16+'10'!D16+'12'!D16+'13'!D16+'14'!D16+'15'!D16+'16'!D16+'17'!D16+'18'!D16+'19'!D16+'20'!D16+'21'!D16+'22'!D16+'23'!D16)/('1'!D15+'2'!D15+'3'!D15+'4'!D15+'5'!D15+'6'!D15+'7'!D15+'8'!D15+'9'!D15+'10'!D15+'12'!D15+'13'!D15+'14'!D15+'15'!D15+'16'!D15+'17'!D15+'18'!D15+'19'!D15+'20'!D15+'21'!D15+'22'!D15+'23'!D15)-1 -> 0.16685691 | BD10: =('1'!E16+'2'!E16+'3'!E16+'4'!E16+'5'!E16+'6'!E16+'7'!E16+'8'!E16+'9'!E16+'10'!E16+'12'!E16+'13'!E16+'14'!E16+'15'!E16+'16'!E16+'17'!E16+'18'!E16+'19'!E16+'20'!E16+'21'!E16+'22'!E16+'23'!E16)/('1'!E15+'2'!E15+'3'!E15+'4'!E15+'5'!E15+'6'!E15+'7'!E15+'8'!E15+'9'!E15+'10'!E15+'12'!E15+'13'!E15+'14'!E15+'15'!E15+'16'!E15+'17'!E15+'18'!E15+'19'!E15+'20'!E15+'21'!E15+'22'!E15+'23'!E15)-1 -> 0.16685691 | BE10: =('1'!F16+'2'!F16+'3'!F16+'4'!F16+'5'!F16+'6'!F16+'7'!F16+'8'!F16+'9'!F16+'10'!F16+'12'!F16+'13'!F16+'14'!F16+'15'!F16+'16'!F16+'17'!F16+'18'!F16+'19'!F16+'20'!F16+'21'!F16+'22'!F16+'23'!F16)/('1'!F15+'2'!F15+'3'!F15+'4'!F15+'5'!F15+'6'!F15+'7'!F15+'8'!F15+'9'!F15+'10'!F15+'12'!F15+'13'!F15+'14'!F15+'15'!F15+'16'!F15+'17'!F15+'18'!F15+'19'!F15+'20'!F15+'21'!F15+'22'!F15+'23'!F15)-1 -> 0.167003 | BF10: =W10/W9-1 -> 0.45325743 | BG10: 2033 | BH10: 0.21 | BI10: 0.34 | BJ10: =BI10-BH10 -> 0.13 | BK10: ='2 (RU)'!AB16+'6 (RU)'!AB16+'7 (RU)'!AB16+'9 (RU)'!AB16+'11 (RU)'!AB16+'12 (RU)'!AB16+'13 (RU)'!AB16+'16 (RU)'!AB16+'17 (RU)'!AB16+'18 (RU)'!AB16+'22 (RU)'!AB16 -> #DIV/0! | BL10: ='1 (RU)'!AB16+'2 (RU)'!AC16+'5 (RU)'!AB16+'6 (RU)'!AC16+'7 (RU)'!AC16+'9 (RU)'!AC16+'11 (RU)'!AC16+'12 (RU)'!AC16+'13 (RU)'!AC16+'15 (RU)'!AB16+'16 (RU)'!AC16+'17 (RU)'!AC16+'18 (RU)'!AC16+'19 (RU)'!AB16+'22 (RU)'!AC16 -> #DIV/0! | BN10: ='3 (RU)'!AB16+'4 (RU)'!AB16+'10 (RU)'!AB16+'20 (RU)'!AB16+'21 (RU)'!AB16+'23 (RU)'!AB16 -> #DIV/0! | BO10: ='8 (RU)'!AB16+'14 (RU)'!AB16 -> #DIV/0! | BP10: ='1 (RU)'!AD16+'2 (RU)'!AD16+'3 (RU)'!AD16+'4 (RU)'!AD16+'5 (RU)'!AD16+'6 (RU)'!AD16+'7 (RU)'!AD16+'8 (RU)'!AD16+'9 (RU)'!AD16+'10 (RU)'!AD16+'11 (RU)'!AD16+'12 (RU)'!AD16+'13 (RU)'!AD16+'14 (RU)'!AD16+'15 (RU)'!AD16+'16 (RU)'!AD16+'17 (RU)'!AD16+'18 (RU)'!AD16+'19 (RU)'!AD16+'20 (RU)'!AD16+'21 (RU)'!AD16+'22 (RU)'!AD16+'23 (RU)'!AD16 -> #DIV/0! | BQ10: ='1 (RU)'!AE16+'2 (RU)'!AE16+'3 (RU)'!AE16+'4 (RU)'!AE16+'5 (RU)'!AE16+'6 (RU)'!AE16+'7 (RU)'!AE16+'8 (RU)'!AE16+'9 (RU)'!AE16+'10 (RU)'!AE16+'11 (RU)'!AE16+'12 (RU)'!AE16+'13 (RU)'!AE16+'14 (RU)'!AE16+'15 (RU)'!AE16+'16 (RU)'!AE16+'17 (RU)'!AE16+'18 (RU)'!AE16+'19 (RU)'!AE16+'20 (RU)'!AE16+'21 (RU)'!AE16+'22 (RU)'!AE16+'23 (RU)'!AE16 -> #DIV/0! | BR10: ='1 (RU)'!AF16+'2 (RU)'!AF16+'3 (RU)'!AF16+'4 (RU)'!AF16+'5 (RU)'!AF16+'6 (RU)'!AF16+'7 (RU)'!AF16+'8 (RU)'!AF16+'9 (RU)'!AF16+'10 (RU)'!AF16+'11 (RU)'!AF16+'12 (RU)'!AF16+'13 (RU)'!AF16+'14 (RU)'!AF16+'15 (RU)'!AF16+'16 (RU)'!AF16+'17 (RU)'!AF16+'18 (RU)'!AF16+'19 (RU)'!AF16+'20 (RU)'!AF16+'21 (RU)'!AF16+'22 (RU)'!AF16+'23 (RU)'!AF16 -> #DIV/0! | BS10: ='1 (RU)'!AG16+'2 (RU)'!AG16+'3 (RU)'!AG16+'4 (RU)'!AG16+'5 (RU)'!AG16+'6 (RU)'!AG16+'7 (RU)'!AG16+'8 (RU)'!AG16+'9 (RU)'!AG16+'10 (RU)'!AG16+'11 (RU)'!AG16+'12 (RU)'!AG16+'13 (RU)'!AG16+'14 (RU)'!AG16+'15 (RU)'!AG16+'16 (RU)'!AG16+'17 (RU)'!AG16+'18 (RU)'!AG16+'19 (RU)'!AG16+'20 (RU)'!AG16+'21 (RU)'!AG16+'22 (RU)'!AG16+'23 (RU)'!AG16 -> #DIV/0! | BT10: ='1 (RU)'!AH16+'2 (RU)'!AH16+'3 (RU)'!AH16+'4 (RU)'!AH16+'5 (RU)'!AH16+'6 (RU)'!AH16+'7 (RU)'!AH16+'8 (RU)'!AH16+'9 (RU)'!AH16+'10 (RU)'!AH16+'11 (RU)'!AH16+'12 (RU)'!AH16+'13 (RU)'!AH16+'14 (RU)'!AH16+'15 (RU)'!AH16+'16 (RU)'!AH16+'17 (RU)'!AH16+'18 (RU)'!AH16+'19 (RU)'!AH16+'20 (RU)'!AH16+'21 (RU)'!AH16+'22 (RU)'!AH16+'23 (RU)'!AH16 -> #DIV/0! | BU10: ='1 (RU)'!AI16+'2 (RU)'!AI16+'3 (RU)'!AI16+'4 (RU)'!AI16+'5 (RU)'!AI16+'6 (RU)'!AI16+'7 (RU)'!AI16+'8 (RU)'!AI16+'9 (RU)'!AI16+'10 (RU)'!AI16+'11 (RU)'!AI16+'12 (RU)'!AI16+'13 (RU)'!AI16+'14 (RU)'!AI16+'15 (RU)'!AI16+'16 (RU)'!AI16+'17 (RU)'!AI16+'18 (RU)'!AI16+'19 (RU)'!AI16+'20 (RU)'!AI16+'21 (RU)'!AI16+'22 (RU)'!AI16+'23 (RU)'!AI16 -> #DIV/0! | BV10: ='1 (RU)'!AJ16+'2 (RU)'!AJ16+'3 (RU)'!AJ16+'4 (RU)'!AJ16+'5 (RU)'!AJ16+'6 (RU)'!AJ16+'7 (RU)'!AJ16+'8 (RU)'!AJ16+'9 (RU)'!AJ16+'10 (RU)'!AJ16+'11 (RU)'!AJ16+'12 (RU)'!AJ16+'13 (RU)'!AJ16+'14 (RU)'!AJ16+'15 (RU)'!AJ16+'16 (RU)'!AJ16+'17 (RU)'!AJ16+'18 (RU)'!AJ16+'19 (RU)'!AJ16+'20 (RU)'!AJ16+'21 (RU)'!AJ16+'22 (RU)'!AJ16+'23 (RU)'!AJ16 -> #DIV/0! | BW10: ='1 (RU)'!AK16+'2 (RU)'!AK16+'3 (RU)'!AK16+'4 (RU)'!AK16+'5 (RU)'!AK16+'6 (RU)'!AK16+'7 (RU)'!AK16+'8 (RU)'!AK16+'9 (RU)'!AK16+'10 (RU)'!AK16+'11 (RU)'!AK16+'12 (RU)'!AK16+'13 (RU)'!AK16+'14 (RU)'!AK16+'15 (RU)'!AK16+'16 (RU)'!AK16+'17 (RU)'!AK16+'18 (RU)'!AK16+'19 (RU)'!AK16+'20 (RU)'!AK16+'21 (RU)'!AK16+'22 (RU)'!AK16+'23 (RU)'!AK16 -> #DIV/0! | BX10: ='1 (RU)'!AL16+'2 (RU)'!AL16+'3 (RU)'!AL16+'4 (RU)'!AL16+'5 (RU)'!AL16+'6 (RU)'!AL16+'7 (RU)'!AL16+'8 (RU)'!AL16+'9 (RU)'!AL16+'10 (RU)'!AL16+'11 (RU)'!AL16+'12 (RU)'!AL16+'13 (RU)'!AL16+'14 (RU)'!AL16+'15 (RU)'!AL16+'16 (RU)'!AL16+'17 (RU)'!AL16+'18 (RU)'!AL16+'19 (RU)'!AL16+'20 (RU)'!AL16+'21 (RU)'!AL16+'22 (RU)'!AL16+'23 (RU)'!AL16 -> #DIV/0! | BY10: =SUM(BK10:BO10) -> #DIV/0! | BZ10: =SUM(BP10:BX10) -> #DIV/0! | CC10: =VLOOKUP(CC$1,emissions!$A$2:$B$5,2,FALSE)*BK10 -> #DIV/0! | CD10: =VLOOKUP(CD$1,emissions!$A$2:$B$5,2,FALSE)*BL10 -> #DIV/0! | CF10: =VLOOKUP(CF$1,emissions!$A$2:$B$5,2,FALSE)*BN10 -> #DIV/0! | CG10: =VLOOKUP(CG$1,emissions!$A$2:$B$5,2,FALSE)*BO10 -> #DIV/0! | CH10: =BP10*(emissions!$D$3*production!$B$4+emissions!$D$4*production!$C$4+emissions!$D$5*production!$D$4+emissions!$D$6*production!$E$4) -> #DIV/0! | CI10: =BQ10*(emissions!$D$3*production!$B$4+emissions!$D$4*production!$C$4+emissions!$D$5*production!$D$4+emissions!$D$6*production!$E$4) -> #DIV/0! | CJ10: =BR10*(emissions!$D$8*production!$B$6+emissions!$D$9*production!$C$6+emissions!$D$10*production!$D$6) -> #DIV/0! | CK10: =BS10*(emissions!$D$12*production!$B$8+emissions!$D$13*production!$C$8+emissions!$D$14*production!$D$8) -> #DIV/0! | CL10: =BT10*(emissions!$D$16*production!$B$10+production!$C$10*emissions!$D$17) -> #DIV/0! | CM10: =BU10*(emissions!$D$19*production!$B$12+production!$C$12*emissions!$D$20+emissions!$D$21*production!$D$12) -> #DIV/0! | CN10: =BV10*(emissions!$D$23*production!$B$14+production!$C$14*emissions!$D$24+emissions!$D$25*production!$D$14) -> #DIV/0! | CO10: =BW10*(emissions!$D$27*production!$B$16+production!$C$16*emissions!$D$28+production!$D$16*emissions!$D$29) -> #DIV/0! | CP10: 0 | CS10: =SUM(CC10:CP10) -> #DIV/0! | CT10: =SUM(CC10:CP10)/SUM(BK10:BX10) -> #DIV/0! | CU10: =(CT10-CW10) -> #DIV/0! | CV10: =CT10-CX10 -> #DIV/0! | CW10: =93.3*(1-BH10) -> 73.707 | CX10: =93.3*(1-BI10) -> 61.578 | CY10: =IF(G10<2028,0,IF(CT10>=CW10,CU10,IF(AND(CT10<CW10,CT10>=CX10),CV10,0))*SUM(BK10:BX10)) -> #DIV/0! | CZ10: =IF(CT10>=CW10,380*CY10,IF(AND(CT10<CW10,CT10>=CX10),100*CY10,0)) -> #DIV/0! | DA10: =IF(G10<2028,"",IF(CT10>=CW10,"Red",IF(AND(CT10<CW10,CT10>=CX10),"Yellow","Green"))) -> #DIV/0! | DB10: =IF(G10<2028,0,IF(CT10<CX10,-CV10*SUM(BK10:BX10),0)) -> #DIV/0! | DC10: =DB10*380 -> #DIV/0! | DD10: 2033 | DE10: =CY10-DB10 -> #DIV/0! | DF10: =CS10 -> #DIV/0! | DG10: 2033 | DH10: =CW10*SUM(BK10:BX10) -> #DIV/0! | DI10: =CX10*SUM(BK10:BX10) -> #DIV/0! | DJ10: =DI10 -> #DIV/0! | DK10: =DH10-DI10 -> #DIV/0! | DL10: =MAX(DH10:DK10) -> #DIV/0! | DM10: =(CZ10-DC10)/1000000 -> #DIV/0! | DN10: =DE10/1000000 -> #DIV/0! | DO10: =ED10/1000000 -> #DIV/0! | DP10: =DM10+DO10 -> #DIV/0! | DQ10: 12169 | DR10: 17053 | DT10: 705 | DU10: 2400 | DV10: =DQ10*VLOOKUP(DQ$1,emissions!$A$2:$B$5,2,FALSE) -> 1776674 | DW10: =DR10*VLOOKUP(DR$1,emissions!$A$2:$B$5,2,FALSE) -> 2489738 | DY10: =DT10*VLOOKUP(DT$1,emissions!$A$2:$B$5,2,FALSE) -> 102225 | DZ10: =DU10*VLOOKUP(DU$1,emissions!$A$2:$B$5,2,FALSE) -> 271200 | EA10: =SUM(DV10:DZ10) -> 4639837 | EB10: =1/(SUM(DQ10:DU10)/EA10) -> 143.52823 | ED10: =SUM(EE10:ER10) -> #DIV/0! | EE10: =cost!$B$2*BK10 -> #DIV/0! | EF10: =cost!$B$3*BL10 -> #DIV/0! | EH10: =cost!$B$4*BN10 -> #DIV/0! | EI10: =cost!$B$5*$BO$2 -> #DIV/0! | EJ10: =BP10*(cost!$D$3*production!$B$4+production!$C$4*cost!$D$4+cost!$D$5*production!$D$4+production!$E$4*cost!$D$6) -> #DIV/0! | EK10: =BQ10*(cost!$D$3*production!$B$4+production!$C$4*cost!$D$4+cost!$D$5*production!$D$4+production!$E$4*cost!$D$6) -> #DIV/0! | EL10: =BR10*(cost!$D$8*production!$B$6+cost!$D$9*production!$C$6+$D$10*production!$D$6) -> #DIV/0! | EM10: =BS10*(cost!$D$12*production!$B$8+cost!$D$13*production!$C$8+cost!$D$14*production!$D$8) -> #DIV/0! | EN10: =BT10*(cost!$D$16*production!$B$10+production!$C$10*cost!$D$17) -> #DIV/0! | EO10: =BU10*(cost!$D$19*production!$B$12+production!$C$12*cost!$D$20+cost!$D$21*production!$D$12) -> #DIV/0! | EP10: =BV10*(cost!$D$23*production!$B$14+production!$C$14*cost!$D$24+cost!$D$25*production!$D$14) -> #DIV/0! | EQ10: =BW10*(cost!$D$27*production!$B$16+production!$C$16*cost!$D$28+cost!$D$29*production!$D$16) -> #DIV/0! | ER10: =BX10*(re!$H$10*re!$C$10+re!$H$11*re!$C$11+re!$H$12*re!$C$12+re!$H$13*re!$C$13+re!$H$14*re!$C$14) -> #DIV/0!
A11: HFO-LFO | B11: 0.3 | C11: 5 | G11: 2034 | H11: ='2'!AB17+'6'!AB17+'7'!AB17+'9'!AB17+'11'!AB17+'12'!AB17+'13'!AB17+'16'!AB17+'17'!AB17+'18'!AB17+'22'!AB17 -> 114.56724 | I11: ='1'!AB17+'2'!AC17+'5'!AB17+'6'!AC17+'7'!AC17+'9'!AC17+'11'!AC17+'12'!AC17+'13'!AC17+'15'!AB17+'16'!AC17+'17'!AC17+'18'!AC17+'19'!AB17+'22'!AC17 -> 318.65055 | K11: ='3'!AB17+'4'!AB17+'10'!AB17+'20'!AB17+'21'!AB17+'23'!AB17 -> 16.316318 | L11: ='8'!AB17+'14'!AB17 -> 150.41534 | M11: ='1'!AD17+'2'!AD17+'3'!AD17+'4'!AD17+'5'!AD17+'6'!AD17+'7'!AD17+'8'!AD17+'9'!AD17+'10'!AD17+'11'!AD17+'12'!AD17+'13'!AD17+'14'!AD17+'15'!AD17+'16'!AD17+'17'!AD17+'18'!AD17+'19'!AD17+'20'!AD17+'21'!AD17+'22'!AD17+'23'!AD17 -> 65.523847 | N11: ='1'!AE17+'2'!AE17+'3'!AE17+'4'!AE17+'5'!AE17+'6'!AE17+'7'!AE17+'8'!AE17+'9'!AE17+'10'!AE17+'11'!AE17+'12'!AE17+'13'!AE17+'14'!AE17+'15'!AE17+'16'!AE17+'17'!AE17+'18'!AE17+'19'!AE17+'20'!AE17+'21'!AE17+'22'!AE17+'23'!AE17 -> 3.8850757 | O11: ='1'!AF17+'2'!AF17+'3'!AF17+'4'!AF17+'5'!AF17+'6'!AF17+'7'!AF17+'8'!AF17+'9'!AF17+'10'!AF17+'11'!AF17+'12'!AF17+'13'!AF17+'14'!AF17+'15'!AF17+'16'!AF17+'17'!AF17+'18'!AF17+'19'!AF17+'20'!AF17+'21'!AF17+'22'!AF17+'23'!AF17 -> 125.5285 | P11: ='1'!AG17+'2'!AG17+'3'!AG17+'4'!AG17+'5'!AG17+'6'!AG17+'7'!AG17+'8'!AG17+'9'!AG17+'10'!AG17+'11'!AG17+'12'!AG17+'13'!AG17+'14'!AG17+'15'!AG17+'16'!AG17+'17'!AG17+'18'!AG17+'19'!AG17+'20'!AG17+'21'!AG17+'22'!AG17+'23'!AG17 -> 114.22186 | Q11: ='1'!AH17+'2'!AH17+'3'!AH17+'4'!AH17+'5'!AH17+'6'!AH17+'7'!AH17+'8'!AH17+'9'!AH17+'10'!AH17+'11'!AH17+'12'!AH17+'13'!AH17+'14'!AH17+'15'!AH17+'16'!AH17+'17'!AH17+'18'!AH17+'19'!AH17+'20'!AH17+'21'!AH17+'22'!AH17+'23'!AH17 -> 2.9316811 | R11: ='1'!AI17+'2'!AI17+'3'!AI17+'4'!AI17+'5'!AI17+'6'!AI17+'7'!AI17+'8'!AI17+'9'!AI17+'10'!AI17+'11'!AI17+'12'!AI17+'13'!AI17+'14'!AI17+'15'!AI17+'16'!AI17+'17'!AI17+'18'!AI17+'19'!AI17+'20'!AI17+'21'!AI17+'22'!AI17+'23'!AI17 -> 19.822314 | S11: ='1'!AJ17+'2'!AJ17+'3'!AJ17+'4'!AJ17+'5'!AJ17+'6'!AJ17+'7'!AJ17+'8'!AJ17+'9'!AJ17+'10'!AJ17+'11'!AJ17+'12'!AJ17+'13'!AJ17+'14'!AJ17+'15'!AJ17+'16'!AJ17+'17'!AJ17+'18'!AJ17+'19'!AJ17+'20'!AJ17+'21'!AJ17+'22'!AJ17+'23'!AJ17 -> 5.6143698 | T11: ='1'!AK17+'2'!AK17+'3'!AK17+'4'!AK17+'5'!AK17+'6'!AK17+'7'!AK17+'8'!AK17+'9'!AK17+'10'!AK17+'11'!AK17+'12'!AK17+'13'!AK17+'14'!AK17+'15'!AK17+'16'!AK17+'17'!AK17+'18'!AK17+'19'!AK17+'20'!AK17+'21'!AK17+'22'!AK17+'23'!AK17 -> 62.148729 | U11: ='1'!AL17+'2'!AL17+'3'!AL17+'4'!AL17+'5'!AL17+'6'!AL17+'7'!AL17+'8'!AL17+'9'!AL17+'10'!AL17+'11'!AL17+'12'!AL17+'13'!AL17+'14'!AL17+'15'!AL17+'16'!AL17+'17'!AL17+'18'!AL17+'19'!AL17+'20'!AL17+'21'!AL17+'22'!AL17+'23'!AL17 -> 0.15122463 | V11: =SUM(H11:L11) -> 599.94945 | W11: =SUM(M11:U11) -> 399.8276 | X11: =W11/W10-1 -> 0.38596011 | Y11: =((M11+N11)*re!$D$2/re!$C$2+O11*re!$D$3/re!$C$3+P11*re!$D$4/re!$C$4+T11*re!$D$5/re!$C$5+U11*re!$D$6/re!$C$6) -> 678.53762 | Z11: =SUM(AA11:AE11) -> 52.350488 | AA11: =((Y11*277.8)/(re!$B$10*8760))*re!$C$10 -> 29.680011 | AB11: =((Y11*277.8)/(re!$B$11*8760))*re!$C$11 -> 11.034876 | AC11: =((Y11*277.8)/(re!$B$12*8760))*re!$C$12 -> 3.9848163 | AD11: =((Y11*277.8)/(re!$B$13*8760))*re!$C$13 -> 1.169457 | AE11: =((Y11*277.8)/(re!$B$14*8760))*re!$C$14 -> 6.4813278 | AF11: =SUM('1'!AD17:AL17)+'1'!AA17 -> 155.24239 | AG11: =SUM('2'!AD17:AL17)+'2'!AA17 -> 2.9885757 | AH11: =SUM('3'!AD17:AL17)+'3'!AA17 -> 12.952064 | AI11: =SUM('4'!AD17:AL17)+'4'!AA17 -> 0.97000271 | AJ11: =SUM('5'!AD17:AL17)+'5'!AA17 -> 5.858056 | AK11: =SUM('6'!AD17:AL17)+'6'!AA17 -> 150.17365 | AL11: =SUM('7'!AD17:AL17)+'7'!AA17 -> 133.38688 | AM11: =SUM('8'!AD17:AL17)+'8'!AA17 -> 256.13477 | AN11: =SUM('9'!AD17:AL17)+'9'!AA17 -> 73.143665 | AO11: =SUM('10'!AD17:AL17)+'10'!AA17 -> 5.3354375 | AP11: =SUM('11'!AD17:AL17)+'11'!AA17 -> 6.8654912 | AQ11: =SUM('12'!AD17:AL17)+'12'!AA17 -> 2.1092202 | AR11: =SUM('13'!AD17:AL17)+'13'!AA17 -> 6.1369492 | AS11: =SUM('14'!AD17:AL17)+'14'!AA17 -> 4.990301 | AT11: =SUM('15'!AD17:AL17)+'15'!AA17 -> 64.986173 | AU11: =SUM('16'!AD17:AL17)+'16'!AA17 -> 26.119325 | AV11: =SUM('17'!AD17:AL17)+'17'!AA17 -> 44.452367 | AW11: =SUM('18'!AD17:AL17)+'18'!AA17 -> 11.101062 | AX11: =SUM('19'!AD17:AL17)+'19'!AA17 -> 28.764966 | AY11: =SUM('20'!AD17:AL17)+'20'!AA17 -> 1.8522564 | AZ11: =SUM('21'!AD17:AL17)+'21'!AA17 -> 0.16747054 | BA11: =SUM('22'!AD17:AL17)+'22'!AA17 -> 0.53903715 | BB11: =SUM('23'!AD17:AL17)+'23'!AA17 -> 5.5069427 | BC11: =('1'!D17+'2'!D17+'3'!D17+'4'!D17+'5'!D17+'6'!D17+'7'!D17+'8'!D17+'9'!D17+'10'!D17+'12'!D17+'13'!D17+'14'!D17+'15'!D17+'16'!D17+'17'!D17+'18'!D17+'19'!D17+'20'!D17+'21'!D17+'22'!D17+'23'!D17)/('1'!D16+'2'!D16+'3'!D16+'4'!D16+'5'!D16+'6'!D16+'7'!D16+'8'!D16+'9'!D16+'10'!D16+'12'!D16+'13'!D16+'14'!D16+'15'!D16+'16'!D16+'17'!D16+'18'!D16+'19'!D16+'20'!D16+'21'!D16+'22'!D16+'23'!D16)-1 -> 0.14845277 | BD11: =('1'!E17+'2'!E17+'3'!E17+'4'!E17+'5'!E17+'6'!E17+'7'!E17+'8'!E17+'9'!E17+'10'!E17+'12'!E17+'13'!E17+'14'!E17+'15'!E17+'16'!E17+'17'!E17+'18'!E17+'19'!E17+'20'!E17+'21'!E17+'22'!E17+'23'!E17)/('1'!E16+'2'!E16+'3'!E16+'4'!E16+'5'!E16+'6'!E16+'7'!E16+'8'!E16+'9'!E16+'10'!E16+'12'!E16+'13'!E16+'14'!E16+'15'!E16+'16'!E16+'17'!E16+'18'!E16+'19'!E16+'20'!E16+'21'!E16+'22'!E16+'23'!E16)-1 -> 0.14845277 | BE11: =('1'!F17+'2'!F17+'3'!F17+'4'!F17+'5'!F17+'6'!F17+'7'!F17+'8'!F17+'9'!F17+'10'!F17+'12'!F17+'13'!F17+'14'!F17+'15'!F17+'16'!F17+'17'!F17+'18'!F17+'19'!F17+'20'!F17+'21'!F17+'22'!F17+'23'!F17)/('1'!F16+'2'!F16+'3'!F16+'4'!F16+'5'!F16+'6'!F16+'7'!F16+'8'!F16+'9'!F16+'10'!F16+'12'!F16+'13'!F16+'14'!F16+'15'!F16+'16'!F16+'17'!F16+'18'!F16+'19'!F16+'20'!F16+'21'!F16+'22'!F16+'23'!F16)-1 -> 0.14874943 | BF11: =W11/W10-1 -> 0.38596011 | BG11: 2034 | BH11: 0.26 | BI11: 0.39 | BJ11: =BI11-BH11 -> 0.13 | BK11: ='2 (RU)'!AB17+'6 (RU)'!AB17+'7 (RU)'!AB17+'9 (RU)'!AB17+'11 (RU)'!AB17+'12 (RU)'!AB17+'13 (RU)'!AB17+'16 (RU)'!AB17+'17 (RU)'!AB17+'18 (RU)'!AB17+'22 (RU)'!AB17 -> #DIV/0! | BL11: ='1 (RU)'!AB17+'2 (RU)'!AC17+'5 (RU)'!AB17+'6 (RU)'!AC17+'7 (RU)'!AC17+'9 (RU)'!AC17+'11 (RU)'!AC17+'12 (RU)'!AC17+'13 (RU)'!AC17+'15 (RU)'!AB17+'16 (RU)'!AC17+'17 (RU)'!AC17+'18 (RU)'!AC17+'19 (RU)'!AB17+'22 (RU)'!AC17 -> #DIV/0! | BN11: ='3 (RU)'!AB17+'4 (RU)'!AB17+'10 (RU)'!AB17+'20 (RU)'!AB17+'21 (RU)'!AB17+'23 (RU)'!AB17 -> #DIV/0! | BO11: ='8 (RU)'!AB17+'14 (RU)'!AB17 -> #DIV/0! | BP11: ='1 (RU)'!AD17+'2 (RU)'!AD17+'3 (RU)'!AD17+'4 (RU)'!AD17+'5 (RU)'!AD17+'6 (RU)'!AD17+'7 (RU)'!AD17+'8 (RU)'!AD17+'9 (RU)'!AD17+'10 (RU)'!AD17+'11 (RU)'!AD17+'12 (RU)'!AD17+'13 (RU)'!AD17+'14 (RU)'!AD17+'15 (RU)'!AD17+'16 (RU)'!AD17+'17 (RU)'!AD17+'18 (RU)'!AD17+'19 (RU)'!AD17+'20 (RU)'!AD17+'21 (RU)'!AD17+'22 (RU)'!AD17+'23 (RU)'!AD17 -> #DIV/0! | BQ11: ='1 (RU)'!AE17+'2 (RU)'!AE17+'3 (RU)'!AE17+'4 (RU)'!AE17+'5 (RU)'!AE17+'6 (RU)'!AE17+'7 (RU)'!AE17+'8 (RU)'!AE17+'9 (RU)'!AE17+'10 (RU)'!AE17+'11 (RU)'!AE17+'12 (RU)'!AE17+'13 (RU)'!AE17+'14 (RU)'!AE17+'15 (RU)'!AE17+'16 (RU)'!AE17+'17 (RU)'!AE17+'18 (RU)'!AE17+'19 (RU)'!AE17+'20 (RU)'!AE17+'21 (RU)'!AE17+'22 (RU)'!AE17+'23 (RU)'!AE17 -> #DIV/0! | BR11: ='1 (RU)'!AF17+'2 (RU)'!AF17+'3 (RU)'!AF17+'4 (RU)'!AF17+'5 (RU)'!AF17+'6 (RU)'!AF17+'7 (RU)'!AF17+'8 (RU)'!AF17+'9 (RU)'!AF17+'10 (RU)'!AF17+'11 (RU)'!AF17+'12 (RU)'!AF17+'13 (RU)'!AF17+'14 (RU)'!AF17+'15 (RU)'!AF17+'16 (RU)'!AF17+'17 (RU)'!AF17+'18 (RU)'!AF17+'19 (RU)'!AF17+'20 (RU)'!AF17+'21 (RU)'!AF17+'22 (RU)'!AF17+'23 (RU)'!AF17 -> #DIV/0! | BS11: ='1 (RU)'!AG17+'2 (RU)'!AG17+'3 (RU)'!AG17+'4 (RU)'!AG17+'5 (RU)'!AG17+'6 (RU)'!AG17+'7 (RU)'!AG17+'8 (RU)'!AG17+'9 (RU)'!AG17+'10 (RU)'!AG17+'11 (RU)'!AG17+'12 (RU)'!AG17+'13 (RU)'!AG17+'14 (RU)'!AG17+'15 (RU)'!AG17+'16 (RU)'!AG17+'17 (RU)'!AG17+'18 (RU)'!AG17+'19 (RU)'!AG17+'20 (RU)'!AG17+'21 (RU)'!AG17+'22 (RU)'!AG17+'23 (RU)'!AG17 -> #DIV/0! | BT11: ='1 (RU)'!AH17+'2 (RU)'!AH17+'3 (RU)'!AH17+'4 (RU)'!AH17+'5 (RU)'!AH17+'6 (RU)'!AH17+'7 (RU)'!AH17+'8 (RU)'!AH17+'9 (RU)'!AH17+'10 (RU)'!AH17+'11 (RU)'!AH17+'12 (RU)'!AH17+'13 (RU)'!AH17+'14 (RU)'!AH17+'15 (RU)'!AH17+'16 (RU)'!AH17+'17 (RU)'!AH17+'18 (RU)'!AH17+'19 (RU)'!AH17+'20 (RU)'!AH17+'21 (RU)'!AH17+'22 (RU)'!AH17+'23 (RU)'!AH17 -> #DIV/0! | BU11: ='1 (RU)'!AI17+'2 (RU)'!AI17+'3 (RU)'!AI17+'4 (RU)'!AI17+'5 (RU)'!AI17+'6 (RU)'!AI17+'7 (RU)'!AI17+'8 (RU)'!AI17+'9 (RU)'!AI17+'10 (RU)'!AI17+'11 (RU)'!AI17+'12 (RU)'!AI17+'13 (RU)'!AI17+'14 (RU)'!AI17+'15 (RU)'!AI17+'16 (RU)'!AI17+'17 (RU)'!AI17+'18 (RU)'!AI17+'19 (RU)'!AI17+'20 (RU)'!AI17+'21 (RU)'!AI17+'22 (RU)'!AI17+'23 (RU)'!AI17 -> #DIV/0! | BV11: ='1 (RU)'!AJ17+'2 (RU)'!AJ17+'3 (RU)'!AJ17+'4 (RU)'!AJ17+'5 (RU)'!AJ17+'6 (RU)'!AJ17+'7 (RU)'!AJ17+'8 (RU)'!AJ17+'9 (RU)'!AJ17+'10 (RU)'!AJ17+'11 (RU)'!AJ17+'12 (RU)'!AJ17+'13 (RU)'!AJ17+'14 (RU)'!AJ17+'15 (RU)'!AJ17+'16 (RU)'!AJ17+'17 (RU)'!AJ17+'18 (RU)'!AJ17+'19 (RU)'!AJ17+'20 (RU)'!AJ17+'21 (RU)'!AJ17+'22 (RU)'!AJ17+'23 (RU)'!AJ17 -> #DIV/0! | BW11: ='1 (RU)'!AK17+'2 (RU)'!AK17+'3 (RU)'!AK17+'4 (RU)'!AK17+'5 (RU)'!AK17+'6 (RU)'!AK17+'7 (RU)'!AK17+'8 (RU)'!AK17+'9 (RU)'!AK17+'10 (RU)'!AK17+'11 (RU)'!AK17+'12 (RU)'!AK17+'13 (RU)'!AK17+'14 (RU)'!AK17+'15 (RU)'!AK17+'16 (RU)'!AK17+'17 (RU)'!AK17+'18 (RU)'!AK17+'19 (RU)'!AK17+'20 (RU)'!AK17+'21 (RU)'!AK17+'22 (RU)'!AK17+'23 (RU)'!AK17 -> #DIV/0! | BX11: ='1 (RU)'!AL17+'2 (RU)'!AL17+'3 (RU)'!AL17+'4 (RU)'!AL17+'5 (RU)'!AL17+'6 (RU)'!AL17+'7 (RU)'!AL17+'8 (RU)'!AL17+'9 (RU)'!AL17+'10 (RU)'!AL17+'11 (RU)'!AL17+'12 (RU)'!AL17+'13 (RU)'!AL17+'14 (RU)'!AL17+'15 (RU)'!AL17+'16 (RU)'!AL17+'17 (RU)'!AL17+'18 (RU)'!AL17+'19 (RU)'!AL17+'20 (RU)'!AL17+'21 (RU)'!AL17+'22 (RU)'!AL17+'23 (RU)'!AL17 -> #DIV/0! | BY11: =SUM(BK11:BO11) -> #DIV/0! | BZ11: =SUM(BP11:BX11) -> #DIV/0! | CC11: =VLOOKUP(CC$1,emissions!$A$2:$B$5,2,FALSE)*BK11 -> #DIV/0! | CD11: =VLOOKUP(CD$1,emissions!$A$2:$B$5,2,FALSE)*BL11 -> #DIV/0! | CF11: =VLOOKUP(CF$1,emissions!$A$2:$B$5,2,FALSE)*BN11 -> #DIV/0! | CG11: =VLOOKUP(CG$1,emissions!$A$2:$B$5,2,FALSE)*BO11 -> #DIV/0! | CH11: =BP11*(emissions!$D$3*production!$B$4+emissions!$D$4*production!$C$4+emissions!$D$5*production!$D$4+emissions!$D$6*production!$E$4) -> #DIV/0! | CI11: =BQ11*(emissions!$D$3*production!$B$4+emissions!$D$4*production!$C$4+emissions!$D$5*production!$D$4+emissions!$D$6*production!$E$4) -> #DIV/0! | CJ11: =BR11*(emissions!$D$8*production!$B$6+emissions!$D$9*production!$C$6+emissions!$D$10*production!$D$6) -> #DIV/0! | CK11: =BS11*(emissions!$D$12*production!$B$8+emissions!$D$13*production!$C$8+emissions!$D$14*production!$D$8) -> #DIV/0! | CL11: =BT11*(emissions!$D$16*production!$B$10+production!$C$10*emissions!$D$17) -> #DIV/0! | CM11: =BU11*(emissions!$D$19*production!$B$12+production!$C$12*emissions!$D$20+emissions!$D$21*production!$D$12) -> #DIV/0! | CN11: =BV11*(emissions!$D$23*production!$B$14+production!$C$14*emissions!$D$24+emissions!$D$25*production!$D$14) -> #DIV/0! | CO11: =BW11*(emissions!$D$27*production!$B$16+production!$C$16*emissions!$D$28+production!$D$16*emissions!$D$29) -> #DIV/0! | CP11: 0 | CS11: =SUM(CC11:CP11) -> #DIV/0! | CT11: =SUM(CC11:CP11)/SUM(BK11:BX11) -> #DIV/0! | CU11: =(CT11-CW11) -> #DIV/0! | CV11: =CT11-CX11 -> #DIV/0! | CW11: =93.3*(1-BH11) -> 69.042 | CX11: =93.3*(1-BI11) -> 56.913 | CY11: =IF(G11<2028,0,IF(CT11>=CW11,CU11,IF(AND(CT11<CW11,CT11>=CX11),CV11,0))*SUM(BK11:BX11)) -> #DIV/0! | CZ11: =IF(CT11>=CW11,380*CY11,IF(AND(CT11<CW11,CT11>=CX11),100*CY11,0)) -> #DIV/0! | DA11: =IF(G11<2028,"",IF(CT11>=CW11,"Red",IF(AND(CT11<CW11,CT11>=CX11),"Yellow","Green"))) -> #DIV/0! | DB11: =IF(G11<2028,0,IF(CT11<CX11,-CV11*SUM(BK11:BX11),0)) -> #DIV/0! | DC11: =DB11*380 -> #DIV/0! | DD11: 2034 | DE11: =CY11-DB11 -> #DIV/0! | DF11: =CS11 -> #DIV/0! | DG11: 2034 | DH11: =CW11*SUM(BK11:BX11) -> #DIV/0! | DI11: =CX11*SUM(BK11:BX11) -> #DIV/0! | DJ11: =DI11 -> #DIV/0! | DK11: =DH11-DI11 -> #DIV/0! | DL11: =MAX(DH11:DK11) -> #DIV/0! | DM11: =(CZ11-DC11)/1000000 -> #DIV/0! | DN11: =DE11/1000000 -> #DIV/0! | DO11: =ED11/1000000 -> #DIV/0! | DP11: =DM11+DO11 -> #DIV/0! | DQ11: 10805 | DR11: 18944 | DT11: 719 | DU11: 2448 | DV11: =DQ11*VLOOKUP(DQ$1,emissions!$A$2:$B$5,2,FALSE) -> 1577530 | DW11: =DR11*VLOOKUP(DR$1,emissions!$A$2:$B$5,2,FALSE) -> 2765824 | DY11: =DT11*VLOOKUP(DT$1,emissions!$A$2:$B$5,2,FALSE) -> 104255 | DZ11: =DU11*VLOOKUP(DU$1,emissions!$A$2:$B$5,2,FALSE) -> 276624 | EA11: =SUM(DV11:DZ11) -> 4724233 | EB11: =1/(SUM(DQ11:DU11)/EA11) -> 143.52391 | ED11: =SUM(EE11:ER11) -> #DIV/0! | EE11: =cost!$B$2*BK11 -> #DIV/0! | EF11: =cost!$B$3*BL11 -> #DIV/0! | EH11: =cost!$B$4*BN11 -> #DIV/0! | EI11: =cost!$B$5*$BO$2 -> #DIV/0! | EJ11: =BP11*(cost!$D$3*production!$B$4+production!$C$4*cost!$D$4+cost!$D$5*production!$D$4+production!$E$4*cost!$D$6) -> #DIV/0! | EK11: =BQ11*(cost!$D$3*production!$B$4+production!$C$4*cost!$D$4+cost!$D$5*production!$D$4+production!$E$4*cost!$D$6) -> #DIV/0! | EL11: =BR11*(cost!$D$8*production!$B$6+cost!$D$9*production!$C$6+$D$10*production!$D$6) -> #DIV/0! | EM11: =BS11*(cost!$D$12*production!$B$8+cost!$D$13*production!$C$8+cost!$D$14*production!$D$8) -> #DIV/0! | EN11: =BT11*(cost!$D$16*production!$B$10+production!$C$10*cost!$D$17) -> #DIV/0! | EO11: =BU11*(cost!$D$19*production!$B$12+production!$C$12*cost!$D$20+cost!$D$21*production!$D$12) -> #DIV/0! | EP11: =BV11*(cost!$D$23*production!$B$14+production!$C$14*cost!$D$24+cost!$D$25*production!$D$14) -> #DIV/0! | EQ11: =BW11*(cost!$D$27*production!$B$16+production!$C$16*cost!$D$28+cost!$D$29*production!$D$16) -> #DIV/0! | ER11: =BX11*(re!$H$10*re!$C$10+re!$H$11*re!$C$11+re!$H$12*re!$C$12+re!$H$13*re!$C$13+re!$H$14*re!$C$14) -> #DIV/0!
A12: MDO-MGO | B12: 0 | C12: 3 | D12: disabled | G12: 2035 | H12: ='2'!AB18+'6'!AB18+'7'!AB18+'9'!AB18+'11'!AB18+'12'!AB18+'13'!AB18+'16'!AB18+'17'!AB18+'18'!AB18+'22'!AB18 -> 84.480622 | I12: ='1'!AB18+'2'!AC18+'5'!AB18+'6'!AC18+'7'!AC18+'9'!AC18+'11'!AC18+'12'!AC18+'13'!AC18+'15'!AB18+'16'!AC18+'17'!AC18+'18'!AC18+'19'!AB18+'22'!AC18 -> 278.00953 | K12: ='3'!AB18+'4'!AB18+'10'!AB18+'20'!AB18+'21'!AB18+'23'!AB18 -> 13.683181 | L12: ='8'!AB18+'14'!AB18 -> 126.11315 | M12: ='1'!AD18+'2'!AD18+'3'!AD18+'4'!AD18+'5'!AD18+'6'!AD18+'7'!AD18+'8'!AD18+'9'!AD18+'10'!AD18+'11'!AD18+'12'!AD18+'13'!AD18+'14'!AD18+'15'!AD18+'16'!AD18+'17'!AD18+'18'!AD18+'19'!AD18+'20'!AD18+'21'!AD18+'22'!AD18+'23'!AD18 -> 86.251485 | N12: ='1'!AE18+'2'!AE18+'3'!AE18+'4'!AE18+'5'!AE18+'6'!AE18+'7'!AE18+'8'!AE18+'9'!AE18+'10'!AE18+'11'!AE18+'12'!AE18+'13'!AE18+'14'!AE18+'15'!AE18+'16'!AE18+'17'!AE18+'18'!AE18+'19'!AE18+'20'!AE18+'21'!AE18+'22'!AE18+'23'!AE18 -> 5.1139476 | O12: ='1'!AF18+'2'!AF18+'3'!AF18+'4'!AF18+'5'!AF18+'6'!AF18+'7'!AF18+'8'!AF18+'9'!AF18+'10'!AF18+'11'!AF18+'12'!AF18+'13'!AF18+'14'!AF18+'15'!AF18+'16'!AF18+'17'!AF18+'18'!AF18+'19'!AF18+'20'!AF18+'21'!AF18+'22'!AF18+'23'!AF18 -> 165.22893 | P12: ='1'!AG18+'2'!AG18+'3'!AG18+'4'!AG18+'5'!AG18+'6'!AG18+'7'!AG18+'8'!AG18+'9'!AG18+'10'!AG18+'11'!AG18+'12'!AG18+'13'!AG18+'14'!AG18+'15'!AG18+'16'!AG18+'17'!AG18+'18'!AG18+'19'!AG18+'20'!AG18+'21'!AG18+'22'!AG18+'23'!AG18 -> 150.36136 | Q12: ='1'!AH18+'2'!AH18+'3'!AH18+'4'!AH18+'5'!AH18+'6'!AH18+'7'!AH18+'8'!AH18+'9'!AH18+'10'!AH18+'11'!AH18+'12'!AH18+'13'!AH18+'14'!AH18+'15'!AH18+'16'!AH18+'17'!AH18+'18'!AH18+'19'!AH18+'20'!AH18+'21'!AH18+'22'!AH18+'23'!AH18 -> 3.8549622 | R12: ='1'!AI18+'2'!AI18+'3'!AI18+'4'!AI18+'5'!AI18+'6'!AI18+'7'!AI18+'8'!AI18+'9'!AI18+'10'!AI18+'11'!AI18+'12'!AI18+'13'!AI18+'14'!AI18+'15'!AI18+'16'!AI18+'17'!AI18+'18'!AI18+'19'!AI18+'20'!AI18+'21'!AI18+'22'!AI18+'23'!AI18 -> 26.093315 | S12: ='1'!AJ18+'2'!AJ18+'3'!AJ18+'4'!AJ18+'5'!AJ18+'6'!AJ18+'7'!AJ18+'8'!AJ18+'9'!AJ18+'10'!AJ18+'11'!AJ18+'12'!AJ18+'13'!AJ18+'14'!AJ18+'15'!AJ18+'16'!AJ18+'17'!AJ18+'18'!AJ18+'19'!AJ18+'20'!AJ18+'21'!AJ18+'22'!AJ18+'23'!AJ18 -> 7.3828678 | T12: ='1'!AK18+'2'!AK18+'3'!AK18+'4'!AK18+'5'!AK18+'6'!AK18+'7'!AK18+'8'!AK18+'9'!AK18+'10'!AK18+'11'!AK18+'12'!AK18+'13'!AK18+'14'!AK18+'15'!AK18+'16'!AK18+'17'!AK18+'18'!AK18+'19'!AK18+'20'!AK18+'21'!AK18+'22'!AK18+'23'!AK18 -> 81.829758 | U12: ='1'!AL18+'2'!AL18+'3'!AL18+'4'!AL18+'5'!AL18+'6'!AL18+'7'!AL18+'8'!AL18+'9'!AL18+'10'!AL18+'11'!AL18+'12'!AL18+'13'!AL18+'14'!AL18+'15'!AL18+'16'!AL18+'17'!AL18+'18'!AL18+'19'!AL18+'20'!AL18+'21'!AL18+'22'!AL18+'23'!AL18 -> 0.19935274 | V12: =SUM(H12:L12) -> 502.28648 | W12: =SUM(M12:U12) -> 526.31597 | X12: =W12/W11-1 -> 0.31635729 | Y12: =((M12+N12)*re!$D$2/re!$C$2+O12*re!$D$3/re!$C$3+P12*re!$D$4/re!$C$4+T12*re!$D$5/re!$C$5+U12*re!$D$6/re!$C$6) -> 893.21521 | Z12: =SUM(AA12:AE12) -> 68.913279 | AA12: =((Y12*277.8)/(re!$B$10*8760))*re!$C$10 -> 39.070254 | AB12: =((Y12*277.8)/(re!$B$11*8760))*re!$C$11 -> 14.52612 | AC12: =((Y12*277.8)/(re!$B$12*8760))*re!$C$12 -> 5.2455434 | AD12: =((Y12*277.8)/(re!$B$13*8760))*re!$C$13 -> 1.539453 | AE12: =((Y12*277.8)/(re!$B$14*8760))*re!$C$14 -> 8.531908 | AF12: =SUM('1'!AD18:AL18)+'1'!AA18 -> 158.33034 | AG12: =SUM('2'!AD18:AL18)+'2'!AA18 -> 3.0679199 | AH12: =SUM('3'!AD18:AL18)+'3'!AA18 -> 13.294328 | AI12: =SUM('4'!AD18:AL18)+'4'!AA18 -> 0.99737138 | AJ12: =SUM('5'!AD18:AL18)+'5'!AA18 -> 6.0081559 | AK12: =SUM('6'!AD18:AL18)+'6'!AA18 -> 153.67148 | AL12: =SUM('7'!AD18:AL18)+'7'!AA18 -> 136.89812 | AM12: =SUM('8'!AD18:AL18)+'8'!AA18 -> 266.86126 | AN12: =SUM('9'!AD18:AL18)+'9'!AA18 -> 75.017812 | AO12: =SUM('10'!AD18:AL18)+'10'!AA18 -> 5.4491093 | AP12: =SUM('11'!AD18:AL18)+'11'!AA18 -> 7.0485168 | AQ12: =SUM('12'!AD18:AL18)+'12'!AA18 -> 2.1654495 | AR12: =SUM('13'!AD18:AL18)+'13'!AA18 -> 6.3005528 | AS12: =SUM('14'!AD18:AL18)+'14'!AA18 -> 5.1914168 | AT12: =SUM('15'!AD18:AL18)+'15'!AA18 -> 66.651302 | AU12: =SUM('16'!AD18:AL18)+'16'!AA18 -> 26.815635 | AV12: =SUM('17'!AD18:AL18)+'17'!AA18 -> 45.637413 | AW12: =SUM('18'!AD18:AL18)+'18'!AA18 -> 11.397003 | AX12: =SUM('19'!AD18:AL18)+'19'!AA18 -> 29.502006 | AY12: =SUM('20'!AD18:AL18)+'20'!AA18 -> 1.9045179 | AZ12: =SUM('21'!AD18:AL18)+'21'!AA18 -> 0.17202197 | BA12: =SUM('22'!AD18:AL18)+'22'!AA18 -> 0.5528488 | BB12: =SUM('23'!AD18:AL18)+'23'!AA18 -> 5.667871 | BC12: =('1'!D18+'2'!D18+'3'!D18+'4'!D18+'5'!D18+'6'!D18+'7'!D18+'8'!D18+'9'!D18+'10'!D18+'12'!D18+'13'!D18+'14'!D18+'15'!D18+'16'!D18+'17'!D18+'18'!D18+'19'!D18+'20'!D18+'21'!D18+'22'!D18+'23'!D18)/('1'!D17+'2'!D17+'3'!D17+'4'!D17+'5'!D17+'6'!D17+'7'!D17+'8'!D17+'9'!D17+'10'!D17+'12'!D17+'13'!D17+'14'!D17+'15'!D17+'16'!D17+'17'!D17+'18'!D17+'19'!D17+'20'!D17+'21'!D17+'22'!D17+'23'!D17)-1 -> 0.13410483 | BD12: =('1'!E18+'2'!E18+'3'!E18+'4'!E18+'5'!E18+'6'!E18+'7'!E18+'8'!E18+'9'!E18+'10'!E18+'12'!E18+'13'!E18+'14'!E18+'15'!E18+'16'!E18+'17'!E18+'18'!E18+'19'!E18+'20'!E18+'21'!E18+'22'!E18+'23'!E18)/('1'!E17+'2'!E17+'3'!E17+'4'!E17+'5'!E17+'6'!E17+'7'!E17+'8'!E17+'9'!E17+'10'!E17+'12'!E17+'13'!E17+'14'!E17+'15'!E17+'16'!E17+'17'!E17+'18'!E17+'19'!E17+'20'!E17+'21'!E17+'22'!E17+'23'!E17)-1 -> 0.13410483 | BE12: =('1'!F18+'2'!F18+'3'!F18+'4'!F18+'5'!F18+'6'!F18+'7'!F18+'8'!F18+'9'!F18+'10'!F18+'12'!F18+'13'!F18+'14'!F18+'15'!F18+'16'!F18+'17'!F18+'18'!F18+'19'!F18+'20'!F18+'21'!F18+'22'!F18+'23'!F18)/('1'!F17+'2'!F17+'3'!F17+'4'!F17+'5'!F17+'6'!F17+'7'!F17+'8'!F17+'9'!F17+'10'!F17+'12'!F17+'13'!F17+'14'!F17+'15'!F17+'16'!F17+'17'!F17+'18'!F17+'19'!F17+'20'!F17+'21'!F17+'22'!F17+'23'!F17)-1 -> 0.13454843 | BF12: =W12/W11-1 -> 0.31635729 | BG12: 2035 | BH12: 0.3 | BI12: 0.43 | BJ12: =BI12-BH12 -> 0.13 | BK12: ='2 (RU)'!AB18+'6 (RU)'!AB18+'7 (RU)'!AB18+'9 (RU)'!AB18+'11 (RU)'!AB18+'12 (RU)'!AB18+'13 (RU)'!AB18+'16 (RU)'!AB18+'17 (RU)'!AB18+'18 (RU)'!AB18+'22 (RU)'!AB18 -> #DIV/0! | BL12: ='1 (RU)'!AB18+'2 (RU)'!AC18+'5 (RU)'!AB18+'6 (RU)'!AC18+'7 (RU)'!AC18+'9 (RU)'!AC18+'11 (RU)'!AC18+'12 (RU)'!AC18+'13 (RU)'!AC18+'15 (RU)'!AB18+'16 (RU)'!AC18+'17 (RU)'!AC18+'18 (RU)'!AC18+'19 (RU)'!AB18+'22 (RU)'!AC18 -> #DIV/0! | BN12: ='3 (RU)'!AB18+'4 (RU)'!AB18+'10 (RU)'!AB18+'20 (RU)'!AB18+'21 (RU)'!AB18+'23 (RU)'!AB18 -> #DIV/0! | BO12: ='8 (RU)'!AB18+'14 (RU)'!AB18 -> #DIV/0! | BP12: ='1 (RU)'!AD18+'2 (RU)'!AD18+'3 (RU)'!AD18+'4 (RU)'!AD18+'5 (RU)'!AD18+'6 (RU)'!AD18+'7 (RU)'!AD18+'8 (RU)'!AD18+'9 (RU)'!AD18+'10 (RU)'!AD18+'11 (RU)'!AD18+'12 (RU)'!AD18+'13 (RU)'!AD18+'14 (RU)'!AD18+'15 (RU)'!AD18+'16 (RU)'!AD18+'17 (RU)'!AD18+'18 (RU)'!AD18+'19 (RU)'!AD18+'20 (RU)'!AD18+'21 (RU)'!AD18+'22 (RU)'!AD18+'23 (RU)'!AD18 -> #DIV/0! | BQ12: ='1 (RU)'!AE18+'2 (RU)'!AE18+'3 (RU)'!AE18+'4 (RU)'!AE18+'5 (RU)'!AE18+'6 (RU)'!AE18+'7 (RU)'!AE18+'8 (RU)'!AE18+'9 (RU)'!AE18+'10 (RU)'!AE18+'11 (RU)'!AE18+'12 (RU)'!AE18+'13 (RU)'!AE18+'14 (RU)'!AE18+'15 (RU)'!AE18+'16 (RU)'!AE18+'17 (RU)'!AE18+'18 (RU)'!AE18+'19 (RU)'!AE18+'20 (RU)'!AE18+'21 (RU)'!AE18+'22 (RU)'!AE18+'23 (RU)'!AE18 -> #DIV/0! | BR12: ='1 (RU)'!AF18+'2 (RU)'!AF18+'3 (RU)'!AF18+'4 (RU)'!AF18+'5 (RU)'!AF18+'6 (RU)'!AF18+'7 (RU)'!AF18+'8 (RU)'!AF18+'9 (RU)'!AF18+'10 (RU)'!AF18+'11 (RU)'!AF18+'12 (RU)'!AF18+'13 (RU)'!AF18+'14 (RU)'!AF18+'15 (RU)'!AF18+'16 (RU)'!AF18+'17 (RU)'!AF18+'18 (RU)'!AF18+'19 (RU)'!AF18+'20 (RU)'!AF18+'21 (RU)'!AF18+'22 (RU)'!AF18+'23 (RU)'!AF18 -> #DIV/0! | BS12: ='1 (RU)'!AG18+'2 (RU)'!AG18+'3 (RU)'!AG18+'4 (RU)'!AG18+'5 (RU)'!AG18+'6 (RU)'!AG18+'7 (RU)'!AG18+'8 (RU)'!AG18+'9 (RU)'!AG18+'10 (RU)'!AG18+'11 (RU)'!AG18+'12 (RU)'!AG18+'13 (RU)'!AG18+'14 (RU)'!AG18+'15 (RU)'!AG18+'16 (RU)'!AG18+'17 (RU)'!AG18+'18 (RU)'!AG18+'19 (RU)'!AG18+'20 (RU)'!AG18+'21 (RU)'!AG18+'22 (RU)'!AG18+'23 (RU)'!AG18 -> #DIV/0! | BT12: ='1 (RU)'!AH18+'2 (RU)'!AH18+'3 (RU)'!AH18+'4 (RU)'!AH18+'5 (RU)'!AH18+'6 (RU)'!AH18+'7 (RU)'!AH18+'8 (RU)'!AH18+'9 (RU)'!AH18+'10 (RU)'!AH18+'11 (RU)'!AH18+'12 (RU)'!AH18+'13 (RU)'!AH18+'14 (RU)'!AH18+'15 (RU)'!AH18+'16 (RU)'!AH18+'17 (RU)'!AH18+'18 (RU)'!AH18+'19 (RU)'!AH18+'20 (RU)'!AH18+'21 (RU)'!AH18+'22 (RU)'!AH18+'23 (RU)'!AH18 -> #DIV/0! | BU12: ='1 (RU)'!AI18+'2 (RU)'!AI18+'3 (RU)'!AI18+'4 (RU)'!AI18+'5 (RU)'!AI18+'6 (RU)'!AI18+'7 (RU)'!AI18+'8 (RU)'!AI18+'9 (RU)'!AI18+'10 (RU)'!AI18+'11 (RU)'!AI18+'12 (RU)'!AI18+'13 (RU)'!AI18+'14 (RU)'!AI18+'15 (RU)'!AI18+'16 (RU)'!AI18+'17 (RU)'!AI18+'18 (RU)'!AI18+'19 (RU)'!AI18+'20 (RU)'!AI18+'21 (RU)'!AI18+'22 (RU)'!AI18+'23 (RU)'!AI18 -> #DIV/0! | BV12: ='1 (RU)'!AJ18+'2 (RU)'!AJ18+'3 (RU)'!AJ18+'4 (RU)'!AJ18+'5 (RU)'!AJ18+'6 (RU)'!AJ18+'7 (RU)'!AJ18+'8 (RU)'!AJ18+'9 (RU)'!AJ18+'10 (RU)'!AJ18+'11 (RU)'!AJ18+'12 (RU)'!AJ18+'13 (RU)'!AJ18+'14 (RU)'!AJ18+'15 (RU)'!AJ18+'16 (RU)'!AJ18+'17 (RU)'!AJ18+'18 (RU)'!AJ18+'19 (RU)'!AJ18+'20 (RU)'!AJ18+'21 (RU)'!AJ18+'22 (RU)'!AJ18+'23 (RU)'!AJ18 -> #DIV/0! | BW12: ='1 (RU)'!AK18+'2 (RU)'!AK18+'3 (RU)'!AK18+'4 (RU)'!AK18+'5 (RU)'!AK18+'6 (RU)'!AK18+'7 (RU)'!AK18+'8 (RU)'!AK18+'9 (RU)'!AK18+'10 (RU)'!AK18+'11 (RU)'!AK18+'12 (RU)'!AK18+'13 (RU)'!AK18+'14 (RU)'!AK18+'15 (RU)'!AK18+'16 (RU)'!AK18+'17 (RU)'!AK18+'18 (RU)'!AK18+'19 (RU)'!AK18+'20 (RU)'!AK18+'21 (RU)'!AK18+'22 (RU)'!AK18+'23 (RU)'!AK18 -> #DIV/0! | BX12: ='1 (RU)'!AL18+'2 (RU)'!AL18+'3 (RU)'!AL18+'4 (RU)'!AL18+'5 (RU)'!AL18+'6 (RU)'!AL18+'7 (RU)'!AL18+'8 (RU)'!AL18+'9 (RU)'!AL18+'10 (RU)'!AL18+'11 (RU)'!AL18+'12 (RU)'!AL18+'13 (RU)'!AL18+'14 (RU)'!AL18+'15 (RU)'!AL18+'16 (RU)'!AL18+'17 (RU)'!AL18+'18 (RU)'!AL18+'19 (RU)'!AL18+'20 (RU)'!AL18+'21 (RU)'!AL18+'22 (RU)'!AL18+'23 (RU)'!AL18 -> #DIV/0! | BY12: =SUM(BK12:BO12) -> #DIV/0! | BZ12: =SUM(BP12:BX12) -> #DIV/0! | CC12: =VLOOKUP(CC$1,emissions!$A$2:$B$5,2,FALSE)*BK12 -> #DIV/0! | CD12: =VLOOKUP(CD$1,emissions!$A$2:$B$5,2,FALSE)*BL12 -> #DIV/0! | CF12: =VLOOKUP(CF$1,emissions!$A$2:$B$5,2,FALSE)*BN12 -> #DIV/0! | CG12: =VLOOKUP(CG$1,emissions!$A$2:$B$5,2,FALSE)*BO12 -> #DIV/0! | CH12: =BP12*(emissions!$D$3*production!$B$4+emissions!$D$4*production!$C$4+emissions!$D$5*production!$D$4+emissions!$D$6*production!$E$4) -> #DIV/0! | CI12: =BQ12*(emissions!$D$3*production!$B$4+emissions!$D$4*production!$C$4+emissions!$D$5*production!$D$4+emissions!$D$6*production!$E$4) -> #DIV/0! | CJ12: =BR12*(emissions!$D$8*production!$B$6+emissions!$D$9*production!$C$6+emissions!$D$10*production!$D$6) -> #DIV/0! | CK12: =BS12*(emissions!$D$12*production!$B$8+emissions!$D$13*production!$C$8+emissions!$D$14*production!$D$8) -> #DIV/0! | CL12: =BT12*(emissions!$D$16*production!$B$10+production!$C$10*emissions!$D$17) -> #DIV/0! | CM12: =BU12*(emissions!$D$19*production!$B$12+production!$C$12*emissions!$D$20+emissions!$D$21*production!$D$12) -> #DIV/0! | CN12: =BV12*(emissions!$D$23*production!$B$14+production!$C$14*emissions!$D$24+emissions!$D$25*production!$D$14) -> #DIV/0! | CO12: =BW12*(emissions!$D$27*production!$B$16+production!$C$16*emissions!$D$28+production!$D$16*emissions!$D$29) -> #DIV/0! | CP12: 0 | CS12: =SUM(CC12:CP12) -> #DIV/0! | CT12: =SUM(CC12:CP12)/SUM(BK12:BX12) -> #DIV/0! | CU12: =(CT12-CW12) -> #DIV/0! | CV12: =CT12-CX12 -> #DIV/0! | CW12: =93.3*(1-BH12) -> 65.31 | CX12: =93.3*(1-BI12) -> 53.181 | CY12: =IF(G12<2028,0,IF(CT12>=CW12,CU12,IF(AND(CT12<CW12,CT12>=CX12),CV12,0))*SUM(BK12:BX12)) -> #DIV/0! | CZ12: =IF(CT12>=CW12,380*CY12,IF(AND(CT12<CW12,CT12>=CX12),100*CY12,0)) -> #DIV/0! | DA12: =IF(G12<2028,"",IF(CT12>=CW12,"Red",IF(AND(CT12<CW12,CT12>=CX12),"Yellow","Green"))) -> #DIV/0! | DB12: =IF(G12<2028,0,IF(CT12<CX12,-CV12*SUM(BK12:BX12),0)) -> #DIV/0! | DC12: =DB12*380 -> #DIV/0! | DD12: 2035 | DE12: =CY12-DB12 -> #DIV/0! | DF12: =CS12 -> #DIV/0! | DG12: 2035 | DH12: =CW12*SUM(BK12:BX12) -> #DIV/0! | DI12: =CX12*SUM(BK12:BX12) -> #DIV/0! | DJ12: =DI12 -> #DIV/0! | DK12: =DH12-DI12 -> #DIV/0! | DL12: =MAX(DH12:DK12) -> #DIV/0! | DM12: =(CZ12-DC12)/1000000 -> #DIV/0! | DN12: =DE12/1000000 -> #DIV/0! | DO12: =ED12/1000000 -> #DIV/0! | DP12: =DM12+DO12 -> #DIV/0! | DQ12: 9458 | DR12: 20827 | DT12: 733 | DU12: 2497 | DV12: =DQ12*VLOOKUP(DQ$1,emissions!$A$2:$B$5,2,FALSE) -> 1380868 | DW12: =DR12*VLOOKUP(DR$1,emissions!$A$2:$B$5,2,FALSE) -> 3040742 | DY12: =DT12*VLOOKUP(DT$1,emissions!$A$2:$B$5,2,FALSE) -> 106285 | DZ12: =DU12*VLOOKUP(DU$1,emissions!$A$2:$B$5,2,FALSE) -> 282161 | EA12: =SUM(DV12:DZ12) -> 4810056 | EB12: =1/(SUM(DQ12:DU12)/EA12) -> 143.5195 | ED12: =SUM(EE12:ER12) -> #DIV/0! | EE12: =cost!$B$2*BK12 -> #DIV/0! | EF12: =cost!$B$3*BL12 -> #DIV/0! | EH12: =cost!$B$4*BN12 -> #DIV/0! | EI12: =cost!$B$5*$BO$2 -> #DIV/0! | EJ12: =BP12*(cost!$D$3*production!$B$4+production!$C$4*cost!$D$4+cost!$D$5*production!$D$4+production!$E$4*cost!$D$6) -> #DIV/0! | EK12: =BQ12*(cost!$D$3*production!$B$4+production!$C$4*cost!$D$4+cost!$D$5*production!$D$4+production!$E$4*cost!$D$6) -> #DIV/0! | EL12: =BR12*(cost!$D$8*production!$B$6+cost!$D$9*production!$C$6+$D$10*production!$D$6) -> #DIV/0! | EM12: =BS12*(cost!$D$12*production!$B$8+cost!$D$13*production!$C$8+cost!$D$14*production!$D$8) -> #DIV/0! | EN12: =BT12*(cost!$D$16*production!$B$10+production!$C$10*cost!$D$17) -> #DIV/0! | EO12: =BU12*(cost!$D$19*production!$B$12+production!$C$12*cost!$D$20+cost!$D$21*production!$D$12) -> #DIV/0! | EP12: =BV12*(cost!$D$23*production!$B$14+production!$C$14*cost!$D$24+cost!$D$25*production!$D$14) -> #DIV/0! | EQ12: =BW12*(cost!$D$27*production!$B$16+production!$C$16*cost!$D$28+cost!$D$29*production!$D$16) -> #DIV/0! | ER12: =BX12*(re!$H$10*re!$C$10+re!$H$11*re!$C$11+re!$H$12*re!$C$12+re!$H$13*re!$C$13+re!$H$14*re!$C$14) -> #DIV/0!
B13: adjusted logistic growth function - k, t0 | G13: 2036 | H13: ='2'!AB19+'6'!AB19+'7'!AB19+'9'!AB19+'11'!AB19+'12'!AB19+'13'!AB19+'16'!AB19+'17'!AB19+'18'!AB19+'22'!AB19 -> 59.866259 | I13: ='1'!AB19+'2'!AC19+'5'!AB19+'6'!AC19+'7'!AC19+'9'!AC19+'11'!AC19+'12'!AC19+'13'!AC19+'15'!AB19+'16'!AC19+'17'!AC19+'18'!AC19+'19'!AB19+'22'!AC19 -> 229.22428 | K13: ='3'!AB19+'4'!AB19+'10'!AB19+'20'!AB19+'21'!AB19+'23'!AB19 -> 10.937034 | L13: ='8'!AB19+'14'!AB19 -> 100.78043 | M13: ='1'!AD19+'2'!AD19+'3'!AD19+'4'!AD19+'5'!AD19+'6'!AD19+'7'!AD19+'8'!AD19+'9'!AD19+'10'!AD19+'11'!AD19+'12'!AD19+'13'!AD19+'14'!AD19+'15'!AD19+'16'!AD19+'17'!AD19+'18'!AD19+'19'!AD19+'20'!AD19+'21'!AD19+'22'!AD19+'23'!AD19 -> 107.72452 | N13: ='1'!AE19+'2'!AE19+'3'!AE19+'4'!AE19+'5'!AE19+'6'!AE19+'7'!AE19+'8'!AE19+'9'!AE19+'10'!AE19+'11'!AE19+'12'!AE19+'13'!AE19+'14'!AE19+'15'!AE19+'16'!AE19+'17'!AE19+'18'!AE19+'19'!AE19+'20'!AE19+'21'!AE19+'22'!AE19+'23'!AE19 -> 6.3869454 | O13: ='1'!AF19+'2'!AF19+'3'!AF19+'4'!AF19+'5'!AF19+'6'!AF19+'7'!AF19+'8'!AF19+'9'!AF19+'10'!AF19+'11'!AF19+'12'!AF19+'13'!AF19+'14'!AF19+'15'!AF19+'16'!AF19+'17'!AF19+'18'!AF19+'19'!AF19+'20'!AF19+'21'!AF19+'22'!AF19+'23'!AF19 -> 206.35281 | P13: ='1'!AG19+'2'!AG19+'3'!AG19+'4'!AG19+'5'!AG19+'6'!AG19+'7'!AG19+'8'!AG19+'9'!AG19+'10'!AG19+'11'!AG19+'12'!AG19+'13'!AG19+'14'!AG19+'15'!AG19+'16'!AG19+'17'!AG19+'18'!AG19+'19'!AG19+'20'!AG19+'21'!AG19+'22'!AG19+'23'!AG19 -> 187.8037 | Q13: ='1'!AH19+'2'!AH19+'3'!AH19+'4'!AH19+'5'!AH19+'6'!AH19+'7'!AH19+'8'!AH19+'9'!AH19+'10'!AH19+'11'!AH19+'12'!AH19+'13'!AH19+'14'!AH19+'15'!AH19+'16'!AH19+'17'!AH19+'18'!AH19+'19'!AH19+'20'!AH19+'21'!AH19+'22'!AH19+'23'!AH19 -> 4.8095424 | R13: ='1'!AI19+'2'!AI19+'3'!AI19+'4'!AI19+'5'!AI19+'6'!AI19+'7'!AI19+'8'!AI19+'9'!AI19+'10'!AI19+'11'!AI19+'12'!AI19+'13'!AI19+'14'!AI19+'15'!AI19+'16'!AI19+'17'!AI19+'18'!AI19+'19'!AI19+'20'!AI19+'21'!AI19+'22'!AI19+'23'!AI19 -> 32.590038 | S13: ='1'!AJ19+'2'!AJ19+'3'!AJ19+'4'!AJ19+'5'!AJ19+'6'!AJ19+'7'!AJ19+'8'!AJ19+'9'!AJ19+'10'!AJ19+'11'!AJ19+'12'!AJ19+'13'!AJ19+'14'!AJ19+'15'!AJ19+'16'!AJ19+'17'!AJ19+'18'!AJ19+'19'!AJ19+'20'!AJ19+'21'!AJ19+'22'!AJ19+'23'!AJ19 -> 9.211481 | T13: ='1'!AK19+'2'!AK19+'3'!AK19+'4'!AK19+'5'!AK19+'6'!AK19+'7'!AK19+'8'!AK19+'9'!AK19+'10'!AK19+'11'!AK19+'12'!AK19+'13'!AK19+'14'!AK19+'15'!AK19+'16'!AK19+'17'!AK19+'18'!AK19+'19'!AK19+'20'!AK19+'21'!AK19+'22'!AK19+'23'!AK19 -> 102.22826 | U13: ='1'!AL19+'2'!AL19+'3'!AL19+'4'!AL19+'5'!AL19+'6'!AL19+'7'!AL19+'8'!AL19+'9'!AL19+'10'!AL19+'11'!AL19+'12'!AL19+'13'!AL19+'14'!AL19+'15'!AL19+'16'!AL19+'17'!AL19+'18'!AL19+'19'!AL19+'20'!AL19+'21'!AL19+'22'!AL19+'23'!AL19 -> 0.24934581 | V13: =SUM(H13:L13) -> 400.808 | W13: =SUM(M13:U13) -> 657.35665 | X13: =W13/W12-1 -> 0.24897719 | Y13: =((M13+N13)*re!$D$2/re!$C$2+O13*re!$D$3/re!$C$3+P13*re!$D$4/re!$C$4+T13*re!$D$5/re!$C$5+U13*re!$D$6/re!$C$6) -> 1115.6271 | Z13: =SUM(AA13:AE13) -> 86.072782 | AA13: =((Y13*277.8)/(re!$B$10*8760))*re!$C$10 -> 48.798803 | AB13: =((Y13*277.8)/(re!$B$11*8760))*re!$C$11 -> 18.143145 | AC13: =((Y13*277.8)/(re!$B$12*8760))*re!$C$12 -> 6.5516911 | AD13: =((Y13*277.8)/(re!$B$13*8760))*re!$C$13 -> 1.9227789 | AE13: =((Y13*277.8)/(re!$B$14*8760))*re!$C$14 -> 10.656365 | AF13: =SUM('1'!AD19:AL19)+'1'!AA19 -> 161.47963 | AG13: =SUM('2'!AD19:AL19)+'2'!AA19 -> 3.1491263 | AH13: =SUM('3'!AD19:AL19)+'3'!AA19 -> 13.645118 | AI13: =SUM('4'!AD19:AL19)+'4'!AA19 -> 1.0254481 | AJ13: =SUM('5'!AD19:AL19)+'5'!AA19 -> 6.1617166 | AK13: =SUM('6'!AD19:AL19)+'6'!AA19 -> 157.24584 | AL13: =SUM('7'!AD19:AL19)+'7'!AA19 -> 140.49141 | AM13: =SUM('8'!AD19:AL19)+'8'!AA19 -> 277.9147 | AN13: =SUM('9'!AD19:AL19)+'9'!AA19 -> 76.935171 | AO13: =SUM('10'!AD19:AL19)+'10'!AA19 -> 5.5652007 | AP13: =SUM('11'!AD19:AL19)+'11'!AA19 -> 7.2359768 | AQ13: =SUM('12'!AD19:AL19)+'12'!AA19 -> 2.223041 | AR13: =SUM('13'!AD19:AL19)+'13'!AA19 -> 6.4681202 | AS13: =SUM('14'!AD19:AL19)+'14'!AA19 -> 5.3982692 | AT13: =SUM('15'!AD19:AL19)+'15'!AA19 -> 68.354823 | AU13: =SUM('16'!AD19:AL19)+'16'!AA19 -> 27.528814 | AV13: =SUM('17'!AD19:AL19)+'17'!AA19 -> 46.85117 | AW13: =SUM('18'!AD19:AL19)+'18'!AA19 -> 11.700114 | AX13: =SUM('19'!AD19:AL19)+'19'!AA19 -> 30.256039 | AY13: =SUM('20'!AD19:AL19)+'20'!AA19 -> 1.9581314 | AZ13: =SUM('21'!AD19:AL19)+'21'!AA19 -> 0.17668586 | BA13: =SUM('22'!AD19:AL19)+'22'!AA19 -> 0.56697891 | BB13: =SUM('23'!AD19:AL19)+'23'!AA19 -> 5.8331297 | BC13: =('1'!D19+'2'!D19+'3'!D19+'4'!D19+'5'!D19+'6'!D19+'7'!D19+'8'!D19+'9'!D19+'10'!D19+'12'!D19+'13'!D19+'14'!D19+'15'!D19+'16'!D19+'17'!D19+'18'!D19+'19'!D19+'20'!D19+'21'!D19+'22'!D19+'23'!D19)/('1'!D18+'2'!D18+'3'!D18+'4'!D18+'5'!D18+'6'!D18+'7'!D18+'8'!D18+'9'!D18+'10'!D18+'12'!D18+'13'!D18+'14'!D18+'15'!D18+'16'!D18+'17'!D18+'18'!D18+'19'!D18+'20'!D18+'21'!D18+'22'!D18+'23'!D18)-1 -> 0.12259643 | BD13: =('1'!E19+'2'!E19+'3'!E19+'4'!E19+'5'!E19+'6'!E19+'7'!E19+'8'!E19+'9'!E19+'10'!E19+'12'!E19+'13'!E19+'14'!E19+'15'!E19+'16'!E19+'17'!E19+'18'!E19+'19'!E19+'20'!E19+'21'!E19+'22'!E19+'23'!E19)/('1'!E18+'2'!E18+'3'!E18+'4'!E18+'5'!E18+'6'!E18+'7'!E18+'8'!E18+'9'!E18+'10'!E18+'12'!E18+'13'!E18+'14'!E18+'15'!E18+'16'!E18+'17'!E18+'18'!E18+'19'!E18+'20'!E18+'21'!E18+'22'!E18+'23'!E18)-1 -> 0.12259643 | BE13: =('1'!F19+'2'!F19+'3'!F19+'4'!F19+'5'!F19+'6'!F19+'7'!F19+'8'!F19+'9'!F19+'10'!F19+'12'!F19+'13'!F19+'14'!F19+'15'!F19+'16'!F19+'17'!F19+'18'!F19+'19'!F19+'20'!F19+'21'!F19+'22'!F19+'23'!F19)/('1'!F18+'2'!F18+'3'!F18+'4'!F18+'5'!F18+'6'!F18+'7'!F18+'8'!F18+'9'!F18+'10'!F18+'12'!F18+'13'!F18+'14'!F18+'15'!F18+'16'!F18+'17'!F18+'18'!F18+'19'!F18+'20'!F18+'21'!F18+'22'!F18+'23'!F18)-1 -> 0.12318422 | BF13: =W13/W12-1 -> 0.24897719 | BG13: 2036 | BH13: =BH12+($BH$17-$BH$12)/5 -> 0.37 | BI13: =BH13+$BJ$5 -> 0.5 | BJ13: =BI13-BH13 -> 0.13 | BK13: ='2 (RU)'!AB19+'6 (RU)'!AB19+'7 (RU)'!AB19+'9 (RU)'!AB19+'11 (RU)'!AB19+'12 (RU)'!AB19+'13 (RU)'!AB19+'16 (RU)'!AB19+'17 (RU)'!AB19+'18 (RU)'!AB19+'22 (RU)'!AB19 -> #DIV/0! | BL13: ='1 (RU)'!AB19+'2 (RU)'!AC19+'5 (RU)'!AB19+'6 (RU)'!AC19+'7 (RU)'!AC19+'9 (RU)'!AC19+'11 (RU)'!AC19+'12 (RU)'!AC19+'13 (RU)'!AC19+'15 (RU)'!AB19+'16 (RU)'!AC19+'17 (RU)'!AC19+'18 (RU)'!AC19+'19 (RU)'!AB19+'22 (RU)'!AC19 -> #DIV/0! | BN13: ='3 (RU)'!AB19+'4 (RU)'!AB19+'10 (RU)'!AB19+'20 (RU)'!AB19+'21 (RU)'!AB19+'23 (RU)'!AB19 -> #DIV/0! | BO13: ='8 (RU)'!AB19+'14 (RU)'!AB19 -> #DIV/0! | BP13: ='1 (RU)'!AD19+'2 (RU)'!AD19+'3 (RU)'!AD19+'4 (RU)'!AD19+'5 (RU)'!AD19+'6 (RU)'!AD19+'7 (RU)'!AD19+'8 (RU)'!AD19+'9 (RU)'!AD19+'10 (RU)'!AD19+'11 (RU)'!AD19+'12 (RU)'!AD19+'13 (RU)'!AD19+'14 (RU)'!AD19+'15 (RU)'!AD19+'16 (RU)'!AD19+'17 (RU)'!AD19+'18 (RU)'!AD19+'19 (RU)'!AD19+'20 (RU)'!AD19+'21 (RU)'!AD19+'22 (RU)'!AD19+'23 (RU)'!AD19 -> #DIV/0! | BQ13: ='1 (RU)'!AE19+'2 (RU)'!AE19+'3 (RU)'!AE19+'4 (RU)'!AE19+'5 (RU)'!AE19+'6 (RU)'!AE19+'7 (RU)'!AE19+'8 (RU)'!AE19+'9 (RU)'!AE19+'10 (RU)'!AE19+'11 (RU)'!AE19+'12 (RU)'!AE19+'13 (RU)'!AE19+'14 (RU)'!AE19+'15 (RU)'!AE19+'16 (RU)'!AE19+'17 (RU)'!AE19+'18 (RU)'!AE19+'19 (RU)'!AE19+'20 (RU)'!AE19+'21 (RU)'!AE19+'22 (RU)'!AE19+'23 (RU)'!AE19 -> #DIV/0! | BR13: ='1 (RU)'!AF19+'2 (RU)'!AF19+'3 (RU)'!AF19+'4 (RU)'!AF19+'5 (RU)'!AF19+'6 (RU)'!AF19+'7 (RU)'!AF19+'8 (RU)'!AF19+'9 (RU)'!AF19+'10 (RU)'!AF19+'11 (RU)'!AF19+'12 (RU)'!AF19+'13 (RU)'!AF19+'14 (RU)'!AF19+'15 (RU)'!AF19+'16 (RU)'!AF19+'17 (RU)'!AF19+'18 (RU)'!AF19+'19 (RU)'!AF19+'20 (RU)'!AF19+'21 (RU)'!AF19+'22 (RU)'!AF19+'23 (RU)'!AF19 -> #DIV/0! | BS13: ='1 (RU)'!AG19+'2 (RU)'!AG19+'3 (RU)'!AG19+'4 (RU)'!AG19+'5 (RU)'!AG19+'6 (RU)'!AG19+'7 (RU)'!AG19+'8 (RU)'!AG19+'9 (RU)'!AG19+'10 (RU)'!AG19+'11 (RU)'!AG19+'12 (RU)'!AG19+'13 (RU)'!AG19+'14 (RU)'!AG19+'15 (RU)'!AG19+'16 (RU)'!AG19+'17 (RU)'!AG19+'18 (RU)'!AG19+'19 (RU)'!AG19+'20 (RU)'!AG19+'21 (RU)'!AG19+'22 (RU)'!AG19+'23 (RU)'!AG19 -> #DIV/0! | BT13: ='1 (RU)'!AH19+'2 (RU)'!AH19+'3 (RU)'!AH19+'4 (RU)'!AH19+'5 (RU)'!AH19+'6 (RU)'!AH19+'7 (RU)'!AH19+'8 (RU)'!AH19+'9 (RU)'!AH19+'10 (RU)'!AH19+'11 (RU)'!AH19+'12 (RU)'!AH19+'13 (RU)'!AH19+'14 (RU)'!AH19+'15 (RU)'!AH19+'16 (RU)'!AH19+'17 (RU)'!AH19+'18 (RU)'!AH19+'19 (RU)'!AH19+'20 (RU)'!AH19+'21 (RU)'!AH19+'22 (RU)'!AH19+'23 (RU)'!AH19 -> #DIV/0! | BU13: ='1 (RU)'!AI19+'2 (RU)'!AI19+'3 (RU)'!AI19+'4 (RU)'!AI19+'5 (RU)'!AI19+'6 (RU)'!AI19+'7 (RU)'!AI19+'8 (RU)'!AI19+'9 (RU)'!AI19+'10 (RU)'!AI19+'11 (RU)'!AI19+'12 (RU)'!AI19+'13 (RU)'!AI19+'14 (RU)'!AI19+'15 (RU)'!AI19+'16 (RU)'!AI19+'17 (RU)'!AI19+'18 (RU)'!AI19+'19 (RU)'!AI19+'20 (RU)'!AI19+'21 (RU)'!AI19+'22 (RU)'!AI19+'23 (RU)'!AI19 -> #DIV/0! | BV13: ='1 (RU)'!AJ19+'2 (RU)'!AJ19+'3 (RU)'!AJ19+'4 (RU)'!AJ19+'5 (RU)'!AJ19+'6 (RU)'!AJ19+'7 (RU)'!AJ19+'8 (RU)'!AJ19+'9 (RU)'!AJ19+'10 (RU)'!AJ19+'11 (RU)'!AJ19+'12 (RU)'!AJ19+'13 (RU)'!AJ19+'14 (RU)'!AJ19+'15 (RU)'!AJ19+'16 (RU)'!AJ19+'17 (RU)'!AJ19+'18 (RU)'!AJ19+'19 (RU)'!AJ19+'20 (RU)'!AJ19+'21 (RU)'!AJ19+'22 (RU)'!AJ19+'23 (RU)'!AJ19 -> #DIV/0! | BW13: ='1 (RU)'!AK19+'2 (RU)'!AK19+'3 (RU)'!AK19+'4 (RU)'!AK19+'5 (RU)'!AK19+'6 (RU)'!AK19+'7 (RU)'!AK19+'8 (RU)'!AK19+'9 (RU)'!AK19+'10 (RU)'!AK19+'11 (RU)'!AK19+'12 (RU)'!AK19+'13 (RU)'!AK19+'14 (RU)'!AK19+'15 (RU)'!AK19+'16 (RU)'!AK19+'17 (RU)'!AK19+'18 (RU)'!AK19+'19 (RU)'!AK19+'20 (RU)'!AK19+'21 (RU)'!AK19+'22 (RU)'!AK19+'23 (RU)'!AK19 -> #DIV/0! | BX13: ='1 (RU)'!AL19+'2 (RU)'!AL19+'3 (RU)'!AL19+'4 (RU)'!AL19+'5 (RU)'!AL19+'6 (RU)'!AL19+'7 (RU)'!AL19+'8 (RU)'!AL19+'9 (RU)'!AL19+'10 (RU)'!AL19+'11 (RU)'!AL19+'12 (RU)'!AL19+'13 (RU)'!AL19+'14 (RU)'!AL19+'15 (RU)'!AL19+'16 (RU)'!AL19+'17 (RU)'!AL19+'18 (RU)'!AL19+'19 (RU)'!AL19+'20 (RU)'!AL19+'21 (RU)'!AL19+'22 (RU)'!AL19+'23 (RU)'!AL19 -> #DIV/0! | BY13: =SUM(BK13:BO13) -> #DIV/0! | BZ13: =SUM(BP13:BX13) -> #DIV/0! | CC13: =VLOOKUP(CC$1,emissions!$A$2:$B$5,2,FALSE)*BK13 -> #DIV/0! | CD13: =VLOOKUP(CD$1,emissions!$A$2:$B$5,2,FALSE)*BL13 -> #DIV/0! | CF13: =VLOOKUP(CF$1,emissions!$A$2:$B$5,2,FALSE)*BN13 -> #DIV/0! | CG13: =VLOOKUP(CG$1,emissions!$A$2:$B$5,2,FALSE)*BO13 -> #DIV/0! | CH13: =BP13*(emissions!$D$3*production!$B$4+emissions!$D$4*production!$C$4+emissions!$D$5*production!$D$4+emissions!$D$6*production!$E$4) -> #DIV/0! | CI13: =BQ13*(emissions!$D$3*production!$B$4+emissions!$D$4*production!$C$4+emissions!$D$5*production!$D$4+emissions!$D$6*production!$E$4) -> #DIV/0! | CJ13: =BR13*(emissions!$D$8*production!$B$6+emissions!$D$9*production!$C$6+emissions!$D$10*production!$D$6) -> #DIV/0! | CK13: =BS13*(emissions!$D$12*production!$B$8+emissions!$D$13*production!$C$8+emissions!$D$14*production!$D$8) -> #DIV/0! | CL13: =BT13*(emissions!$D$16*production!$B$10+production!$C$10*emissions!$D$17) -> #DIV/0! | CM13: =BU13*(emissions!$D$19*production!$B$12+production!$C$12*emissions!$D$20+emissions!$D$21*production!$D$12) -> #DIV/0! | CN13: =BV13*(emissions!$D$23*production!$B$14+production!$C$14*emissions!$D$24+emissions!$D$25*production!$D$14) -> #DIV/0! | CO13: =BW13*(emissions!$D$27*production!$B$16+production!$C$16*emissions!$D$28+production!$D$16*emissions!$D$29) -> #DIV/0! | CP13: 0 | CS13: =SUM(CC13:CP13) -> #DIV/0! | CT13: =SUM(CC13:CP13)/SUM(BK13:BX13) -> #DIV/0! | CU13: =(CT13-CW13) -> #DIV/0! | CV13: =CT13-CX13 -> #DIV/0! | CW13: =93.3*(1-BH13) -> 58.779 | CX13: =93.3*(1-BI13) -> 46.65 | CY13: =IF(G13<2028,0,IF(CT13>=CW13,CU13,IF(AND(CT13<CW13,CT13>=CX13),CV13,0))*SUM(BK13:BX13)) -> #DIV/0! | CZ13: =IF(CT13>=CW13,380*CY13,IF(AND(CT13<CW13,CT13>=CX13),100*CY13,0)) -> #DIV/0! | DA13: =IF(G13<2028,"",IF(CT13>=CW13,"Red",IF(AND(CT13<CW13,CT13>=CX13),"Yellow","Green"))) -> #DIV/0! | DB13: =IF(G13<2028,0,IF(CT13<CX13,-CV13*SUM(BK13:BX13),0)) -> #DIV/0! | DC13: =DB13*380 -> #DIV/0! | DD13: 2036 | DE13: =CY13-DB13 -> #DIV/0! | DF13: =CS13 -> #DIV/0! | DG13: 2036 | DH13: =CW13*SUM(BK13:BX13) -> #DIV/0! | DI13: =CX13*SUM(BK13:BX13) -> #DIV/0! | DJ13: =DI13 -> #DIV/0! | DK13: =DH13-DI13 -> #DIV/0! | DL13: =MAX(DH13:DK13) -> #DIV/0! | DM13: =(CZ13-DC13)/1000000 -> #DIV/0! | DN13: =DE13/1000000 -> #DIV/0! | DO13: =ED13/1000000 -> #DIV/0! | DP13: =DM13+DO13 -> #DIV/0! | DQ13: 8190 | DR13: 22641 | DT13: 748 | DU13: 2546 | DV13: =DQ13*VLOOKUP(DQ$1,emissions!$A$2:$B$5,2,FALSE) -> 1195740 | DW13: =DR13*VLOOKUP(DR$1,emissions!$A$2:$B$5,2,FALSE) -> 3305586 | DY13: =DT13*VLOOKUP(DT$1,emissions!$A$2:$B$5,2,FALSE) -> 108460 | DZ13: =DU13*VLOOKUP(DU$1,emissions!$A$2:$B$5,2,FALSE) -> 287698 | EA13: =SUM(DV13:DZ13) -> 4897484 | EB13: =1/(SUM(DQ13:DU13)/EA13) -> 143.51601 | ED13: =SUM(EE13:ER13) -> #DIV/0! | EE13: =cost!$B$2*BK13 -> #DIV/0! | EF13: =cost!$B$3*BL13 -> #DIV/0! | EH13: =cost!$B$4*BN13 -> #DIV/0! | EI13: =cost!$B$5*$BO$2 -> #DIV/0! | EJ13: =BP13*(cost!$D$3*production!$B$4+production!$C$4*cost!$D$4+cost!$D$5*production!$D$4+production!$E$4*cost!$D$6) -> #DIV/0! | EK13: =BQ13*(cost!$D$3*production!$B$4+production!$C$4*cost!$D$4+cost!$D$5*production!$D$4+production!$E$4*cost!$D$6) -> #DIV/0! | EL13: =BR13*(cost!$D$8*production!$B$6+cost!$D$9*production!$C$6+$D$10*production!$D$6) -> #DIV/0! | EM13: =BS13*(cost!$D$12*production!$B$8+cost!$D$13*production!$C$8+cost!$D$14*production!$D$8) -> #DIV/0! | EN13: =BT13*(cost!$D$16*production!$B$10+production!$C$10*cost!$D$17) -> #DIV/0! | EO13: =BU13*(cost!$D$19*production!$B$12+production!$C$12*cost!$D$20+cost!$D$21*production!$D$12) -> #DIV/0! | EP13: =BV13*(cost!$D$23*production!$B$14+production!$C$14*cost!$D$24+cost!$D$25*production!$D$14) -> #DIV/0! | EQ13: =BW13*(cost!$D$27*production!$B$16+production!$C$16*cost!$D$28+cost!$D$29*production!$D$16) -> #DIV/0! | ER13: =BX13*(re!$H$10*re!$C$10+re!$H$11*re!$C$11+re!$H$12*re!$C$12+re!$H$13*re!$C$13+re!$H$14*re!$C$14) -> #DIV/0!
A14: RESULTS SUMMARY | B14: 2025 | C14: 2050 | D14: 2030 | E14: 2040 | G14: 2037 | H14: ='2'!AB20+'6'!AB20+'7'!AB20+'9'!AB20+'11'!AB20+'12'!AB20+'13'!AB20+'16'!AB20+'17'!AB20+'18'!AB20+'22'!AB20 -> 41.046412 | I14: ='1'!AB20+'2'!AC20+'5'!AB20+'6'!AC20+'7'!AC20+'9'!AC20+'11'!AC20+'12'!AC20+'13'!AC20+'15'!AB20+'16'!AC20+'17'!AC20+'18'!AC20+'19'!AB20+'22'!AC20 -> 179.4915 | K14: ='3'!AB20+'4'!AB20+'10'!AB20+'20'!AB20+'21'!AB20+'23'!AB20 -> 8.3622512 | L14: ='8'!AB20+'14'!AB20 -> 77.037714 | M14: ='1'!AD20+'2'!AD20+'3'!AD20+'4'!AD20+'5'!AD20+'6'!AD20+'7'!AD20+'8'!AD20+'9'!AD20+'10'!AD20+'11'!AD20+'12'!AD20+'13'!AD20+'14'!AD20+'15'!AD20+'16'!AD20+'17'!AD20+'18'!AD20+'19'!AD20+'20'!AD20+'21'!AD20+'22'!AD20+'23'!AD20 -> 128.0738 | N14: ='1'!AE20+'2'!AE20+'3'!AE20+'4'!AE20+'5'!AE20+'6'!AE20+'7'!AE20+'8'!AE20+'9'!AE20+'10'!AE20+'11'!AE20+'12'!AE20+'13'!AE20+'14'!AE20+'15'!AE20+'16'!AE20+'17'!AE20+'18'!AE20+'19'!AE20+'20'!AE20+'21'!AE20+'22'!AE20+'23'!AE20 -> 7.5932412 | O14: ='1'!AF20+'2'!AF20+'3'!AF20+'4'!AF20+'5'!AF20+'6'!AF20+'7'!AF20+'8'!AF20+'9'!AF20+'10'!AF20+'11'!AF20+'12'!AF20+'13'!AF20+'14'!AF20+'15'!AF20+'16'!AF20+'17'!AF20+'18'!AF20+'19'!AF20+'20'!AF20+'21'!AF20+'22'!AF20+'23'!AF20 -> 245.31959 | P14: ='1'!AG20+'2'!AG20+'3'!AG20+'4'!AG20+'5'!AG20+'6'!AG20+'7'!AG20+'8'!AG20+'9'!AG20+'10'!AG20+'11'!AG20+'12'!AG20+'13'!AG20+'14'!AG20+'15'!AG20+'16'!AG20+'17'!AG20+'18'!AG20+'19'!AG20+'20'!AG20+'21'!AG20+'22'!AG20+'23'!AG20 -> 223.29034 | Q14: ='1'!AH20+'2'!AH20+'3'!AH20+'4'!AH20+'5'!AH20+'6'!AH20+'7'!AH20+'8'!AH20+'9'!AH20+'10'!AH20+'11'!AH20+'12'!AH20+'13'!AH20+'14'!AH20+'15'!AH20+'16'!AH20+'17'!AH20+'18'!AH20+'19'!AH20+'20'!AH20+'21'!AH20+'22'!AH20+'23'!AH20 -> 5.7119547 | R14: ='1'!AI20+'2'!AI20+'3'!AI20+'4'!AI20+'5'!AI20+'6'!AI20+'7'!AI20+'8'!AI20+'9'!AI20+'10'!AI20+'11'!AI20+'12'!AI20+'13'!AI20+'14'!AI20+'15'!AI20+'16'!AI20+'17'!AI20+'18'!AI20+'19'!AI20+'20'!AI20+'21'!AI20+'22'!AI20+'23'!AI20 -> 38.747006 | S14: ='1'!AJ20+'2'!AJ20+'3'!AJ20+'4'!AJ20+'5'!AJ20+'6'!AJ20+'7'!AJ20+'8'!AJ20+'9'!AJ20+'10'!AJ20+'11'!AJ20+'12'!AJ20+'13'!AJ20+'14'!AJ20+'15'!AJ20+'16'!AJ20+'17'!AJ20+'18'!AJ20+'19'!AJ20+'20'!AJ20+'21'!AJ20+'22'!AJ20+'23'!AJ20 -> 10.94035 | T14: ='1'!AK20+'2'!AK20+'3'!AK20+'4'!AK20+'5'!AK20+'6'!AK20+'7'!AK20+'8'!AK20+'9'!AK20+'10'!AK20+'11'!AK20+'12'!AK20+'13'!AK20+'14'!AK20+'15'!AK20+'16'!AK20+'17'!AK20+'18'!AK20+'19'!AK20+'20'!AK20+'21'!AK20+'22'!AK20+'23'!AK20 -> 121.57052 | U14: ='1'!AL20+'2'!AL20+'3'!AL20+'4'!AL20+'5'!AL20+'6'!AL20+'7'!AL20+'8'!AL20+'9'!AL20+'10'!AL20+'11'!AL20+'12'!AL20+'13'!AL20+'14'!AL20+'15'!AL20+'16'!AL20+'17'!AL20+'18'!AL20+'19'!AL20+'20'!AL20+'21'!AL20+'22'!AL20+'23'!AL20 -> 0.29687865 | V14: =SUM(H14:L14) -> 305.93788 | W14: =SUM(M14:U14) -> 781.54369 | X14: =W14/W13-1 -> 0.18891881 | Y14: =((M14+N14)*re!$D$2/re!$C$2+O14*re!$D$3/re!$C$3+P14*re!$D$4/re!$C$4+T14*re!$D$5/re!$C$5+U14*re!$D$6/re!$C$6) -> 1326.4158 | Z14: =SUM(AA14:AE14) -> 102.33554 | AA14: =((Y14*277.8)/(re!$B$10*8760))*re!$C$10 -> 58.018942 | AB14: =((Y14*277.8)/(re!$B$11*8760))*re!$C$11 -> 21.571145 | AC14: =((Y14*277.8)/(re!$B$12*8760))*re!$C$12 -> 7.7895802 | AD14: =((Y14*277.8)/(re!$B$13*8760))*re!$C$13 -> 2.2860725 | AE14: =((Y14*277.8)/(re!$B$14*8760))*re!$C$14 -> 12.669799 | AF14: =SUM('1'!AD20:AL20)+'1'!AA20 -> 164.67769 | AG14: =SUM('2'!AD20:AL20)+'2'!AA20 -> 3.2296054 | AH14: =SUM('3'!AD20:AL20)+'3'!AA20 -> 13.996562 | AI14: =SUM('4'!AD20:AL20)+'4'!AA20 -> 1.0534767 | AJ14: =SUM('5'!AD20:AL20)+'5'!AA20 -> 6.3141821 | AK14: =SUM('6'!AD20:AL20)+'6'!AA20 -> 160.81342 | AL14: =SUM('7'!AD20:AL20)+'7'!AA20 -> 144.05408 | AM14: =SUM('8'!AD20:AL20)+'8'!AA20 -> 288.75975 | AN14: =SUM('9'!AD20:AL20)+'9'!AA20 -> 78.838854 | AO14: =SUM('10'!AD20:AL20)+'10'!AA20 -> 5.6830895 | AP14: =SUM('11'!AD20:AL20)+'11'!AA20 -> 7.4225283 | AQ14: =SUM('12'!AD20:AL20)+'12'!AA20 -> 2.2803535 | AR14: =SUM('13'!AD20:AL20)+'13'!AA20 -> 6.6348755 | AS14: =SUM('14'!AD20:AL20)+'14'!AA20 -> 5.6004523 | AT14: =SUM('15'!AD20:AL20)+'15'!AA20 -> 70.046194 | AU14: =SUM('16'!AD20:AL20)+'16'!AA20 -> 28.238538 | AV14: =SUM('17'!AD20:AL20)+'17'!AA20 -> 48.059045 | AW14: =SUM('18'!AD20:AL20)+'18'!AA20 -> 12.001756 | AX14: =SUM('19'!AD20:AL20)+'19'!AA20 -> 31.004694 | AY14: =SUM('20'!AD20:AL20)+'20'!AA20 -> 2.0116531 | AZ14: =SUM('21'!AD20:AL20)+'21'!AA20 -> 0.18133171 | BA14: =SUM('22'!AD20:AL20)+'22'!AA20 -> 0.58100823 | BB14: =SUM('23'!AD20:AL20)+'23'!AA20 -> 5.9984228 | BC14: =('1'!D20+'2'!D20+'3'!D20+'4'!D20+'5'!D20+'6'!D20+'7'!D20+'8'!D20+'9'!D20+'10'!D20+'12'!D20+'13'!D20+'14'!D20+'15'!D20+'16'!D20+'17'!D20+'18'!D20+'19'!D20+'20'!D20+'21'!D20+'22'!D20+'23'!D20)/('1'!D19+'2'!D19+'3'!D19+'4'!D19+'5'!D19+'6'!D19+'7'!D19+'8'!D19+'9'!D19+'10'!D19+'12'!D19+'13'!D19+'14'!D19+'15'!D19+'16'!D19+'17'!D19+'18'!D19+'19'!D19+'20'!D19+'21'!D19+'22'!D19+'23'!D19)-1 -> 0.11315336 | BD14: =('1'!E20+'2'!E20+'3'!E20+'4'!E20+'5'!E20+'6'!E20+'7'!E20+'8'!E20+'9'!E20+'10'!E20+'12'!E20+'13'!E20+'14'!E20+'15'!E20+'16'!E20+'17'!E20+'18'!E20+'19'!E20+'20'!E20+'21'!E20+'22'!E20+'23'!E20)/('1'!E19+'2'!E19+'3'!E19+'4'!E19+'5'!E19+'6'!E19+'7'!E19+'8'!E19+'9'!E19+'10'!E19+'12'!E19+'13'!E19+'14'!E19+'15'!E19+'16'!E19+'17'!E19+'18'!E19+'19'!E19+'20'!E19+'21'!E19+'22'!E19+'23'!E19)-1 -> 0.11315336 | BE14: =('1'!F20+'2'!F20+'3'!F20+'4'!F20+'5'!F20+'6'!F20+'7'!F20+'8'!F20+'9'!F20+'10'!F20+'12'!F20+'13'!F20+'14'!F20+'15'!F20+'16'!F20+'17'!F20+'18'!F20+'19'!F20+'20'!F20+'21'!F20+'22'!F20+'23'!F20)/('1'!F19+'2'!F19+'3'!F19+'4'!F19+'5'!F19+'6'!F19+'7'!F19+'8'!F19+'9'!F19+'10'!F19+'12'!F19+'13'!F19+'14'!F19+'15'!F19+'16'!F19+'17'!F19+'18'!F19+'19'!F19+'20'!F19+'21'!F19+'22'!F19+'23'!F19)-1 -> 0.11388313 | BF14: =W14/W13-1 -> 0.18891881 | BG14: 2037 | BH14: =BH13+($BH$17-$BH$12)/5 -> 0.44 | BI14: =BH14+$BJ$5 -> 0.57 | BJ14: =BI14-BH14 -> 0.13 | BK14: ='2 (RU)'!AB20+'6 (RU)'!AB20+'7 (RU)'!AB20+'9 (RU)'!AB20+'11 (RU)'!AB20+'12 (RU)'!AB20+'13 (RU)'!AB20+'16 (RU)'!AB20+'17 (RU)'!AB20+'18 (RU)'!AB20+'22 (RU)'!AB20 -> #DIV/0! | BL14: ='1 (RU)'!AB20+'2 (RU)'!AC20+'5 (RU)'!AB20+'6 (RU)'!AC20+'7 (RU)'!AC20+'9 (RU)'!AC20+'11 (RU)'!AC20+'12 (RU)'!AC20+'13 (RU)'!AC20+'15 (RU)'!AB20+'16 (RU)'!AC20+'17 (RU)'!AC20+'18 (RU)'!AC20+'19 (RU)'!AB20+'22 (RU)'!AC20 -> #DIV/0! | BN14: ='3 (RU)'!AB20+'4 (RU)'!AB20+'10 (RU)'!AB20+'20 (RU)'!AB20+'21 (RU)'!AB20+'23 (RU)'!AB20 -> #DIV/0! | BO14: ='8 (RU)'!AB20+'14 (RU)'!AB20 -> #DIV/0! | BP14: ='1 (RU)'!AD20+'2 (RU)'!AD20+'3 (RU)'!AD20+'4 (RU)'!AD20+'5 (RU)'!AD20+'6 (RU)'!AD20+'7 (RU)'!AD20+'8 (RU)'!AD20+'9 (RU)'!AD20+'10 (RU)'!AD20+'11 (RU)'!AD20+'12 (RU)'!AD20+'13 (RU)'!AD20+'14 (RU)'!AD20+'15 (RU)'!AD20+'16 (RU)'!AD20+'17 (RU)'!AD20+'18 (RU)'!AD20+'19 (RU)'!AD20+'20 (RU)'!AD20+'21 (RU)'!AD20+'22 (RU)'!AD20+'23 (RU)'!AD20 -> #DIV/0! | BQ14: ='1 (RU)'!AE20+'2 (RU)'!AE20+'3 (RU)'!AE20+'4 (RU)'!AE20+'5 (RU)'!AE20+'6 (RU)'!AE20+'7 (RU)'!AE20+'8 (RU)'!AE20+'9 (RU)'!AE20+'10 (RU)'!AE20+'11 (RU)'!AE20+'12 (RU)'!AE20+'13 (RU)'!AE20+'14 (RU)'!AE20+'15 (RU)'!AE20+'16 (RU)'!AE20+'17 (RU)'!AE20+'18 (RU)'!AE20+'19 (RU)'!AE20+'20 (RU)'!AE20+'21 (RU)'!AE20+'22 (RU)'!AE20+'23 (RU)'!AE20 -> #DIV/0! | BR14: ='1 (RU)'!AF20+'2 (RU)'!AF20+'3 (RU)'!AF20+'4 (RU)'!AF20+'5 (RU)'!AF20+'6 (RU)'!AF20+'7 (RU)'!AF20+'8 (RU)'!AF20+'9 (RU)'!AF20+'10 (RU)'!AF20+'11 (RU)'!AF20+'12 (RU)'!AF20+'13 (RU)'!AF20+'14 (RU)'!AF20+'15 (RU)'!AF20+'16 (RU)'!AF20+'17 (RU)'!AF20+'18 (RU)'!AF20+'19 (RU)'!AF20+'20 (RU)'!AF20+'21 (RU)'!AF20+'22 (RU)'!AF20+'23 (RU)'!AF20 -> #DIV/0! | BS14: ='1 (RU)'!AG20+'2 (RU)'!AG20+'3 (RU)'!AG20+'4 (RU)'!AG20+'5 (RU)'!AG20+'6 (RU)'!AG20+'7 (RU)'!AG20+'8 (RU)'!AG20+'9 (RU)'!AG20+'10 (RU)'!AG20+'11 (RU)'!AG20+'12 (RU)'!AG20+'13 (RU)'!AG20+'14 (RU)'!AG20+'15 (RU)'!AG20+'16 (RU)'!AG20+'17 (RU)'!AG20+'18 (RU)'!AG20+'19 (RU)'!AG20+'20 (RU)'!AG20+'21 (RU)'!AG20+'22 (RU)'!AG20+'23 (RU)'!AG20 -> #DIV/0! | BT14: ='1 (RU)'!AH20+'2 (RU)'!AH20+'3 (RU)'!AH20+'4 (RU)'!AH20+'5 (RU)'!AH20+'6 (RU)'!AH20+'7 (RU)'!AH20+'8 (RU)'!AH20+'9 (RU)'!AH20+'10 (RU)'!AH20+'11 (RU)'!AH20+'12 (RU)'!AH20+'13 (RU)'!AH20+'14 (RU)'!AH20+'15 (RU)'!AH20+'16 (RU)'!AH20+'17 (RU)'!AH20+'18 (RU)'!AH20+'19 (RU)'!AH20+'20 (RU)'!AH20+'21 (RU)'!AH20+'22 (RU)'!AH20+'23 (RU)'!AH20 -> #DIV/0! | BU14: ='1 (RU)'!AI20+'2 (RU)'!AI20+'3 (RU)'!AI20+'4 (RU)'!AI20+'5 (RU)'!AI20+'6 (RU)'!AI20+'7 (RU)'!AI20+'8 (RU)'!AI20+'9 (RU)'!AI20+'10 (RU)'!AI20+'11 (RU)'!AI20+'12 (RU)'!AI20+'13 (RU)'!AI20+'14 (RU)'!AI20+'15 (RU)'!AI20+'16 (RU)'!AI20+'17 (RU)'!AI20+'18 (RU)'!AI20+'19 (RU)'!AI20+'20 (RU)'!AI20+'21 (RU)'!AI20+'22 (RU)'!AI20+'23 (RU)'!AI20 -> #DIV/0! | BV14: ='1 (RU)'!AJ20+'2 (RU)'!AJ20+'3 (RU)'!AJ20+'4 (RU)'!AJ20+'5 (RU)'!AJ20+'6 (RU)'!AJ20+'7 (RU)'!AJ20+'8 (RU)'!AJ20+'9 (RU)'!AJ20+'10 (RU)'!AJ20+'11 (RU)'!AJ20+'12 (RU)'!AJ20+'13 (RU)'!AJ20+'14 (RU)'!AJ20+'15 (RU)'!AJ20+'16 (RU)'!AJ20+'17 (RU)'!AJ20+'18 (RU)'!AJ20+'19 (RU)'!AJ20+'20 (RU)'!AJ20+'21 (RU)'!AJ20+'22 (RU)'!AJ20+'23 (RU)'!AJ20 -> #DIV/0! | BW14: ='1 (RU)'!AK20+'2 (RU)'!AK20+'3 (RU)'!AK20+'4 (RU)'!AK20+'5 (RU)'!AK20+'6 (RU)'!AK20+'7 (RU)'!AK20+'8 (RU)'!AK20+'9 (RU)'!AK20+'10 (RU)'!AK20+'11 (RU)'!AK20+'12 (RU)'!AK20+'13 (RU)'!AK20+'14 (RU)'!AK20+'15 (RU)'!AK20+'16 (RU)'!AK20+'17 (RU)'!AK20+'18 (RU)'!AK20+'19 (RU)'!AK20+'20 (RU)'!AK20+'21 (RU)'!AK20+'22 (RU)'!AK20+'23 (RU)'!AK20 -> #DIV/0! | BX14: ='1 (RU)'!AL20+'2 (RU)'!AL20+'3 (RU)'!AL20+'4 (RU)'!AL20+'5 (RU)'!AL20+'6 (RU)'!AL20+'7 (RU)'!AL20+'8 (RU)'!AL20+'9 (RU)'!AL20+'10 (RU)'!AL20+'11 (RU)'!AL20+'12 (RU)'!AL20+'13 (RU)'!AL20+'14 (RU)'!AL20+'15 (RU)'!AL20+'16 (RU)'!AL20+'17 (RU)'!AL20+'18 (RU)'!AL20+'19 (RU)'!AL20+'20 (RU)'!AL20+'21 (RU)'!AL20+'22 (RU)'!AL20+'23 (RU)'!AL20 -> #DIV/0! | BY14: =SUM(BK14:BO14) -> #DIV/0! | BZ14: =SUM(BP14:BX14) -> #DIV/0! | CC14: =VLOOKUP(CC$1,emissions!$A$2:$B$5,2,FALSE)*BK14 -> #DIV/0! | CD14: =VLOOKUP(CD$1,emissions!$A$2:$B$5,2,FALSE)*BL14 -> #DIV/0! | CF14: =VLOOKUP(CF$1,emissions!$A$2:$B$5,2,FALSE)*BN14 -> #DIV/0! | CG14: =VLOOKUP(CG$1,emissions!$A$2:$B$5,2,FALSE)*BO14 -> #DIV/0! | CH14: =BP14*(emissions!$D$3*production!$B$4+emissions!$D$4*production!$C$4+emissions!$D$5*production!$D$4+emissions!$D$6*production!$E$4) -> #DIV/0! | CI14: =BQ14*(emissions!$D$3*production!$B$4+emissions!$D$4*production!$C$4+emissions!$D$5*production!$D$4+emissions!$D$6*production!$E$4) -> #DIV/0! | CJ14: =BR14*(emissions!$D$8*production!$B$6+emissions!$D$9*production!$C$6+emissions!$D$10*production!$D$6) -> #DIV/0! | CK14: =BS14*(emissions!$D$12*production!$B$8+emissions!$D$13*production!$C$8+emissions!$D$14*production!$D$8) -> #DIV/0! | CL14: =BT14*(emissions!$D$16*production!$B$10+production!$C$10*emissions!$D$17) -> #DIV/0! | CM14: =BU14*(emissions!$D$19*production!$B$12+production!$C$12*emissions!$D$20+emissions!$D$21*production!$D$12) -> #DIV/0! | CN14: =BV14*(emissions!$D$23*production!$B$14+production!$C$14*emissions!$D$24+emissions!$D$25*production!$D$14) -> #DIV/0! | CO14: =BW14*(emissions!$D$27*production!$B$16+production!$C$16*emissions!$D$28+production!$D$16*emissions!$D$29) -> #DIV/0! | CP14: 0 | CS14: =SUM(CC14:CP14) -> #DIV/0! | CT14: =SUM(CC14:CP14)/SUM(BK14:BX14) -> #DIV/0! | CU14: =(CT14-CW14) -> #DIV/0! | CV14: =CT14-CX14 -> #DIV/0! | CW14: =93.3*(1-BH14) -> 52.248 | CX14: =93.3*(1-BI14) -> 40.119 | CY14: =IF(G14<2028,0,IF(CT14>=CW14,CU14,IF(AND(CT14<CW14,CT14>=CX14),CV14,0))*SUM(BK14:BX14)) -> #DIV/0! | CZ14: =IF(CT14>=CW14,380*CY14,IF(AND(CT14<CW14,CT14>=CX14),100*CY14,0)) -> #DIV/0! | DA14: =IF(G14<2028,"",IF(CT14>=CW14,"Red",IF(AND(CT14<CW14,CT14>=CX14),"Yellow","Green"))) -> #DIV/0! | DB14: =IF(G14<2028,0,IF(CT14<CX14,-CV14*SUM(BK14:BX14),0)) -> #DIV/0! | DC14: =DB14*380 -> #DIV/0! | DD14: 2037 | DE14: =CY14-DB14 -> #DIV/0! | DF14: =CS14 -> #DIV/0! | DG14: 2037 | DH14: =CW14*SUM(BK14:BX14) -> #DIV/0! | DI14: =CX14*SUM(BK14:BX14) -> #DIV/0! | DJ14: =DI14 -> #DIV/0! | DK14: =DH14-DI14 -> #DIV/0! | DL14: =MAX(DH14:DK14) -> #DIV/0! | DM14: =(CZ14-DC14)/1000000 -> #DIV/0! | DN14: =DE14/1000000 -> #DIV/0! | DO14: =ED14/1000000 -> #DIV/0! | DP14: =DM14+DO14 -> #DIV/0! | DQ14: 7046 | DR14: 24340 | DT14: 763 | DU14: 2597 | DV14: =DQ14*VLOOKUP(DQ$1,emissions!$A$2:$B$5,2,FALSE) -> 1028716 | DW14: =DR14*VLOOKUP(DR$1,emissions!$A$2:$B$5,2,FALSE) -> 3553640 | DY14: =DT14*VLOOKUP(DT$1,emissions!$A$2:$B$5,2,FALSE) -> 110635 | DZ14: =DU14*VLOOKUP(DU$1,emissions!$A$2:$B$5,2,FALSE) -> 293461 | EA14: =SUM(DV14:DZ14) -> 4986452 | EB14: =1/(SUM(DQ14:DU14)/EA14) -> 143.51154 | ED14: =SUM(EE14:ER14) -> #DIV/0! | EE14: =cost!$B$2*BK14 -> #DIV/0! | EF14: =cost!$B$3*BL14 -> #DIV/0! | EH14: =cost!$B$4*BN14 -> #DIV/0! | EI14: =cost!$B$5*$BO$2 -> #DIV/0! | EJ14: =BP14*(cost!$D$3*production!$B$4+production!$C$4*cost!$D$4+cost!$D$5*production!$D$4+production!$E$4*cost!$D$6) -> #DIV/0! | EK14: =BQ14*(cost!$D$3*production!$B$4+production!$C$4*cost!$D$4+cost!$D$5*production!$D$4+production!$E$4*cost!$D$6) -> #DIV/0! | EL14: =BR14*(cost!$D$8*production!$B$6+cost!$D$9*production!$C$6+$D$10*production!$D$6) -> #DIV/0! | EM14: =BS14*(cost!$D$12*production!$B$8+cost!$D$13*production!$C$8+cost!$D$14*production!$D$8) -> #DIV/0! | EN14: =BT14*(cost!$D$16*production!$B$10+production!$C$10*cost!$D$17) -> #DIV/0! | EO14: =BU14*(cost!$D$19*production!$B$12+production!$C$12*cost!$D$20+cost!$D$21*production!$D$12) -> #DIV/0! | EP14: =BV14*(cost!$D$23*production!$B$14+production!$C$14*cost!$D$24+cost!$D$25*production!$D$14) -> #DIV/0! | EQ14: =BW14*(cost!$D$27*production!$B$16+production!$C$16*cost!$D$28+cost!$D$29*production!$D$16) -> #DIV/0! | ER14: =BX14*(re!$H$10*re!$C$10+re!$H$11*re!$C$11+re!$H$12*re!$C$12+re!$H$13*re!$C$13+re!$H$14*re!$C$14) -> #DIV/0!
A15: Hydrogen | B15: =SUM(M2:N2) -> 0 | C15: =SUM(M27:N27) -> 243.21337 | D15: =SUM(M7:N7) -> 14.380639 | E15: =SUM(M17:N17) -> 183.01863 | G15: 2038 | H15: ='2'!AB21+'6'!AB21+'7'!AB21+'9'!AB21+'11'!AB21+'12'!AB21+'13'!AB21+'16'!AB21+'17'!AB21+'18'!AB21+'22'!AB21 -> 27.50601 | I15: ='1'!AB21+'2'!AC21+'5'!AB21+'6'!AC21+'7'!AC21+'9'!AC21+'11'!AC21+'12'!AC21+'13'!AC21+'15'!AB21+'16'!AC21+'17'!AC21+'18'!AC21+'19'!AB21+'22'!AC21 -> 134.74774 | K15: ='3'!AB21+'4'!AB21+'10'!AB21+'20'!AB21+'21'!AB21+'23'!AB21 -> 6.1660664 | L15: ='8'!AB21+'14'!AB21 -> 56.792637 | M15: ='1'!AD21+'2'!AD21+'3'!AD21+'4'!AD21+'5'!AD21+'6'!AD21+'7'!AD21+'8'!AD21+'9'!AD21+'10'!AD21+'11'!AD21+'12'!AD21+'13'!AD21+'14'!AD21+'15'!AD21+'16'!AD21+'17'!AD21+'18'!AD21+'19'!AD21+'20'!AD21+'21'!AD21+'22'!AD21+'23'!AD21 -> 145.94818 | N15: ='1'!AE21+'2'!AE21+'3'!AE21+'4'!AE21+'5'!AE21+'6'!AE21+'7'!AE21+'8'!AE21+'9'!AE21+'10'!AE21+'11'!AE21+'12'!AE21+'13'!AE21+'14'!AE21+'15'!AE21+'16'!AE21+'17'!AE21+'18'!AE21+'19'!AE21+'20'!AE21+'21'!AE21+'22'!AE21+'23'!AE21 -> 8.6527277 | O15: ='1'!AF21+'2'!AF21+'3'!AF21+'4'!AF21+'5'!AF21+'6'!AF21+'7'!AF21+'8'!AF21+'9'!AF21+'10'!AF21+'11'!AF21+'12'!AF21+'13'!AF21+'14'!AF21+'15'!AF21+'16'!AF21+'17'!AF21+'18'!AF21+'19'!AF21+'20'!AF21+'21'!AF21+'22'!AF21+'23'!AF21 -> 279.54159 | P15: ='1'!AG21+'2'!AG21+'3'!AG21+'4'!AG21+'5'!AG21+'6'!AG21+'7'!AG21+'8'!AG21+'9'!AG21+'10'!AG21+'11'!AG21+'12'!AG21+'13'!AG21+'14'!AG21+'15'!AG21+'16'!AG21+'17'!AG21+'18'!AG21+'19'!AG21+'20'!AG21+'21'!AG21+'22'!AG21+'23'!AG21 -> 254.46524 | Q15: ='1'!AH21+'2'!AH21+'3'!AH21+'4'!AH21+'5'!AH21+'6'!AH21+'7'!AH21+'8'!AH21+'9'!AH21+'10'!AH21+'11'!AH21+'12'!AH21+'13'!AH21+'14'!AH21+'15'!AH21+'16'!AH21+'17'!AH21+'18'!AH21+'19'!AH21+'20'!AH21+'21'!AH21+'22'!AH21+'23'!AH21 -> 6.5021667 | R15: ='1'!AI21+'2'!AI21+'3'!AI21+'4'!AI21+'5'!AI21+'6'!AI21+'7'!AI21+'8'!AI21+'9'!AI21+'10'!AI21+'11'!AI21+'12'!AI21+'13'!AI21+'14'!AI21+'15'!AI21+'16'!AI21+'17'!AI21+'18'!AI21+'19'!AI21+'20'!AI21+'21'!AI21+'22'!AI21+'23'!AI21 -> 44.155417 | S15: ='1'!AJ21+'2'!AJ21+'3'!AJ21+'4'!AJ21+'5'!AJ21+'6'!AJ21+'7'!AJ21+'8'!AJ21+'9'!AJ21+'10'!AJ21+'11'!AJ21+'12'!AJ21+'13'!AJ21+'14'!AJ21+'15'!AJ21+'16'!AJ21+'17'!AJ21+'18'!AJ21+'19'!AJ21+'20'!AJ21+'21'!AJ21+'22'!AJ21+'23'!AJ21 -> 12.454474 | T15: ='1'!AK21+'2'!AK21+'3'!AK21+'4'!AK21+'5'!AK21+'6'!AK21+'7'!AK21+'8'!AK21+'9'!AK21+'10'!AK21+'11'!AK21+'12'!AK21+'13'!AK21+'14'!AK21+'15'!AK21+'16'!AK21+'17'!AK21+'18'!AK21+'19'!AK21+'20'!AK21+'21'!AK21+'22'!AK21+'23'!AK21 -> 138.57282 | U15: ='1'!AL21+'2'!AL21+'3'!AL21+'4'!AL21+'5'!AL21+'6'!AL21+'7'!AL21+'8'!AL21+'9'!AL21+'10'!AL21+'11'!AL21+'12'!AL21+'13'!AL21+'14'!AL21+'15'!AL21+'16'!AL21+'17'!AL21+'18'!AL21+'19'!AL21+'20'!AL21+'21'!AL21+'22'!AL21+'23'!AL21 -> 0.33880322 | V15: =SUM(H15:L15) -> 225.21245 | W15: =SUM(M15:U15) -> 890.63142 | X15: =W15/W14-1 -> 0.13957983 | Y15: =((M15+N15)*re!$D$2/re!$C$2+O15*re!$D$3/re!$C$3+P15*re!$D$4/re!$C$4+T15*re!$D$5/re!$C$5+U15*re!$D$6/re!$C$6) -> 1511.5861 | Z15: =SUM(AA15:AE15) -> 116.62179 | AA15: =((Y15*277.8)/(re!$B$10*8760))*re!$C$10 -> 66.118505 | AB15: =((Y15*277.8)/(re!$B$11*8760))*re!$C$11 -> 24.582521 | AC15: =((Y15*277.8)/(re!$B$12*8760))*re!$C$12 -> 8.8770215 | AD15: =((Y15*277.8)/(re!$B$13*8760))*re!$C$13 -> 2.6052128 | AE15: =((Y15*277.8)/(re!$B$14*8760))*re!$C$14 -> 14.438529 | AF15: =SUM('1'!AD21:AL21)+'1'!AA21 -> 167.91578 | AG15: =SUM('2'!AD21:AL21)+'2'!AA21 -> 3.3075007 | AH15: =SUM('3'!AD21:AL21)+'3'!AA21 -> 14.342964 | AI15: =SUM('4'!AD21:AL21)+'4'!AA21 -> 1.0809094 | AJ15: =SUM('5'!AD21:AL21)+'5'!AA21 -> 6.4622869 | AK15: =SUM('6'!AD21:AL21)+'6'!AA21 -> 164.31461 | AL15: =SUM('7'!AD21:AL21)+'7'!AA21 -> 147.50533 | AM15: =SUM('8'!AD21:AL21)+'8'!AA21 -> 299.00737 | AN15: =SUM('9'!AD21:AL21)+'9'!AA21 -> 80.68809 | AO15: =SUM('10'!AD21:AL21)+'10'!AA21 -> 5.8023362 | AP15: =SUM('11'!AD21:AL21)+'11'!AA21 -> 7.6043258 | AQ15: =SUM('12'!AD21:AL21)+'12'!AA21 -> 2.3362055 | AR15: =SUM('13'!AD21:AL21)+'13'!AA21 -> 6.7973813 | AS15: =SUM('14'!AD21:AL21)+'14'!AA21 -> 5.790457 | AT15: =SUM('15'!AD21:AL21)+'15'!AA21 -> 71.689191 | AU15: =SUM('16'!AD21:AL21)+'16'!AA21 -> 28.930175 | AV15: =SUM('17'!AD21:AL21)+'17'!AA21 -> 49.236139 | AW15: =SUM('18'!AD21:AL21)+'18'!AA21 -> 12.295711 | AX15: =SUM('19'!AD21:AL21)+'19'!AA21 -> 31.731937 | AY15: =SUM('20'!AD21:AL21)+'20'!AA21 -> 2.0640369 | AZ15: =SUM('21'!AD21:AL21)+'21'!AA21 -> 0.18586533 | BA15: =SUM('22'!AD21:AL21)+'22'!AA21 -> 0.5946363 | BB15: =SUM('23'!AD21:AL21)+'23'!AA21 -> 6.1606238 | BC15: =('1'!D21+'2'!D21+'3'!D21+'4'!D21+'5'!D21+'6'!D21+'7'!D21+'8'!D21+'9'!D21+'10'!D21+'12'!D21+'13'!D21+'14'!D21+'15'!D21+'16'!D21+'17'!D21+'18'!D21+'19'!D21+'20'!D21+'21'!D21+'22'!D21+'23'!D21)/('1'!D20+'2'!D20+'3'!D20+'4'!D20+'5'!D20+'6'!D20+'7'!D20+'8'!D20+'9'!D20+'10'!D20+'12'!D20+'13'!D20+'14'!D20+'15'!D20+'16'!D20+'17'!D20+'18'!D20+'19'!D20+'20'!D20+'21'!D20+'22'!D20+'23'!D20)-1 -> 0.10525952 | BD15: =('1'!E21+'2'!E21+'3'!E21+'4'!E21+'5'!E21+'6'!E21+'7'!E21+'8'!E21+'9'!E21+'10'!E21+'12'!E21+'13'!E21+'14'!E21+'15'!E21+'16'!E21+'17'!E21+'18'!E21+'19'!E21+'20'!E21+'21'!E21+'22'!E21+'23'!E21)/('1'!E20+'2'!E20+'3'!E20+'4'!E20+'5'!E20+'6'!E20+'7'!E20+'8'!E20+'9'!E20+'10'!E20+'12'!E20+'13'!E20+'14'!E20+'15'!E20+'16'!E20+'17'!E20+'18'!E20+'19'!E20+'20'!E20+'21'!E20+'22'!E20+'23'!E20)-1 -> 0.10525952 | BE15: =('1'!F21+'2'!F21+'3'!F21+'4'!F21+'5'!F21+'6'!F21+'7'!F21+'8'!F21+'9'!F21+'10'!F21+'12'!F21+'13'!F21+'14'!F21+'15'!F21+'16'!F21+'17'!F21+'18'!F21+'19'!F21+'20'!F21+'21'!F21+'22'!F21+'23'!F21)/('1'!F20+'2'!F20+'3'!F20+'4'!F20+'5'!F20+'6'!F20+'7'!F20+'8'!F20+'9'!F20+'10'!F20+'12'!F20+'13'!F20+'14'!F20+'15'!F20+'16'!F20+'17'!F20+'18'!F20+'19'!F20+'20'!F20+'21'!F20+'22'!F20+'23'!F20)-1 -> 0.10612939 | BF15: =W15/W14-1 -> 0.13957983 | BG15: 2038 | BH15: =BH14+($BH$17-$BH$12)/5 -> 0.51 | BI15: =BH15+$BJ$5 -> 0.64 | BJ15: =BI15-BH15 -> 0.13 | BK15: ='2 (RU)'!AB21+'6 (RU)'!AB21+'7 (RU)'!AB21+'9 (RU)'!AB21+'11 (RU)'!AB21+'12 (RU)'!AB21+'13 (RU)'!AB21+'16 (RU)'!AB21+'17 (RU)'!AB21+'18 (RU)'!AB21+'22 (RU)'!AB21 -> #DIV/0! | BL15: ='1 (RU)'!AB21+'2 (RU)'!AC21+'5 (RU)'!AB21+'6 (RU)'!AC21+'7 (RU)'!AC21+'9 (RU)'!AC21+'11 (RU)'!AC21+'12 (RU)'!AC21+'13 (RU)'!AC21+'15 (RU)'!AB21+'16 (RU)'!AC21+'17 (RU)'!AC21+'18 (RU)'!AC21+'19 (RU)'!AB21+'22 (RU)'!AC21 -> #DIV/0! | BN15: ='3 (RU)'!AB21+'4 (RU)'!AB21+'10 (RU)'!AB21+'20 (RU)'!AB21+'21 (RU)'!AB21+'23 (RU)'!AB21 -> #DIV/0! | BO15: ='8 (RU)'!AB21+'14 (RU)'!AB21 -> #DIV/0! | BP15: ='1 (RU)'!AD21+'2 (RU)'!AD21+'3 (RU)'!AD21+'4 (RU)'!AD21+'5 (RU)'!AD21+'6 (RU)'!AD21+'7 (RU)'!AD21+'8 (RU)'!AD21+'9 (RU)'!AD21+'10 (RU)'!AD21+'11 (RU)'!AD21+'12 (RU)'!AD21+'13 (RU)'!AD21+'14 (RU)'!AD21+'15 (RU)'!AD21+'16 (RU)'!AD21+'17 (RU)'!AD21+'18 (RU)'!AD21+'19 (RU)'!AD21+'20 (RU)'!AD21+'21 (RU)'!AD21+'22 (RU)'!AD21+'23 (RU)'!AD21 -> #DIV/0! | BQ15: ='1 (RU)'!AE21+'2 (RU)'!AE21+'3 (RU)'!AE21+'4 (RU)'!AE21+'5 (RU)'!AE21+'6 (RU)'!AE21+'7 (RU)'!AE21+'8 (RU)'!AE21+'9 (RU)'!AE21+'10 (RU)'!AE21+'11 (RU)'!AE21+'12 (RU)'!AE21+'13 (RU)'!AE21+'14 (RU)'!AE21+'15 (RU)'!AE21+'16 (RU)'!AE21+'17 (RU)'!AE21+'18 (RU)'!AE21+'19 (RU)'!AE21+'20 (RU)'!AE21+'21 (RU)'!AE21+'22 (RU)'!AE21+'23 (RU)'!AE21 -> #DIV/0! | BR15: ='1 (RU)'!AF21+'2 (RU)'!AF21+'3 (RU)'!AF21+'4 (RU)'!AF21+'5 (RU)'!AF21+'6 (RU)'!AF21+'7 (RU)'!AF21+'8 (RU)'!AF21+'9 (RU)'!AF21+'10 (RU)'!AF21+'11 (RU)'!AF21+'12 (RU)'!AF21+'13 (RU)'!AF21+'14 (RU)'!AF21+'15 (RU)'!AF21+'16 (RU)'!AF21+'17 (RU)'!AF21+'18 (RU)'!AF21+'19 (RU)'!AF21+'20 (RU)'!AF21+'21 (RU)'!AF21+'22 (RU)'!AF21+'23 (RU)'!AF21 -> #DIV/0! | BS15: ='1 (RU)'!AG21+'2 (RU)'!AG21+'3 (RU)'!AG21+'4 (RU)'!AG21+'5 (RU)'!AG21+'6 (RU)'!AG21+'7 (RU)'!AG21+'8 (RU)'!AG21+'9 (RU)'!AG21+'10 (RU)'!AG21+'11 (RU)'!AG21+'12 (RU)'!AG21+'13 (RU)'!AG21+'14 (RU)'!AG21+'15 (RU)'!AG21+'16 (RU)'!AG21+'17 (RU)'!AG21+'18 (RU)'!AG21+'19 (RU)'!AG21+'20 (RU)'!AG21+'21 (RU)'!AG21+'22 (RU)'!AG21+'23 (RU)'!AG21 -> #DIV/0! | BT15: ='1 (RU)'!AH21+'2 (RU)'!AH21+'3 (RU)'!AH21+'4 (RU)'!AH21+'5 (RU)'!AH21+'6 (RU)'!AH21+'7 (RU)'!AH21+'8 (RU)'!AH21+'9 (RU)'!AH21+'10 (RU)'!AH21+'11 (RU)'!AH21+'12 (RU)'!AH21+'13 (RU)'!AH21+'14 (RU)'!AH21+'15 (RU)'!AH21+'16 (RU)'!AH21+'17 (RU)'!AH21+'18 (RU)'!AH21+'19 (RU)'!AH21+'20 (RU)'!AH21+'21 (RU)'!AH21+'22 (RU)'!AH21+'23 (RU)'!AH21 -> #DIV/0! | BU15: ='1 (RU)'!AI21+'2 (RU)'!AI21+'3 (RU)'!AI21+'4 (RU)'!AI21+'5 (RU)'!AI21+'6 (RU)'!AI21+'7 (RU)'!AI21+'8 (RU)'!AI21+'9 (RU)'!AI21+'10 (RU)'!AI21+'11 (RU)'!AI21+'12 (RU)'!AI21+'13 (RU)'!AI21+'14 (RU)'!AI21+'15 (RU)'!AI21+'16 (RU)'!AI21+'17 (RU)'!AI21+'18 (RU)'!AI21+'19 (RU)'!AI21+'20 (RU)'!AI21+'21 (RU)'!AI21+'22 (RU)'!AI21+'23 (RU)'!AI21 -> #DIV/0! | BV15: ='1 (RU)'!AJ21+'2 (RU)'!AJ21+'3 (RU)'!AJ21+'4 (RU)'!AJ21+'5 (RU)'!AJ21+'6 (RU)'!AJ21+'7 (RU)'!AJ21+'8 (RU)'!AJ21+'9 (RU)'!AJ21+'10 (RU)'!AJ21+'11 (RU)'!AJ21+'12 (RU)'!AJ21+'13 (RU)'!AJ21+'14 (RU)'!AJ21+'15 (RU)'!AJ21+'16 (RU)'!AJ21+'17 (RU)'!AJ21+'18 (RU)'!AJ21+'19 (RU)'!AJ21+'20 (RU)'!AJ21+'21 (RU)'!AJ21+'22 (RU)'!AJ21+'23 (RU)'!AJ21 -> #DIV/0! | BW15: ='1 (RU)'!AK21+'2 (RU)'!AK21+'3 (RU)'!AK21+'4 (RU)'!AK21+'5 (RU)'!AK21+'6 (RU)'!AK21+'7 (RU)'!AK21+'8 (RU)'!AK21+'9 (RU)'!AK21+'10 (RU)'!AK21+'11 (RU)'!AK21+'12 (RU)'!AK21+'13 (RU)'!AK21+'14 (RU)'!AK21+'15 (RU)'!AK21+'16 (RU)'!AK21+'17 (RU)'!AK21+'18 (RU)'!AK21+'19 (RU)'!AK21+'20 (RU)'!AK21+'21 (RU)'!AK21+'22 (RU)'!AK21+'23 (RU)'!AK21 -> #DIV/0! | BX15: ='1 (RU)'!AL21+'2 (RU)'!AL21+'3 (RU)'!AL21+'4 (RU)'!AL21+'5 (RU)'!AL21+'6 (RU)'!AL21+'7 (RU)'!AL21+'8 (RU)'!AL21+'9 (RU)'!AL21+'10 (RU)'!AL21+'11 (RU)'!AL21+'12 (RU)'!AL21+'13 (RU)'!AL21+'14 (RU)'!AL21+'15 (RU)'!AL21+'16 (RU)'!AL21+'17 (RU)'!AL21+'18 (RU)'!AL21+'19 (RU)'!AL21+'20 (RU)'!AL21+'21 (RU)'!AL21+'22 (RU)'!AL21+'23 (RU)'!AL21 -> #DIV/0! | BY15: =SUM(BK15:BO15) -> #DIV/0! | BZ15: =SUM(BP15:BX15) -> #DIV/0! | CC15: =VLOOKUP(CC$1,emissions!$A$2:$B$5,2,FALSE)*BK15 -> #DIV/0! | CD15: =VLOOKUP(CD$1,emissions!$A$2:$B$5,2,FALSE)*BL15 -> #DIV/0! | CF15: =VLOOKUP(CF$1,emissions!$A$2:$B$5,2,FALSE)*BN15 -> #DIV/0! | CG15: =VLOOKUP(CG$1,emissions!$A$2:$B$5,2,FALSE)*BO15 -> #DIV/0! | CH15: =BP15*(emissions!$D$3*production!$B$4+emissions!$D$4*production!$C$4+emissions!$D$5*production!$D$4+emissions!$D$6*production!$E$4) -> #DIV/0! | CI15: =BQ15*(emissions!$D$3*production!$B$4+emissions!$D$4*production!$C$4+emissions!$D$5*production!$D$4+emissions!$D$6*production!$E$4) -> #DIV/0! | CJ15: =BR15*(emissions!$D$8*production!$B$6+emissions!$D$9*production!$C$6+emissions!$D$10*production!$D$6) -> #DIV/0! | CK15: =BS15*(emissions!$D$12*production!$B$8+emissions!$D$13*production!$C$8+emissions!$D$14*production!$D$8) -> #DIV/0! | CL15: =BT15*(emissions!$D$16*production!$B$10+production!$C$10*emissions!$D$17) -> #DIV/0! | CM15: =BU15*(emissions!$D$19*production!$B$12+production!$C$12*emissions!$D$20+emissions!$D$21*production!$D$12) -> #DIV/0! | CN15: =BV15*(emissions!$D$23*production!$B$14+production!$C$14*emissions!$D$24+emissions!$D$25*production!$D$14) -> #DIV/0! | CO15: =BW15*(emissions!$D$27*production!$B$16+production!$C$16*emissions!$D$28+production!$D$16*emissions!$D$29) -> #DIV/0! | CP15: 0 | CS15: =SUM(CC15:CP15) -> #DIV/0! | CT15: =SUM(CC15:CP15)/SUM(BK15:BX15) -> #DIV/0! | CU15: =(CT15-CW15) -> #DIV/0! | CV15: =CT15-CX15 -> #DIV/0! | CW15: =93.3*(1-BH15) -> 45.717 | CX15: =93.3*(1-BI15) -> 33.588 | CY15: =IF(G15<2028,0,IF(CT15>=CW15,CU15,IF(AND(CT15<CW15,CT15>=CX15),CV15,0))*SUM(BK15:BX15)) -> #DIV/0! | CZ15: =IF(CT15>=CW15,380*CY15,IF(AND(CT15<CW15,CT15>=CX15),100*CY15,0)) -> #DIV/0! | DA15: =IF(G15<2028,"",IF(CT15>=CW15,"Red",IF(AND(CT15<CW15,CT15>=CX15),"Yellow","Green"))) -> #DIV/0! | DB15: =IF(G15<2028,0,IF(CT15<CX15,-CV15*SUM(BK15:BX15),0)) -> #DIV/0! | DC15: =DB15*380 -> #DIV/0! | DD15: 2038 | DE15: =CY15-DB15 -> #DIV/0! | DF15: =CS15 -> #DIV/0! | DG15: 2038 | DH15: =CW15*SUM(BK15:BX15) -> #DIV/0! | DI15: =CX15*SUM(BK15:BX15) -> #DIV/0! | DJ15: =DI15 -> #DIV/0! | DK15: =DH15-DI15 -> #DIV/0! | DL15: =MAX(DH15:DK15) -> #DIV/0! | DM15: =(CZ15-DC15)/1000000 -> #DIV/0! | DN15: =DE15/1000000 -> #DIV/0! | DO15: =ED15/1000000 -> #DIV/0! | DP15: =DM15+DO15 -> #DIV/0! | DQ15: 6054 | DR15: 25899 | DT15: 778 | DU15: 2649 | DV15: =DQ15*VLOOKUP(DQ$1,emissions!$A$2:$B$5,2,FALSE) -> 883884 | DW15: =DR15*VLOOKUP(DR$1,emissions!$A$2:$B$5,2,FALSE) -> 3781254 | DY15: =DT15*VLOOKUP(DT$1,emissions!$A$2:$B$5,2,FALSE) -> 112810 | DZ15: =DU15*VLOOKUP(DU$1,emissions!$A$2:$B$5,2,FALSE) -> 299337 | EA15: =SUM(DV15:DZ15) -> 5077285 | EB15: =1/(SUM(DQ15:DU15)/EA15) -> 143.50721 | ED15: =SUM(EE15:ER15) -> #DIV/0! | EE15: =cost!$B$2*BK15 -> #DIV/0! | EF15: =cost!$B$3*BL15 -> #DIV/0! | EH15: =cost!$B$4*BN15 -> #DIV/0! | EI15: =cost!$B$5*$BO$2 -> #DIV/0! | EJ15: =BP15*(cost!$D$3*production!$B$4+production!$C$4*cost!$D$4+cost!$D$5*production!$D$4+production!$E$4*cost!$D$6) -> #DIV/0! | EK15: =BQ15*(cost!$D$3*production!$B$4+production!$C$4*cost!$D$4+cost!$D$5*production!$D$4+production!$E$4*cost!$D$6) -> #DIV/0! | EL15: =BR15*(cost!$D$8*production!$B$6+cost!$D$9*production!$C$6+$D$10*production!$D$6) -> #DIV/0! | EM15: =BS15*(cost!$D$12*production!$B$8+cost!$D$13*production!$C$8+cost!$D$14*production!$D$8) -> #DIV/0! | EN15: =BT15*(cost!$D$16*production!$B$10+production!$C$10*cost!$D$17) -> #DIV/0! | EO15: =BU15*(cost!$D$19*production!$B$12+production!$C$12*cost!$D$20+cost!$D$21*production!$D$12) -> #DIV/0! | EP15: =BV15*(cost!$D$23*production!$B$14+production!$C$14*cost!$D$24+cost!$D$25*production!$D$14) -> #DIV/0! | EQ15: =BW15*(cost!$D$27*production!$B$16+production!$C$16*cost!$D$28+cost!$D$29*production!$D$16) -> #DIV/0! | ER15: =BX15*(re!$H$10*re!$C$10+re!$H$11*re!$C$11+re!$H$12*re!$C$12+re!$H$13*re!$C$13+re!$H$14*re!$C$14) -> #DIV/0!
